Lab1/Advanced/1-3/Lab1_111062109_Crossbar_4x4_4bit.v
`timescale 1ns/1ps

module Dmux_1x2_4bit(in, a, b, sel);

input [4-1:0] in;
input sel;
output [4-1:0] a, b;
wire nsel;

not notsel(nsel, sel);
and anda1(a[0], in[0], nsel);
and anda2(a[1], in[1], nsel);
and anda3(a[2], in[2], nsel);
and anda4(a[3], in[3], nsel);

and andb1(b[0], in[0], sel);
and andb2(b[1], in[1], sel);
and andb3(b[2], in[2], sel);
and andb4(b[3], in[3], sel);

endmodule

module Mux_2x1_4bit(a, b, sel, f);
    input [4-1:0] a, b;
    input sel;
    output [4-1:0] f;

    wire not_sel;
    wire [4-1:0] newa, newb;
    not n1(not_sel, sel);
    and na1(newa[0], not_sel, a[0]);
    and na2(newa[1], not_sel, a[1]);
    and na3(newa[2], not_sel, a[2]);
    and na4(newa[3], not_sel, a[3]);
    and nb1(newb[0], sel, b[0]);
    and nb2(newb[1], sel, b[1]);
    and nb3(newb[2], sel, b[2]);
    and nb4(newb[3], sel, b[3]);
    or o1(f[0], newa[0], newb[0]);
    or o2(f[1], newa[1], newb[1]);
    or o3(f[2], newa[2], newb[2]);
    or o4(f[3], newa[3], newb[3]);

endmodule

module Crossbar_2x2_4bit(in1, in2, control, out1, out2);
input [4-1:0] in1, in2;
input control;
output [4-1:0] out1, out2;
wire [3:0] temp1, temp2, temp3, temp4;
wire ncontrol;

not notcontrol(ncontrol, control);
Dmux_1x2_4bit d1(.in(in1), .a(temp1), .b(temp2), .sel(control));
Dmux_1x2_4bit d2(.in(in2), .a(temp3), .b(temp4), .sel(ncontrol));

Mux_2x1_4bit m1(.a(temp1), .b(temp3), .sel(control), .f(out1));
Mux_2x1_4bit m2(.a(temp2), .b(temp4), .sel(ncontrol), .f(out2));

endmodule

module Crossbar_4x4_4bit(in1, in2, in3, in4, out1, out2, out3, out4, control);
input [4-1:0] in1, in2, in3, in4;
input [5-1:0] control;
output [4-1:0] out1, out2, out3, out4;

wire [4-1:0] temp1, temp2, temp3, temp4, temp5, temp6;

Crossbar_2x2_4bit c1(.in1(in1), .in2(in2), .control(control[0]), .out1(temp1), .out2(temp2));
Crossbar_2x2_4bit c2(.in1(in3), .in2(in4), .control(control[3]), .out1(temp3), .out2(temp4));
Crossbar_2x2_4bit c3(.in1(temp2), .in2(temp3), .control(control[2]), .out1(temp5), .out2(temp6));
Crossbar_2x2_4bit c4(.in1(temp1), .in2(temp5), .control(control[1]), .out1(out1), .out2(out2));
Crossbar_2x2_4bit c5(.in1(temp6), .in2(temp4), .control(control[4]), .out1(out3), .out2(out4));

endmodule

Lab1/Advanced/1-3/Lab1_111062109_Crossbar_4x4_4bit_t.v
`include "Lab1_111062109_Crossbar_4x4_4bit.v"
`timescale 1ns/1ps

module Crossbar_4x4_4bit_t;
reg [3:0] in1 = 4'b0001;
reg [3:0] in2 = 4'b0011;
reg [3:0] in3 = 4'b0101;
reg [3:0] in4 = 4'b0111;
reg [4:0] ctl = 5'b00000;
wire [3:0] o1, o2, o3, o4;


initial begin
     $dumpfile("Cbar_4x4.vcd");
     $dumpvars(0, Crossbar_4x4_4bit_t);
end

Crossbar_4x4_4bit C1(
    .in1 (in1),
    .in2 (in2),
    .in3 (in3),
    .in4 (in4),
    .control (ctl),
    .out1 (o1),
    .out2 (o2),
    .out3 (o3),
    .out4 (o4)
);

initial begin
    repeat (2 ** 5) begin
        #1 ctl = ctl + 5'b00001;
        in1 = in1 + 4'b1;
        in2 = in2 + 4'b1;
        in3 = in3 + 4'b1;
        in4 = in4 + 4'b1;
    end
    #1 $finish;
end
endmodule

Lab1/Advanced/1-3/Cbar_4x4.vcd
$date
	Mon Sep 25 22:02:29 2023
$end
$version
	Icarus Verilog
$end
$timescale
	1ps
$end
$scope module Crossbar_4x4_4bit_t $end
$var wire 4 ! o4 [3:0] $end
$var wire 4 " o3 [3:0] $end
$var wire 4 # o2 [3:0] $end
$var wire 4 $ o1 [3:0] $end
$var reg 5 % ctl [4:0] $end
$var reg 4 & in1 [3:0] $end
$var reg 4 ' in2 [3:0] $end
$var reg 4 ( in3 [3:0] $end
$var reg 4 ) in4 [3:0] $end
$scope module C1 $end
$var wire 5 * control [4:0] $end
$var wire 4 + in1 [3:0] $end
$var wire 4 , in2 [3:0] $end
$var wire 4 - in3 [3:0] $end
$var wire 4 . in4 [3:0] $end
$var wire 4 / temp6 [3:0] $end
$var wire 4 0 temp5 [3:0] $end
$var wire 4 1 temp4 [3:0] $end
$var wire 4 2 temp3 [3:0] $end
$var wire 4 3 temp2 [3:0] $end
$var wire 4 4 temp1 [3:0] $end
$var wire 4 5 out4 [3:0] $end
$var wire 4 6 out3 [3:0] $end
$var wire 4 7 out2 [3:0] $end
$var wire 4 8 out1 [3:0] $end
$scope module c1 $end
$var wire 1 9 control $end
$var wire 4 : in1 [3:0] $end
$var wire 4 ; in2 [3:0] $end
$var wire 1 < ncontrol $end
$var wire 4 = temp4 [3:0] $end
$var wire 4 > temp3 [3:0] $end
$var wire 4 ? temp2 [3:0] $end
$var wire 4 @ temp1 [3:0] $end
$var wire 4 A out2 [3:0] $end
$var wire 4 B out1 [3:0] $end
$scope module d1 $end
$var wire 4 C in [3:0] $end
$var wire 1 D nsel $end
$var wire 1 9 sel $end
$var wire 4 E b [3:0] $end
$var wire 4 F a [3:0] $end
$upscope $end
$scope module d2 $end
$var wire 4 G in [3:0] $end
$var wire 1 H nsel $end
$var wire 1 < sel $end
$var wire 4 I b [3:0] $end
$var wire 4 J a [3:0] $end
$upscope $end
$scope module m1 $end
$var wire 4 K a [3:0] $end
$var wire 4 L b [3:0] $end
$var wire 1 M not_sel $end
$var wire 1 9 sel $end
$var wire 4 N newb [3:0] $end
$var wire 4 O newa [3:0] $end
$var wire 4 P f [3:0] $end
$upscope $end
$scope module m2 $end
$var wire 4 Q a [3:0] $end
$var wire 4 R b [3:0] $end
$var wire 1 S not_sel $end
$var wire 1 < sel $end
$var wire 4 T newb [3:0] $end
$var wire 4 U newa [3:0] $end
$var wire 4 V f [3:0] $end
$upscope $end
$upscope $end
$scope module c2 $end
$var wire 1 W control $end
$var wire 4 X in1 [3:0] $end
$var wire 4 Y in2 [3:0] $end
$var wire 1 Z ncontrol $end
$var wire 4 [ temp4 [3:0] $end
$var wire 4 \ temp3 [3:0] $end
$var wire 4 ] temp2 [3:0] $end
$var wire 4 ^ temp1 [3:0] $end
$var wire 4 _ out2 [3:0] $end
$var wire 4 ` out1 [3:0] $end
$scope module d1 $end
$var wire 4 a in [3:0] $end
$var wire 1 b nsel $end
$var wire 1 W sel $end
$var wire 4 c b [3:0] $end
$var wire 4 d a [3:0] $end
$upscope $end
$scope module d2 $end
$var wire 4 e in [3:0] $end
$var wire 1 f nsel $end
$var wire 1 Z sel $end
$var wire 4 g b [3:0] $end
$var wire 4 h a [3:0] $end
$upscope $end
$scope module m1 $end
$var wire 4 i a [3:0] $end
$var wire 4 j b [3:0] $end
$var wire 1 k not_sel $end
$var wire 1 W sel $end
$var wire 4 l newb [3:0] $end
$var wire 4 m newa [3:0] $end
$var wire 4 n f [3:0] $end
$upscope $end
$scope module m2 $end
$var wire 4 o a [3:0] $end
$var wire 4 p b [3:0] $end
$var wire 1 q not_sel $end
$var wire 1 Z sel $end
$var wire 4 r newb [3:0] $end
$var wire 4 s newa [3:0] $end
$var wire 4 t f [3:0] $end
$upscope $end
$upscope $end
$scope module c3 $end
$var wire 1 u control $end
$var wire 4 v in1 [3:0] $end
$var wire 4 w in2 [3:0] $end
$var wire 1 x ncontrol $end
$var wire 4 y temp4 [3:0] $end
$var wire 4 z temp3 [3:0] $end
$var wire 4 { temp2 [3:0] $end
$var wire 4 | temp1 [3:0] $end
$var wire 4 } out2 [3:0] $end
$var wire 4 ~ out1 [3:0] $end
$scope module d1 $end
$var wire 4 !" in [3:0] $end
$var wire 1 "" nsel $end
$var wire 1 u sel $end
$var wire 4 #" b [3:0] $end
$var wire 4 $" a [3:0] $end
$upscope $end
$scope module d2 $end
$var wire 4 %" in [3:0] $end
$var wire 1 &" nsel $end
$var wire 1 x sel $end
$var wire 4 '" b [3:0] $end
$var wire 4 (" a [3:0] $end
$upscope $end
$scope module m1 $end
$var wire 4 )" a [3:0] $end
$var wire 4 *" b [3:0] $end
$var wire 1 +" not_sel $end
$var wire 1 u sel $end
$var wire 4 ," newb [3:0] $end
$var wire 4 -" newa [3:0] $end
$var wire 4 ." f [3:0] $end
$upscope $end
$scope module m2 $end
$var wire 4 /" a [3:0] $end
$var wire 4 0" b [3:0] $end
$var wire 1 1" not_sel $end
$var wire 1 x sel $end
$var wire 4 2" newb [3:0] $end
$var wire 4 3" newa [3:0] $end
$var wire 4 4" f [3:0] $end
$upscope $end
$upscope $end
$scope module c4 $end
$var wire 1 5" control $end
$var wire 4 6" in1 [3:0] $end
$var wire 4 7" in2 [3:0] $end
$var wire 1 8" ncontrol $end
$var wire 4 9" temp4 [3:0] $end
$var wire 4 :" temp3 [3:0] $end
$var wire 4 ;" temp2 [3:0] $end
$var wire 4 <" temp1 [3:0] $end
$var wire 4 =" out2 [3:0] $end
$var wire 4 >" out1 [3:0] $end
$scope module d1 $end
$var wire 4 ?" in [3:0] $end
$var wire 1 @" nsel $end
$var wire 1 5" sel $end
$var wire 4 A" b [3:0] $end
$var wire 4 B" a [3:0] $end
$upscope $end
$scope module d2 $end
$var wire 4 C" in [3:0] $end
$var wire 1 D" nsel $end
$var wire 1 8" sel $end
$var wire 4 E" b [3:0] $end
$var wire 4 F" a [3:0] $end
$upscope $end
$scope module m1 $end
$var wire 4 G" a [3:0] $end
$var wire 4 H" b [3:0] $end
$var wire 1 I" not_sel $end
$var wire 1 5" sel $end
$var wire 4 J" newb [3:0] $end
$var wire 4 K" newa [3:0] $end
$var wire 4 L" f [3:0] $end
$upscope $end
$scope module m2 $end
$var wire 4 M" a [3:0] $end
$var wire 4 N" b [3:0] $end
$var wire 1 O" not_sel $end
$var wire 1 8" sel $end
$var wire 4 P" newb [3:0] $end
$var wire 4 Q" newa [3:0] $end
$var wire 4 R" f [3:0] $end
$upscope $end
$upscope $end
$scope module c5 $end
$var wire 1 S" control $end
$var wire 4 T" in1 [3:0] $end
$var wire 4 U" in2 [3:0] $end
$var wire 1 V" ncontrol $end
$var wire 4 W" temp4 [3:0] $end
$var wire 4 X" temp3 [3:0] $end
$var wire 4 Y" temp2 [3:0] $end
$var wire 4 Z" temp1 [3:0] $end
$var wire 4 [" out2 [3:0] $end
$var wire 4 \" out1 [3:0] $end
$scope module d1 $end
$var wire 4 ]" in [3:0] $end
$var wire 1 ^" nsel $end
$var wire 1 S" sel $end
$var wire 4 _" b [3:0] $end
$var wire 4 `" a [3:0] $end
$upscope $end
$scope module d2 $end
$var wire 4 a" in [3:0] $end
$var wire 1 b" nsel $end
$var wire 1 V" sel $end
$var wire 4 c" b [3:0] $end
$var wire 4 d" a [3:0] $end
$upscope $end
$scope module m1 $end
$var wire 4 e" a [3:0] $end
$var wire 4 f" b [3:0] $end
$var wire 1 g" not_sel $end
$var wire 1 S" sel $end
$var wire 4 h" newb [3:0] $end
$var wire 4 i" newa [3:0] $end
$var wire 4 j" f [3:0] $end
$upscope $end
$scope module m2 $end
$var wire 4 k" a [3:0] $end
$var wire 4 l" b [3:0] $end
$var wire 1 m" not_sel $end
$var wire 1 V" sel $end
$var wire 4 n" newb [3:0] $end
$var wire 4 o" newa [3:0] $end
$var wire 4 p" f [3:0] $end
$upscope $end
$upscope $end
$upscope $end
$upscope $end
$enddefinitions $end
#0
$dumpvars
b100 p"
b0 o"
b100 n"
0m"
b100 l"
b0 k"
b11 j"
b11 i"
b0 h"
1g"
b0 f"
b11 e"
b0 d"
b100 c"
0b"
b100 a"
b11 `"
b0 _"
1^"
b11 ]"
b11 \"
b100 ["
b11 Z"
b0 Y"
b0 X"
b100 W"
1V"
b100 U"
b11 T"
0S"
b10 R"
b0 Q"
b10 P"
0O"
b10 N"
b0 M"
b1 L"
b1 K"
b0 J"
1I"
b0 H"
b1 G"
b0 F"
b10 E"
0D"
b10 C"
b1 B"
b0 A"
1@"
b1 ?"
b1 >"
b10 ="
b1 <"
b0 ;"
b0 :"
b10 9"
18"
b10 7"
b1 6"
05"
b11 4"
b0 3"
b11 2"
01"
b11 0"
b0 /"
b10 ."
b10 -"
b0 ,"
1+"
b0 *"
b10 )"
b0 ("
b11 '"
0&"
b11 %"
b10 $"
b0 #"
1""
b10 !"
b10 ~
b11 }
b10 |
b0 {
b0 z
b11 y
1x
b11 w
b10 v
0u
b100 t
b0 s
b100 r
0q
b100 p
b0 o
b11 n
b11 m
b0 l
1k
b0 j
b11 i
b0 h
b100 g
0f
b100 e
b11 d
b0 c
1b
b11 a
b11 `
b100 _
b11 ^
b0 ]
b0 \
b100 [
1Z
b100 Y
b11 X
0W
b10 V
b0 U
b10 T
0S
b10 R
b0 Q
b1 P
b1 O
b0 N
1M
b0 L
b1 K
b0 J
b10 I
0H
b10 G
b1 F
b0 E
1D
b1 C
b1 B
b10 A
b1 @
b0 ?
b0 >
b10 =
1<
b10 ;
b1 :
09
b1 8
b10 7
b11 6
b100 5
b1 4
b10 3
b11 2
b100 1
b10 0
b11 /
b100 .
b11 -
b10 ,
b1 +
b0 *
b100 )
b11 (
b10 '
b1 &
b0 %
b1 $
b10 #
b11 "
b100 !
$end
#1000
b1 #
b1 7
b1 ="
b1 R"
b1 P"
b1 9"
b1 E"
b1 N"
b1 0
b1 ~
b1 ."
b1 7"
b1 C"
b10 $
b10 8
b10 >"
b10 L"
b1 -"
b10 K"
b1 |
b1 $"
b1 )"
b10 <"
b10 B"
b10 G"
b10 N
b1 3
b1 A
b1 V
b1 v
b1 !"
b10 4
b10 B
b10 P
b10 6"
b10 ?"
b10 >
b10 J
b10 L
b1 U
1H
b0 =
b0 I
b0 R
1S
b0 T
b0 @
b0 F
b0 K
b0 O
0<
0D
b1 ?
b1 E
b1 Q
0M
19
b1 %
b1 *
#2000
b10 0
b10 ~
b10 ."
b10 7"
b10 C"
b10 -"
b10 |
b10 $"
b10 )"
b10 3
b10 A
b10 V
b10 v
b10 !"
b10 J"
b10 T
b1 O
b1 #
b1 7
b1 ="
b1 R"
b10 $
b10 8
b10 >"
b10 L"
b0 >
b0 J
b0 L
b0 U
b1 4
b1 B
b1 P
b1 6"
b1 ?"
b10 :"
b10 F"
b10 H"
b1 Q"
0H
b10 =
b10 I
b10 R
0S
b1 @
b1 F
b1 K
1D"
b0 9"
b0 E"
b0 N"
1O"
b0 P"
b0 <"
b0 B"
b0 G"
b0 K"
1<
1D
b0 ?
b0 E
b0 Q
1M
b0 N
08"
0@"
b1 ;"
b1 A"
b1 M"
0I"
09
15"
b10 %
b10 *
#3000
b1 $
b1 8
b1 >"
b1 L"
b1 J"
b1 :"
b1 F"
b1 H"
b1 0
b1 ~
b1 ."
b1 7"
b1 C"
b10 #
b10 7
b10 ="
b10 R"
b1 -"
b10 Q"
b1 |
b1 $"
b1 )"
b10 ;"
b10 A"
b10 M"
b10 N
b1 3
b1 A
b1 V
b1 v
b1 !"
b10 4
b10 B
b10 P
b10 6"
b10 ?"
b10 >
b10 J
b10 L
b1 U
1H
b0 =
b0 I
b0 R
1S
b0 T
b0 @
b0 F
b0 K
b0 O
0<
0D
b1 ?
b1 E
b1 Q
0M
19
b11 %
b11 *
#4000
b10 "
b10 6
b10 \"
b10 j"
b10 i"
b10 Z"
b10 `"
b10 e"
b10 3
b10 A
b10 V
b10 v
b10 !"
b11 ,"
b11 #
b11 7
b11 ="
b11 R"
b10 T
b1 O
b10 /
b10 }
b10 4"
b10 T"
b10 ]"
b11 0
b11 ~
b11 ."
b11 7"
b11 C"
b11 P"
b1 K"
b0 >
b0 J
b0 L
b0 U
b1 4
b1 B
b1 P
b1 6"
b1 ?"
b11 z
b11 ("
b11 *"
b10 3"
b0 :"
b0 F"
b0 H"
b0 Q"
b1 $
b1 8
b1 >"
b1 L"
0H
b10 =
b10 I
b10 R
0S
b1 @
b1 F
b1 K
1&"
b0 y
b0 '"
b0 0"
11"
b0 2"
b0 |
b0 $"
b0 )"
b0 -"
0D"
b11 9"
b11 E"
b11 N"
0O"
b1 <"
b1 B"
b1 G"
1<
1D
b0 ?
b0 E
b0 Q
1M
b0 N
0x
0""
b10 {
b10 #"
b10 /"
0+"
18"
1@"
b0 ;"
b0 A"
b0 M"
1I"
b0 J"
09
1u
05"
b100 %
b100 *
#5000
b1 "
b1 6
b1 \"
b1 j"
b1 i"
b1 Z"
b1 `"
b1 e"
b1 /
b1 }
b1 4"
b1 T"
b1 ]"
b10 $
b10 8
b10 >"
b10 L"
b1 3"
b10 K"
b1 {
b1 #"
b1 /"
b10 <"
b10 B"
b10 G"
b10 N
b1 3
b1 A
b1 V
b1 v
b1 !"
b10 4
b10 B
b10 P
b10 6"
b10 ?"
b10 >
b10 J
b10 L
b1 U
1H
b0 =
b0 I
b0 R
1S
b0 T
b0 @
b0 F
b0 K
b0 O
0<
0D
b1 ?
b1 E
b1 Q
0M
19
b101 %
b101 *
#6000
b10 "
b10 6
b10 \"
b10 j"
b10 i"
b10 Z"
b10 `"
b10 e"
b10 /
b10 }
b10 4"
b10 T"
b10 ]"
b10 3"
b10 {
b10 #"
b10 /"
b10 3
b10 A
b10 V
b10 v
b10 !"
b11 J"
b10 T
b1 O
b1 #
b1 7
b1 ="
b1 R"
b11 $
b11 8
b11 >"
b11 L"
b0 >
b0 J
b0 L
b0 U
b1 4
b1 B
b1 P
b1 6"
b1 ?"
b11 :"
b11 F"
b11 H"
b1 Q"
0H
b10 =
b10 I
b10 R
0S
b1 @
b1 F
b1 K
1D"
b0 9"
b0 E"
b0 N"
1O"
b0 P"
b0 <"
b0 B"
b0 G"
b0 K"
1<
1D
b0 ?
b0 E
b0 Q
1M
b0 N
08"
0@"
b1 ;"
b1 A"
b1 M"
0I"
09
15"
b110 %
b110 *
#7000
b1 "
b1 6
b1 \"
b1 j"
b1 i"
b1 Z"
b1 `"
b1 e"
b1 /
b1 }
b1 4"
b1 T"
b1 ]"
b10 #
b10 7
b10 ="
b10 R"
b1 3"
b10 Q"
b1 {
b1 #"
b1 /"
b10 ;"
b10 A"
b10 M"
b10 N
b1 3
b1 A
b1 V
b1 v
b1 !"
b10 4
b10 B
b10 P
b10 6"
b10 ?"
b10 >
b10 J
b10 L
b1 U
1H
b0 =
b0 I
b0 R
1S
b0 T
b0 @
b0 F
b0 K
b0 O
0<
0D
b1 ?
b1 E
b1 Q
0M
19
b111 %
b111 *
#8000
b100 "
b100 6
b100 \"
b100 j"
b11 !
b11 5
b11 ["
b11 p"
b100 i"
b11 n"
b100 Z"
b100 `"
b100 e"
b11 W"
b11 c"
b11 l"
b10 3
b10 A
b10 V
b10 v
b10 !"
b100 l
b100 /
b100 }
b100 4"
b100 T"
b100 ]"
b10 #
b10 7
b10 ="
b10 R"
b10 T
b1 O
b11 1
b11 _
b11 t
b11 U"
b11 a"
b100 2
b100 `
b100 n
b100 w
b100 %"
b100 2"
b10 -"
b10 P"
b1 K"
b0 >
b0 J
b0 L
b0 U
b1 4
b1 B
b1 P
b1 6"
b1 ?"
b100 \
b100 h
b100 j
b11 s
b0 z
b0 ("
b0 *"
b0 3"
b10 0
b10 ~
b10 ."
b10 7"
b10 C"
b0 :"
b0 F"
b0 H"
b0 Q"
b1 $
b1 8
b1 >"
b1 L"
0H
b10 =
b10 I
b10 R
0S
b1 @
b1 F
b1 K
1f
b0 [
b0 g
b0 p
1q
b0 r
b0 ^
b0 d
b0 i
b0 m
0&"
b100 y
b100 '"
b100 0"
01"
b10 |
b10 $"
b10 )"
0D"
b10 9"
b10 E"
b10 N"
0O"
b1 <"
b1 B"
b1 G"
1<
1D
b0 ?
b0 E
b0 Q
1M
b0 N
0Z
0b
b11 ]
b11 c
b11 o
0k
1x
1""
b0 {
b0 #"
b0 /"
1+"
b0 ,"
18"
1@"
b0 ;"
b0 A"
b0 M"
1I"
b0 J"
09
1W
0u
05"
b1000 %
b1000 *
#9000
b1 #
b1 7
b1 ="
b1 R"
b1 P"
b1 9"
b1 E"
b1 N"
b1 0
b1 ~
b1 ."
b1 7"
b1 C"
b10 $
b10 8
b10 >"
b10 L"
b1 -"
b10 K"
b1 |
b1 $"
b1 )"
b10 <"
b10 B"
b10 G"
b10 N
b1 3
b1 A
b1 V
b1 v
b1 !"
b10 4
b10 B
b10 P
b10 6"
b10 ?"
b10 >
b10 J
b10 L
b1 U
1H
b0 =
b0 I
b0 R
1S
b0 T
b0 @
b0 F
b0 K
b0 O
0<
0D
b1 ?
b1 E
b1 Q
0M
19
b1001 %
b1001 *
#10000
b10 0
b10 ~
b10 ."
b10 7"
b10 C"
b10 -"
b10 |
b10 $"
b10 )"
b10 3
b10 A
b10 V
b10 v
b10 !"
b10 J"
b10 T
b1 O
b1 #
b1 7
b1 ="
b1 R"
b10 $
b10 8
b10 >"
b10 L"
b0 >
b0 J
b0 L
b0 U
b1 4
b1 B
b1 P
b1 6"
b1 ?"
b10 :"
b10 F"
b10 H"
b1 Q"
0H
b10 =
b10 I
b10 R
0S
b1 @
b1 F
b1 K
1D"
b0 9"
b0 E"
b0 N"
1O"
b0 P"
b0 <"
b0 B"
b0 G"
b0 K"
1<
1D
b0 ?
b0 E
b0 Q
1M
b0 N
08"
0@"
b1 ;"
b1 A"
b1 M"
0I"
09
15"
b1010 %
b1010 *
#11000
b1 $
b1 8
b1 >"
b1 L"
b1 J"
b1 :"
b1 F"
b1 H"
b1 0
b1 ~
b1 ."
b1 7"
b1 C"
b10 #
b10 7
b10 ="
b10 R"
b1 -"
b10 Q"
b1 |
b1 $"
b1 )"
b10 ;"
b10 A"
b10 M"
b10 N
b1 3
b1 A
b1 V
b1 v
b1 !"
b10 4
b10 B
b10 P
b10 6"
b10 ?"
b10 >
b10 J
b10 L
b1 U
1H
b0 =
b0 I
b0 R
1S
b0 T
b0 @
b0 F
b0 K
b0 O
0<
0D
b1 ?
b1 E
b1 Q
0M
19
b1011 %
b1011 *
#12000
b10 "
b10 6
b10 \"
b10 j"
b10 i"
b10 Z"
b10 `"
b10 e"
b10 3
b10 A
b10 V
b10 v
b10 !"
b100 ,"
b100 #
b100 7
b100 ="
b100 R"
b10 T
b1 O
b10 /
b10 }
b10 4"
b10 T"
b10 ]"
b100 0
b100 ~
b100 ."
b100 7"
b100 C"
b100 P"
b1 K"
b0 >
b0 J
b0 L
b0 U
b1 4
b1 B
b1 P
b1 6"
b1 ?"
b100 z
b100 ("
b100 *"
b10 3"
b0 :"
b0 F"
b0 H"
b0 Q"
b1 $
b1 8
b1 >"
b1 L"
0H
b10 =
b10 I
b10 R
0S
b1 @
b1 F
b1 K
1&"
b0 y
b0 '"
b0 0"
11"
b0 2"
b0 |
b0 $"
b0 )"
b0 -"
0D"
b100 9"
b100 E"
b100 N"
0O"
b1 <"
b1 B"
b1 G"
1<
1D
b0 ?
b0 E
b0 Q
1M
b0 N
0x
0""
b10 {
b10 #"
b10 /"
0+"
18"
1@"
b0 ;"
b0 A"
b0 M"
1I"
b0 J"
09
1u
05"
b1100 %
b1100 *
#13000
b1 "
b1 6
b1 \"
b1 j"
b1 i"
b1 Z"
b1 `"
b1 e"
b1 /
b1 }
b1 4"
b1 T"
b1 ]"
b10 $
b10 8
b10 >"
b10 L"
b1 3"
b10 K"
b1 {
b1 #"
b1 /"
b10 <"
b10 B"
b10 G"
b10 N
b1 3
b1 A
b1 V
b1 v
b1 !"
b10 4
b10 B
b10 P
b10 6"
b10 ?"
b10 >
b10 J
b10 L
b1 U
1H
b0 =
b0 I
b0 R
1S
b0 T
b0 @
b0 F
b0 K
b0 O
0<
0D
b1 ?
b1 E
b1 Q
0M
19
b1101 %
b1101 *
#14000
b10 "
b10 6
b10 \"
b10 j"
b10 i"
b10 Z"
b10 `"
b10 e"
b10 /
b10 }
b10 4"
b10 T"
b10 ]"
b10 3"
b10 {
b10 #"
b10 /"
b10 3
b10 A
b10 V
b10 v
b10 !"
b100 J"
b10 T
b1 O
b1 #
b1 7
b1 ="
b1 R"
b100 $
b100 8
b100 >"
b100 L"
b0 >
b0 J
b0 L
b0 U
b1 4
b1 B
b1 P
b1 6"
b1 ?"
b100 :"
b100 F"
b100 H"
b1 Q"
0H
b10 =
b10 I
b10 R
0S
b1 @
b1 F
b1 K
1D"
b0 9"
b0 E"
b0 N"
1O"
b0 P"
b0 <"
b0 B"
b0 G"
b0 K"
1<
1D
b0 ?
b0 E
b0 Q
1M
b0 N
08"
0@"
b1 ;"
b1 A"
b1 M"
0I"
09
15"
b1110 %
b1110 *
#15000
b1 "
b1 6
b1 \"
b1 j"
b1 i"
b1 Z"
b1 `"
b1 e"
b1 /
b1 }
b1 4"
b1 T"
b1 ]"
b10 #
b10 7
b10 ="
b10 R"
b1 3"
b10 Q"
b1 {
b1 #"
b1 /"
b10 ;"
b10 A"
b10 M"
b10 N
b1 3
b1 A
b1 V
b1 v
b1 !"
b10 4
b10 B
b10 P
b10 6"
b10 ?"
b10 >
b10 J
b10 L
b1 U
1H
b0 =
b0 I
b0 R
1S
b0 T
b0 @
b0 F
b0 K
b0 O
0<
0D
b1 ?
b1 E
b1 Q
0M
19
b1111 %
b1111 *
#16000
b10 3
b10 A
b10 V
b10 v
b10 !"
b100 1
b100 _
b100 t
b100 U"
b100 a"
b11 /
b11 }
b11 4"
b11 T"
b11 ]"
b10 #
b10 7
b10 ="
b10 R"
b100 h"
b10 T
b1 O
b100 r
b11 m
b11 2"
b10 -"
b10 P"
b1 K"
b11 !
b11 5
b11 ["
b11 p"
b100 "
b100 6
b100 \"
b100 j"
b0 >
b0 J
b0 L
b0 U
b1 4
b1 B
b1 P
b1 6"
b1 ?"
b0 \
b0 h
b0 j
b0 s
b11 2
b11 `
b11 n
b11 w
b11 %"
b0 z
b0 ("
b0 *"
b0 3"
b10 0
b10 ~
b10 ."
b10 7"
b10 C"
b0 :"
b0 F"
b0 H"
b0 Q"
b1 $
b1 8
b1 >"
b1 L"
b100 X"
b100 d"
b100 f"
b11 o"
0H
b10 =
b10 I
b10 R
0S
b1 @
b1 F
b1 K
0f
b100 [
b100 g
b100 p
0q
b11 ^
b11 d
b11 i
0&"
b11 y
b11 '"
b11 0"
01"
b10 |
b10 $"
b10 )"
0D"
b10 9"
b10 E"
b10 N"
0O"
b1 <"
b1 B"
b1 G"
1b"
b0 W"
b0 c"
b0 l"
1m"
b0 n"
b0 Z"
b0 `"
b0 e"
b0 i"
1<
1D
b0 ?
b0 E
b0 Q
1M
b0 N
1Z
1b
b0 ]
b0 c
b0 o
1k
b0 l
1x
1""
b0 {
b0 #"
b0 /"
1+"
b0 ,"
18"
1@"
b0 ;"
b0 A"
b0 M"
1I"
b0 J"
0V"
0^"
b11 Y"
b11 _"
b11 k"
0g"
09
0W
0u
05"
1S"
b10000 %
b10000 *
#17000
b1 #
b1 7
b1 ="
b1 R"
b1 P"
b1 9"
b1 E"
b1 N"
b1 0
b1 ~
b1 ."
b1 7"
b1 C"
b10 $
b10 8
b10 >"
b10 L"
b1 -"
b10 K"
b1 |
b1 $"
b1 )"
b10 <"
b10 B"
b10 G"
b10 N
b1 3
b1 A
b1 V
b1 v
b1 !"
b10 4
b10 B
b10 P
b10 6"
b10 ?"
b10 >
b10 J
b10 L
b1 U
1H
b0 =
b0 I
b0 R
1S
b0 T
b0 @
b0 F
b0 K
b0 O
0<
0D
b1 ?
b1 E
b1 Q
0M
19
b10001 %
b10001 *
#18000
b10 0
b10 ~
b10 ."
b10 7"
b10 C"
b10 -"
b10 |
b10 $"
b10 )"
b10 3
b10 A
b10 V
b10 v
b10 !"
b10 J"
b10 T
b1 O
b1 #
b1 7
b1 ="
b1 R"
b10 $
b10 8
b10 >"
b10 L"
b0 >
b0 J
b0 L
b0 U
b1 4
b1 B
b1 P
b1 6"
b1 ?"
b10 :"
b10 F"
b10 H"
b1 Q"
0H
b10 =
b10 I
b10 R
0S
b1 @
b1 F
b1 K
1D"
b0 9"
b0 E"
b0 N"
1O"
b0 P"
b0 <"
b0 B"
b0 G"
b0 K"
1<
1D
b0 ?
b0 E
b0 Q
1M
b0 N
08"
0@"
b1 ;"
b1 A"
b1 M"
0I"
09
15"
b10010 %
b10010 *
#19000
b1 $
b1 8
b1 >"
b1 L"
b1 J"
b1 :"
b1 F"
b1 H"
b1 0
b1 ~
b1 ."
b1 7"
b1 C"
b10 #
b10 7
b10 ="
b10 R"
b1 -"
b10 Q"
b1 |
b1 $"
b1 )"
b10 ;"
b10 A"
b10 M"
b10 N
b1 3
b1 A
b1 V
b1 v
b1 !"
b10 4
b10 B
b10 P
b10 6"
b10 ?"
b10 >
b10 J
b10 L
b1 U
1H
b0 =
b0 I
b0 R
1S
b0 T
b0 @
b0 F
b0 K
b0 O
0<
0D
b1 ?
b1 E
b1 Q
0M
19
b10011 %
b10011 *
