Lab4/Basic/4-3/Lab4_Many_To_One_LFSR.v
`timescale 1ns/1ps

module Many_To_One_LFSR(clk, rst_n, out);
    input clk;
    input rst_n;
    output reg [8-1:0] out;
    wire [8-1:0] next_DFF;
    wire temp1, temp2;
    always @(posedge clk) begin
        if(!rst_n) begin
            out <= 8'b10111101;
        end
        else begin
            out <= next_DFF;
        end
    end
    assign next_DFF = {out[6:0] , (out[7] ^ out[3]) ^ (out[1] ^ out[2])};
endmodule

Lab4/Basic/4-3/Many_to_one_LFSR_t.v
`timescale 1ns/1ps
`include "Lab4_Many_To_One_LFSR.v"
module Many_To_One_LFSR_t;
reg clk = 0;
reg rst_n = 1;
wire [7:0] out;

// specify duration of a clock cycle.
parameter cyc = 10;

// generate clock.
always#(cyc/2)clk = !clk;

Many_To_One_LFSR m21lfsr(
    .clk(clk),
    .rst_n(rst_n),
    .out(out)
);

// uncommment and add "+access+r" to your nverilog command to dump fsdb waveform on NTHUCAD
// initial begin
//     $fsdbDumpfile("Many_To_One_LFSR.fsdb");
//     $fsdbDumpvars;
// end

initial begin
    $dumpfile("Many_To_One_LFSR.vcd");
    $dumpvars(0, Many_To_One_LFSR_t);
    @(negedge clk)
    rst_n = 1'b0;
    @(negedge clk)
    rst_n = 1'b1;
    #(cyc * 16)
    $finish;
end
endmodule

Lab4/Basic/4-3/Many_to_one_LFSR.vcd
$date
	Thu Oct 26 16:10:32 2023
$end
$version
	Icarus Verilog
$end
$timescale
	1ps
$end
$scope module Many_To_One_LFSR_t $end
$var wire 8 ! out [7:0] $end
$var reg 1 " clk $end
$var reg 1 # rst_n $end
$scope module m21lfsr $end
$var wire 1 " clk $end
$var wire 1 # rst_n $end
$var wire 8 $ next_DFF [7:0] $end
$var reg 8 % out [7:0] $end
$upscope $end
$upscope $end
$enddefinitions $end
#0
$dumpvars
bx %
bx $
1#
0"
bx !
$end
#5000
1"
#10000
0#
0"
#15000
b1111011 $
b10111101 !
b10111101 %
1"
#20000
1#
0"
#25000
b11110110 $
b1111011 !
b1111011 %
1"
#30000
0"
#35000
b11101101 $
b11110110 !
b11110110 %
1"
#40000
0"
#45000
b11011011 $
b11101101 !
b11101101 %
1"
#50000
0"
#55000
b10110111 $
b11011011 !
b11011011 %
1"
#60000
0"
#65000
b1101111 $
b10110111 !
b10110111 %
1"
#70000
0"
#75000
b11011111 $
b1101111 !
b1101111 %
1"
#80000
0"
#85000
b10111110 $
b11011111 !
b11011111 %
1"
#90000
0"
#95000
b1111100 $
b10111110 !
b10111110 %
1"
#100000
0"
#105000
b11111000 $
b1111100 !
b1111100 %
1"
#110000
0"
#115000
b11110000 $
b11111000 !
b11111000 %
1"
#120000
0"
#125000
b11100001 $
b11110000 !
b11110000 %
1"
#130000
0"
#135000
b11000011 $
b11100001 !
b11100001 %
1"
#140000
0"
#145000
b10000110 $
b11000011 !
b11000011 %
1"
#150000
0"
#155000
b1101 $
b10000110 !
b10000110 %
1"
#160000
0"
#165000
b11010 $
b1101 !
b1101 %
1"
#170000
0"
#175000
b110100 $
b11010 !
b11010 %
1"
