Lab4/Advanced/4-4/Lab4_111062109_Mealy_Sequence_Detector.v
`timescale 1ns/1ps

module Mealy_Sequence_Detector (clk, rst_n, in, dec);
    input clk, rst_n;
    input in;
    output dec;

    parameter S0 = 3'b000, S1 = 3'b001, S2 = 3'b010, S3 = 3'b011, S4 = 3'b100, S5 = 3'b101, S6 = 3'b110, S7 = 3'b111;

    reg [2:0] state, next_state;
    reg dec;

    reg [1:0] count;

    always @(posedge clk) begin
        if(!rst_n) begin
            state <= S0;
            count <= 2'b00;
            dec <= 0;
        end
        else begin
            if(count == 2'b11) begin
                count <= 2'b00;
                state <= S0;
            end
            else begin
                count <= count + 1;
                state <= next_state;
            end
        end
    end
    always @(*) begin
        case (state)
            S0: begin
                dec = 0;
                next_state = in ? S1 : S4;
            end
            S1: begin
                dec = 0;
                next_state = in ? S6 : S2;
            end
            S2: begin
                dec = 0;
                next_state = in ? S0 : S3;
            end
            S3: begin
                next_state = S0;
                dec = in;
            end
            S4: begin
                dec = 0;
                next_state = in ? S5 : S0;
            end
            S5: begin
                dec = 0;
                next_state = in ? S3 : S0;
            end
            S6: begin
                dec = 0;
                next_state = in ? S7 : S0;
            end
            S7: begin
                next_state = S0;
                dec = !in;
            end
        endcase
    end
endmodule

Lab4/Advanced/4-4/Lab4_111062109_Mealy_Sequence_Detector_t.v
`timescale 1ns / 1ps
`include "Lab4_111062109_Mealy_Sequence_Detector.v"

module Mealy_Sequence_Detector_t;
    reg clk;
    reg rst_n;
    reg in;
    wire Dec;

    Mealy_Sequence_Detector Mealy_Sequence_Detector(clk, rst_n, in, Dec);

    initial begin
        $dumpfile("Mealy_Sequence_Detector_t.vcd");
        $dumpvars(0, Mealy_Sequence_Detector_t);
        clk = 0;
        rst_n = 0;
        in = 0;
        #10 rst_n = 1;
        #10 in = 1;
        #30 in = 0;
        #10 in = 1;
        #20 in = 0;
        #10 in = 1;
        #10 in = 0;
        #20 in = 1;
        #10 in = 0;
        #10 in = 1;
        #10 in = 0;
        #20 $finish;
    end
    always #5 clk = ~clk;
endmodule

Lab4/Advanced/4-4/Mealy_Sequence_Detector_t.vcd
$date
	Mon Oct 30 20:59:21 2023
$end
$version
	Icarus Verilog
$end
$timescale
	1ps
$end
$scope module Mealy_Sequence_Detector_t $end
$var wire 1 ! Dec $end
$var reg 1 " clk $end
$var reg 1 # in $end
$var reg 1 $ rst_n $end
$scope module Mealy_Sequence_Detector $end
$var wire 1 " clk $end
$var wire 1 # in $end
$var wire 1 $ rst_n $end
$var reg 2 % count [1:0] $end
$var reg 1 ! dec $end
$var reg 3 & next_state [2:0] $end
$var reg 3 ' state [2:0] $end
$upscope $end
$upscope $end
$enddefinitions $end
#0
$dumpvars
bx '
bx &
bx %
0$
0#
0"
x!
$end
#5000
b100 &
0!
b0 %
b0 '
1"
#10000
0"
1$
#15000
b0 &
b100 '
b1 %
1"
#20000
b101 &
0"
1#
#25000
b11 &
b101 '
b10 %
1"
#30000
0"
#35000
1!
b0 &
b11 '
b11 %
1"
#40000
0"
#45000
b1 &
0!
b0 '
b0 %
1"
#50000
b100 &
0"
0#
#55000
b0 &
b100 '
b1 %
1"
#60000
b101 &
0"
1#
#65000
b11 &
b101 '
b10 %
1"
#70000
0"
#75000
1!
b0 &
b11 '
b11 %
1"
#80000
0!
0"
0#
#85000
b100 &
b0 '
b0 %
1"
#90000
b1 &
0"
1#
#95000
b110 &
b1 '
b1 %
1"
#100000
b10 &
0"
0#
#105000
b11 &
b10 '
b10 %
1"
#110000
0"
#115000
b0 &
b11 '
b11 %
1"
#120000
1!
0"
1#
#125000
b1 &
0!
b0 '
b0 %
1"
#130000
b100 &
0"
0#
#135000
b0 &
b100 '
b1 %
1"
#140000
b101 &
0"
1#
#145000
b11 &
b101 '
b10 %
1"
#150000
b0 &
0"
0#
#155000
b100 &
b0 '
b11 %
1"
#160000
0"
#165000
b0 %
1"
