Lab4/Advanced/4-1/Lab4_111062109_Content_Addressable_Memory.v
`timescale 1ns/1ps

module priority_encoder_4bit(in, out);
    input [15:0] in;
    output reg [3:0] out;
    always @(*) begin
        if(in[15]) out = 4'b1111;
        else if(in[14]) out = 4'b1110;
        else if(in[13]) out = 4'b1101;
        else if(in[12]) out = 4'b1100;
        else if(in[11]) out = 4'b1011;
        else if(in[10]) out = 4'b1010;
        else if(in[9]) out = 4'b1001;
        else if(in[8]) out = 4'b1000;
        else if(in[7]) out = 4'b0111;
        else if(in[6]) out = 4'b0110;
        else if(in[5]) out = 4'b0101;
        else if(in[4]) out = 4'b0100;
        else if(in[3]) out = 4'b0011;
        else if(in[2]) out = 4'b0010;
        else if(in[1]) out = 4'b0001;
        else out = 4'b0000;
    end
endmodule

module Content_Addressable_Memory(clk, wen, ren, din, addr, dout, hit);
    input clk;
    input wen, ren;
    input [7:0] din;
    input [3:0] addr;
    output [3:0] dout;
    output hit;

    reg [7:0] memory [15:0];
    wire [15:0] match;
    reg [3:0] dout;
    reg hit;
    wire [3:0] temp_dout;
    priority_encoder_4bit match_encoder(match, temp_dout);

    assign match[0] = memory[0] === din;
    assign match[1] = memory[1] === din;
    assign match[2] = memory[2] === din;
    assign match[3] = memory[3] === din;
    assign match[4] = memory[4] === din;
    assign match[5] = memory[5] === din;
    assign match[6] = memory[6] === din;
    assign match[7] = memory[7] === din;
    assign match[8] = memory[8] === din;
    assign match[9] = memory[9] === din;
    assign match[10] = memory[10] === din;
    assign match[11] = memory[11] === din;
    assign match[12] = memory[12] === din;
    assign match[13] = memory[13] === din;
    assign match[14] = memory[14] === din;
    assign match[15] = memory[15] === din;

    always @(posedge clk) begin
        if(ren) begin
            dout <= temp_dout;
            hit <= (match != 16'd0);
        end
        else if(wen) begin
            memory[addr] <= din;
            hit <= 1'b0;
            dout <= 4'b0000;
        end
        else begin
            hit <= 1'b0;
            dout <= 4'b0000;
        end
    end
endmodule

Lab4/Advanced/4-1/Lab4_111062109_Content_Addressable_Memory_t.v
`timescale 1ns/1ps
`include "Lab4_111062109_Content_Addressable_Memory.v"

module Content_Addressable_Memory_t;
    reg clk;
    reg wen, ren;
    reg [7:0] din;
    reg [3:0] addr;
    wire [3:0] dout;
    wire hit;

    Content_Addressable_Memory uut(clk, wen, ren, din, addr, dout, hit);

    initial begin
        $dumpfile("Content_Addressable_Memory.vcd");
        $dumpvars(0, Content_Addressable_Memory_t);
        clk = 0;
        wen = 0;
        ren = 0;
        din = 0;
        addr = 0;
        @(negedge clk)
        wen = 1;
        din = 8'd4;
        addr = 4'd0;
        @(negedge clk)
        din = 8'd8;
        addr = 4'd7;
        @(negedge clk)
        din = 8'd35;
        addr = 4'd15;
        @(negedge clk)
        din = 8'd8;
        addr = 4'd9;
        @(negedge clk)
        din = 8'd8;
        addr = 4'd5;
        @(negedge clk)
        wen = 0;
        din = 8'd0;
        addr = 4'd0;
        #25;
        @(negedge clk)
        ren = 1;
        din = 8'd4;
        @(negedge clk)
        din = 8'd8;
        @(negedge clk)
        din = 8'd35;
        @(negedge clk)
        din = 8'd87;
        @(negedge clk)
        din = 8'd45;
        @(negedge clk)
        ren = 0;
        din = 8'd0;
        #30 $finish;
    end

    always #5 clk = ~clk;
endmodule

Lab4/Advanced/4-1/Content_Addressable_Memory.vcd
$date
	Fri Oct 27 13:38:49 2023
$end
$version
	Icarus Verilog
$end
$timescale
	1ps
$end
$scope module Content_Addressable_Memory_t $end
$var wire 1 ! hit $end
$var wire 4 " dout [3:0] $end
$var reg 4 # addr [3:0] $end
$var reg 1 $ clk $end
$var reg 8 % din [7:0] $end
$var reg 1 & ren $end
$var reg 1 ' wen $end
$scope module uut $end
$var wire 4 ( addr [3:0] $end
$var wire 1 $ clk $end
$var wire 8 ) din [7:0] $end
$var wire 1 & ren $end
$var wire 1 ' wen $end
$var wire 4 * temp_dout [3:0] $end
$var wire 16 + match [15:0] $end
$var reg 4 , dout [3:0] $end
$var reg 1 ! hit $end
$scope module match_encoder $end
$var wire 16 - in [15:0] $end
$var reg 4 . out [3:0] $end
$upscope $end
$upscope $end
$upscope $end
$enddefinitions $end
#0
$dumpvars
b0 .
b0 -
bx ,
b0 +
b0 *
b0 )
b0 (
0'
0&
b0 %
0$
b0 #
bx "
x!
$end
#5000
b0 "
b0 ,
0!
1$
#10000
b100 %
b100 )
1'
0$
#15000
b1 +
b1 -
1$
#20000
b111 #
b111 (
b0 +
b0 -
b1000 %
b1000 )
0$
#25000
b111 *
b111 .
b10000000 +
b10000000 -
1$
#30000
b0 *
b0 .
b1111 #
b1111 (
b0 +
b0 -
b100011 %
b100011 )
0$
#35000
b1111 *
b1111 .
b1000000000000000 +
b1000000000000000 -
1$
#40000
b111 *
b111 .
b1001 #
b1001 (
b10000000 +
b10000000 -
b1000 %
b1000 )
0$
#45000
b1001 *
b1001 .
b1010000000 +
b1010000000 -
1$
#50000
b101 #
b101 (
0$
#55000
b1010100000 +
b1010100000 -
1$
#60000
b0 *
b0 .
b0 #
b0 (
b0 +
b0 -
b0 %
b0 )
0'
0$
#65000
1$
#70000
0$
#75000
1$
#80000
0$
#85000
1$
#90000
b1 +
b1 -
b100 %
b100 )
1&
0$
#95000
1!
1$
#100000
b1001 *
b1001 .
b1010100000 +
b1010100000 -
b1000 %
b1000 )
0$
#105000
b1001 "
b1001 ,
1$
#110000
b1111 *
b1111 .
b1000000000000000 +
b1000000000000000 -
b100011 %
b100011 )
0$
#115000
b1111 "
b1111 ,
1$
#120000
b0 *
b0 .
b0 +
b0 -
b1010111 %
b1010111 )
0$
#125000
0!
b0 "
b0 ,
1$
#130000
b101101 %
b101101 )
0$
#135000
1$
#140000
b0 %
b0 )
0&
0$
