Lab2/Advanced/2-4/Lab2_111062109_Multiplier_4bit.v
`timescale 1ns/1ps
module AND(out, a, b);
    input a, b;
    output out;
    wire temp;
    nand n1 (temp, a, b);
    nand n2 (out, temp, temp);
endmodule

module OR(out, a, b);
    input a, b;
    output out;
    wire temp1, temp2;
    nand n1 (temp1, a, a);
    nand n2 (temp2, b, b);
    nand n3 (out, temp1, temp2);
endmodule

module XOR(out, a, b);
    input a, b;
    output out;
    wire temp1, temp2, na, nb;
    nand n1 (na, a, a);
    nand n2 (nb, b, b);
    nand n3 (temp1, na, b);
    nand n4 (temp2, nb, a);
    nand n5 (out, temp1, temp2);
endmodule

module Majority(a, b, c, out);
    input a, b, c;
    output out;
    wire temp1, temp2, temp3, temp4, temp5, temp6;
    AND A1 (temp1, a, b);
    AND A2 (temp2, a, c);
    AND A3 (temp3, b, c);
    OR O1 (temp4, temp1, temp2);
    OR O2 (out, temp4, temp3);
endmodule

module Full_Adder (a, b, cin, cout, sum);
    input a, b, cin;
    output cout, sum;
    wire temp1;
    Majority M1 (a, b, cin, cout);
    XOR X1 (temp1, a, b);
    XOR X2 (sum, temp1, cin);
endmodule

module Half_Adder(a, b, cout, sum);
    input a, b;
    output cout, sum;

    XOR X1 (sum, a, b);
    AND A1 (cout, a, b);
endmodule

module Adder_4bit(a, b, sum, cout);
    input [4-1:0] a, b;
    output cout;
    output [4-1:0] sum;
    wire [4-1-1:0] tempcin;
    Half_Adder H1 (a[0], b[0], tempcin[0], sum[0]);
    Full_Adder F2 (a[1], b[1], tempcin[0], tempcin[1], sum[1]);
    Full_Adder F3 (a[2], b[2], tempcin[1], tempcin[2], sum[2]);
    Full_Adder F4 (a[3], b[3], tempcin[2], cout, sum[3]);
endmodule

module Multiplier_4x1bit(a, b, p);
    input [4-1:0] a;
    input b;
    output [4-1:0] p;
    AND A1 (p[0], a[0], b);
    AND A2 (p[1], a[1], b);
    AND A3 (p[2], a[2], b);
    AND A4 (p[3], a[3], b);
endmodule

module Multiplier_4bit(a, b, p);
    input [4-1:0] a, b;
    output [8-1:0] p;
    wire [4-1:0] ab0, ab1, ab2, ab3;
    wire [4-1:0] addtemp1, addtemp2;
    Multiplier_4x1bit M1 (a, b[0], ab0);
    Multiplier_4x1bit M2 (a, b[1], ab1);
    Multiplier_4x1bit M3 (a, b[2], ab2);
    Multiplier_4x1bit M4 (a, b[3], ab3);
    AND A1 (p[0], a[0], b[0]);
    Adder_4bit A2 ({1'b0, ab0[3:1]}, ab1, {addtemp1[2:0], p[1]}, addtemp1[3]);
    Adder_4bit A3 ( addtemp1, ab2, {addtemp2[2:0], p[2]}, addtemp2[3]);
    Adder_4bit A4 ( addtemp2, ab3, p[6:3], p[7]);
endmodule

Lab2/Advanced/2-4/Lab2_111062109_Multiplier_4bit_t.v
`timescale 1ns/1ps
`include "Lab2_111062109_Multiplier_4bit.v"
module Multiplier_4bit_t;
    reg [4-1:0] a = 4'b0000;
    reg [4-1:0] b = 4'b0000;
    wire [8-1:0] sum;
    
    Multiplier_4bit MUL (a, b, sum);

    initial begin
        $dumpfile("Multiplier_4bit_t.vcd");
        $dumpvars(0, Multiplier_4bit_t);
        repeat(16) begin
            repeat(16) begin
                #1 b = b + 1;
            end
            a = a + 1;
        end
    end
endmodule

Lab2/Advanced/2-4/Multiplier_4bit_t.vcd
$date
	Sun Oct  8 10:43:40 2023
$end
$version
	Icarus Verilog
$end
$timescale
	1ps
$end
$scope module Multiplier_4bit_t $end
$var wire 8 ! sum [7:0] $end
$var reg 4 " a [3:0] $end
$var reg 4 # b [3:0] $end
$scope module MUL $end
$var wire 4 $ a [3:0] $end
$var wire 4 % b [3:0] $end
$var wire 8 & p [7:0] $end
$var wire 4 ' addtemp2 [3:0] $end
$var wire 4 ( addtemp1 [3:0] $end
$var wire 4 ) ab3 [3:0] $end
$var wire 4 * ab2 [3:0] $end
$var wire 4 + ab1 [3:0] $end
$var wire 4 , ab0 [3:0] $end
$scope module A1 $end
$var wire 1 - a $end
$var wire 1 . b $end
$var wire 1 / out $end
$var wire 1 0 temp $end
$upscope $end
$scope module A2 $end
$var wire 4 1 a [3:0] $end
$var wire 3 2 tempcin [2:0] $end
$var wire 4 3 sum [3:0] $end
$var wire 1 4 cout $end
$var wire 4 5 b [3:0] $end
$scope module F2 $end
$var wire 1 6 a $end
$var wire 1 7 b $end
$var wire 1 8 cin $end
$var wire 1 9 temp1 $end
$var wire 1 : sum $end
$var wire 1 ; cout $end
$scope module M1 $end
$var wire 1 6 a $end
$var wire 1 7 b $end
$var wire 1 8 c $end
$var wire 1 < temp4 $end
$var wire 1 = temp3 $end
$var wire 1 > temp2 $end
$var wire 1 ? temp1 $end
$var wire 1 ; out $end
$scope module A1 $end
$var wire 1 6 a $end
$var wire 1 7 b $end
$var wire 1 ? out $end
$var wire 1 @ temp $end
$upscope $end
$scope module A2 $end
$var wire 1 6 a $end
$var wire 1 8 b $end
$var wire 1 > out $end
$var wire 1 A temp $end
$upscope $end
$scope module A3 $end
$var wire 1 7 a $end
$var wire 1 8 b $end
$var wire 1 = out $end
$var wire 1 B temp $end
$upscope $end
$scope module O1 $end
$var wire 1 ? a $end
$var wire 1 > b $end
$var wire 1 < out $end
$var wire 1 C temp1 $end
$var wire 1 D temp2 $end
$upscope $end
$scope module O2 $end
$var wire 1 < a $end
$var wire 1 = b $end
$var wire 1 ; out $end
$var wire 1 E temp1 $end
$var wire 1 F temp2 $end
$upscope $end
$upscope $end
$scope module X1 $end
$var wire 1 6 a $end
$var wire 1 7 b $end
$var wire 1 G na $end
$var wire 1 H nb $end
$var wire 1 9 out $end
$var wire 1 I temp1 $end
$var wire 1 J temp2 $end
$upscope $end
$scope module X2 $end
$var wire 1 9 a $end
$var wire 1 8 b $end
$var wire 1 K na $end
$var wire 1 L nb $end
$var wire 1 : out $end
$var wire 1 M temp1 $end
$var wire 1 N temp2 $end
$upscope $end
$upscope $end
$scope module F3 $end
$var wire 1 O a $end
$var wire 1 P b $end
$var wire 1 Q cin $end
$var wire 1 R temp1 $end
$var wire 1 S sum $end
$var wire 1 T cout $end
$scope module M1 $end
$var wire 1 O a $end
$var wire 1 P b $end
$var wire 1 Q c $end
$var wire 1 U temp4 $end
$var wire 1 V temp3 $end
$var wire 1 W temp2 $end
$var wire 1 X temp1 $end
$var wire 1 T out $end
$scope module A1 $end
$var wire 1 O a $end
$var wire 1 P b $end
$var wire 1 X out $end
$var wire 1 Y temp $end
$upscope $end
$scope module A2 $end
$var wire 1 O a $end
$var wire 1 Q b $end
$var wire 1 W out $end
$var wire 1 Z temp $end
$upscope $end
$scope module A3 $end
$var wire 1 P a $end
$var wire 1 Q b $end
$var wire 1 V out $end
$var wire 1 [ temp $end
$upscope $end
$scope module O1 $end
$var wire 1 X a $end
$var wire 1 W b $end
$var wire 1 U out $end
$var wire 1 \ temp1 $end
$var wire 1 ] temp2 $end
$upscope $end
$scope module O2 $end
$var wire 1 U a $end
$var wire 1 V b $end
$var wire 1 T out $end
$var wire 1 ^ temp1 $end
$var wire 1 _ temp2 $end
$upscope $end
$upscope $end
$scope module X1 $end
$var wire 1 O a $end
$var wire 1 P b $end
$var wire 1 ` na $end
$var wire 1 a nb $end
$var wire 1 R out $end
$var wire 1 b temp1 $end
$var wire 1 c temp2 $end
$upscope $end
$scope module X2 $end
$var wire 1 R a $end
$var wire 1 Q b $end
$var wire 1 d na $end
$var wire 1 e nb $end
$var wire 1 S out $end
$var wire 1 f temp1 $end
$var wire 1 g temp2 $end
$upscope $end
$upscope $end
$scope module F4 $end
$var wire 1 h a $end
$var wire 1 i b $end
$var wire 1 j cin $end
$var wire 1 k temp1 $end
$var wire 1 l sum $end
$var wire 1 4 cout $end
$scope module M1 $end
$var wire 1 h a $end
$var wire 1 i b $end
$var wire 1 j c $end
$var wire 1 m temp4 $end
$var wire 1 n temp3 $end
$var wire 1 o temp2 $end
$var wire 1 p temp1 $end
$var wire 1 4 out $end
$scope module A1 $end
$var wire 1 h a $end
$var wire 1 i b $end
$var wire 1 p out $end
$var wire 1 q temp $end
$upscope $end
$scope module A2 $end
$var wire 1 h a $end
$var wire 1 j b $end
$var wire 1 o out $end
$var wire 1 r temp $end
$upscope $end
$scope module A3 $end
$var wire 1 i a $end
$var wire 1 j b $end
$var wire 1 n out $end
$var wire 1 s temp $end
$upscope $end
$scope module O1 $end
$var wire 1 p a $end
$var wire 1 o b $end
$var wire 1 m out $end
$var wire 1 t temp1 $end
$var wire 1 u temp2 $end
$upscope $end
$scope module O2 $end
$var wire 1 m a $end
$var wire 1 n b $end
$var wire 1 4 out $end
$var wire 1 v temp1 $end
$var wire 1 w temp2 $end
$upscope $end
$upscope $end
$scope module X1 $end
$var wire 1 h a $end
$var wire 1 i b $end
$var wire 1 x na $end
$var wire 1 y nb $end
$var wire 1 k out $end
$var wire 1 z temp1 $end
$var wire 1 { temp2 $end
$upscope $end
$scope module X2 $end
$var wire 1 k a $end
$var wire 1 j b $end
$var wire 1 | na $end
$var wire 1 } nb $end
$var wire 1 l out $end
$var wire 1 ~ temp1 $end
$var wire 1 !" temp2 $end
$upscope $end
$upscope $end
$scope module H1 $end
$var wire 1 "" a $end
$var wire 1 #" b $end
$var wire 1 $" sum $end
$var wire 1 %" cout $end
$scope module A1 $end
$var wire 1 "" a $end
$var wire 1 #" b $end
$var wire 1 %" out $end
$var wire 1 &" temp $end
$upscope $end
$scope module X1 $end
$var wire 1 "" a $end
$var wire 1 #" b $end
$var wire 1 '" na $end
$var wire 1 (" nb $end
$var wire 1 $" out $end
$var wire 1 )" temp1 $end
$var wire 1 *" temp2 $end
$upscope $end
$upscope $end
$upscope $end
$scope module A3 $end
$var wire 4 +" a [3:0] $end
$var wire 3 ," tempcin [2:0] $end
$var wire 4 -" sum [3:0] $end
$var wire 1 ." cout $end
$var wire 4 /" b [3:0] $end
$scope module F2 $end
$var wire 1 0" a $end
$var wire 1 1" b $end
$var wire 1 2" cin $end
$var wire 1 3" temp1 $end
$var wire 1 4" sum $end
$var wire 1 5" cout $end
$scope module M1 $end
$var wire 1 0" a $end
$var wire 1 1" b $end
$var wire 1 2" c $end
$var wire 1 6" temp4 $end
$var wire 1 7" temp3 $end
$var wire 1 8" temp2 $end
$var wire 1 9" temp1 $end
$var wire 1 5" out $end
$scope module A1 $end
$var wire 1 0" a $end
$var wire 1 1" b $end
$var wire 1 9" out $end
$var wire 1 :" temp $end
$upscope $end
$scope module A2 $end
$var wire 1 0" a $end
$var wire 1 2" b $end
$var wire 1 8" out $end
$var wire 1 ;" temp $end
$upscope $end
$scope module A3 $end
$var wire 1 1" a $end
$var wire 1 2" b $end
$var wire 1 7" out $end
$var wire 1 <" temp $end
$upscope $end
$scope module O1 $end
$var wire 1 9" a $end
$var wire 1 8" b $end
$var wire 1 6" out $end
$var wire 1 =" temp1 $end
$var wire 1 >" temp2 $end
$upscope $end
$scope module O2 $end
$var wire 1 6" a $end
$var wire 1 7" b $end
$var wire 1 5" out $end
$var wire 1 ?" temp1 $end
$var wire 1 @" temp2 $end
$upscope $end
$upscope $end
$scope module X1 $end
$var wire 1 0" a $end
$var wire 1 1" b $end
$var wire 1 A" na $end
$var wire 1 B" nb $end
$var wire 1 3" out $end
$var wire 1 C" temp1 $end
$var wire 1 D" temp2 $end
$upscope $end
$scope module X2 $end
$var wire 1 3" a $end
$var wire 1 2" b $end
$var wire 1 E" na $end
$var wire 1 F" nb $end
$var wire 1 4" out $end
$var wire 1 G" temp1 $end
$var wire 1 H" temp2 $end
$upscope $end
$upscope $end
$scope module F3 $end
$var wire 1 I" a $end
$var wire 1 J" b $end
$var wire 1 K" cin $end
$var wire 1 L" temp1 $end
$var wire 1 M" sum $end
$var wire 1 N" cout $end
$scope module M1 $end
$var wire 1 I" a $end
$var wire 1 J" b $end
$var wire 1 K" c $end
$var wire 1 O" temp4 $end
$var wire 1 P" temp3 $end
$var wire 1 Q" temp2 $end
$var wire 1 R" temp1 $end
$var wire 1 N" out $end
$scope module A1 $end
$var wire 1 I" a $end
$var wire 1 J" b $end
$var wire 1 R" out $end
$var wire 1 S" temp $end
$upscope $end
$scope module A2 $end
$var wire 1 I" a $end
$var wire 1 K" b $end
$var wire 1 Q" out $end
$var wire 1 T" temp $end
$upscope $end
$scope module A3 $end
$var wire 1 J" a $end
$var wire 1 K" b $end
$var wire 1 P" out $end
$var wire 1 U" temp $end
$upscope $end
$scope module O1 $end
$var wire 1 R" a $end
$var wire 1 Q" b $end
$var wire 1 O" out $end
$var wire 1 V" temp1 $end
$var wire 1 W" temp2 $end
$upscope $end
$scope module O2 $end
$var wire 1 O" a $end
$var wire 1 P" b $end
$var wire 1 N" out $end
$var wire 1 X" temp1 $end
$var wire 1 Y" temp2 $end
$upscope $end
$upscope $end
$scope module X1 $end
$var wire 1 I" a $end
$var wire 1 J" b $end
$var wire 1 Z" na $end
$var wire 1 [" nb $end
$var wire 1 L" out $end
$var wire 1 \" temp1 $end
$var wire 1 ]" temp2 $end
$upscope $end
$scope module X2 $end
$var wire 1 L" a $end
$var wire 1 K" b $end
$var wire 1 ^" na $end
$var wire 1 _" nb $end
$var wire 1 M" out $end
$var wire 1 `" temp1 $end
$var wire 1 a" temp2 $end
$upscope $end
$upscope $end
$scope module F4 $end
$var wire 1 b" a $end
$var wire 1 c" b $end
$var wire 1 d" cin $end
$var wire 1 e" temp1 $end
$var wire 1 f" sum $end
$var wire 1 ." cout $end
$scope module M1 $end
$var wire 1 b" a $end
$var wire 1 c" b $end
$var wire 1 d" c $end
$var wire 1 g" temp4 $end
$var wire 1 h" temp3 $end
$var wire 1 i" temp2 $end
$var wire 1 j" temp1 $end
$var wire 1 ." out $end
$scope module A1 $end
$var wire 1 b" a $end
$var wire 1 c" b $end
$var wire 1 j" out $end
$var wire 1 k" temp $end
$upscope $end
$scope module A2 $end
$var wire 1 b" a $end
$var wire 1 d" b $end
$var wire 1 i" out $end
$var wire 1 l" temp $end
$upscope $end
$scope module A3 $end
$var wire 1 c" a $end
$var wire 1 d" b $end
$var wire 1 h" out $end
$var wire 1 m" temp $end
$upscope $end
$scope module O1 $end
$var wire 1 j" a $end
$var wire 1 i" b $end
$var wire 1 g" out $end
$var wire 1 n" temp1 $end
$var wire 1 o" temp2 $end
$upscope $end
$scope module O2 $end
$var wire 1 g" a $end
$var wire 1 h" b $end
$var wire 1 ." out $end
$var wire 1 p" temp1 $end
$var wire 1 q" temp2 $end
$upscope $end
$upscope $end
$scope module X1 $end
$var wire 1 b" a $end
$var wire 1 c" b $end
$var wire 1 r" na $end
$var wire 1 s" nb $end
$var wire 1 e" out $end
$var wire 1 t" temp1 $end
$var wire 1 u" temp2 $end
$upscope $end
$scope module X2 $end
$var wire 1 e" a $end
$var wire 1 d" b $end
$var wire 1 v" na $end
$var wire 1 w" nb $end
$var wire 1 f" out $end
$var wire 1 x" temp1 $end
$var wire 1 y" temp2 $end
$upscope $end
$upscope $end
$scope module H1 $end
$var wire 1 z" a $end
$var wire 1 {" b $end
$var wire 1 |" sum $end
$var wire 1 }" cout $end
$scope module A1 $end
$var wire 1 z" a $end
$var wire 1 {" b $end
$var wire 1 }" out $end
$var wire 1 ~" temp $end
$upscope $end
$scope module X1 $end
$var wire 1 z" a $end
$var wire 1 {" b $end
$var wire 1 !# na $end
$var wire 1 "# nb $end
$var wire 1 |" out $end
$var wire 1 ## temp1 $end
$var wire 1 $# temp2 $end
$upscope $end
$upscope $end
$upscope $end
$scope module A4 $end
$var wire 4 %# a [3:0] $end
$var wire 3 &# tempcin [2:0] $end
$var wire 4 '# sum [3:0] $end
$var wire 1 (# cout $end
$var wire 4 )# b [3:0] $end
$scope module F2 $end
$var wire 1 *# a $end
$var wire 1 +# b $end
$var wire 1 ,# cin $end
$var wire 1 -# temp1 $end
$var wire 1 .# sum $end
$var wire 1 /# cout $end
$scope module M1 $end
$var wire 1 *# a $end
$var wire 1 +# b $end
$var wire 1 ,# c $end
$var wire 1 0# temp4 $end
$var wire 1 1# temp3 $end
$var wire 1 2# temp2 $end
$var wire 1 3# temp1 $end
$var wire 1 /# out $end
$scope module A1 $end
$var wire 1 *# a $end
$var wire 1 +# b $end
$var wire 1 3# out $end
$var wire 1 4# temp $end
$upscope $end
$scope module A2 $end
$var wire 1 *# a $end
$var wire 1 ,# b $end
$var wire 1 2# out $end
$var wire 1 5# temp $end
$upscope $end
$scope module A3 $end
$var wire 1 +# a $end
$var wire 1 ,# b $end
$var wire 1 1# out $end
$var wire 1 6# temp $end
$upscope $end
$scope module O1 $end
$var wire 1 3# a $end
$var wire 1 2# b $end
$var wire 1 0# out $end
$var wire 1 7# temp1 $end
$var wire 1 8# temp2 $end
$upscope $end
$scope module O2 $end
$var wire 1 0# a $end
$var wire 1 1# b $end
$var wire 1 /# out $end
$var wire 1 9# temp1 $end
$var wire 1 :# temp2 $end
$upscope $end
$upscope $end
$scope module X1 $end
$var wire 1 *# a $end
$var wire 1 +# b $end
$var wire 1 ;# na $end
$var wire 1 <# nb $end
$var wire 1 -# out $end
$var wire 1 =# temp1 $end
$var wire 1 ># temp2 $end
$upscope $end
$scope module X2 $end
$var wire 1 -# a $end
$var wire 1 ,# b $end
$var wire 1 ?# na $end
$var wire 1 @# nb $end
$var wire 1 .# out $end
$var wire 1 A# temp1 $end
$var wire 1 B# temp2 $end
$upscope $end
$upscope $end
$scope module F3 $end
$var wire 1 C# a $end
$var wire 1 D# b $end
$var wire 1 E# cin $end
$var wire 1 F# temp1 $end
$var wire 1 G# sum $end
$var wire 1 H# cout $end
$scope module M1 $end
$var wire 1 C# a $end
$var wire 1 D# b $end
$var wire 1 E# c $end
$var wire 1 I# temp4 $end
$var wire 1 J# temp3 $end
$var wire 1 K# temp2 $end
$var wire 1 L# temp1 $end
$var wire 1 H# out $end
$scope module A1 $end
$var wire 1 C# a $end
$var wire 1 D# b $end
$var wire 1 L# out $end
$var wire 1 M# temp $end
$upscope $end
$scope module A2 $end
$var wire 1 C# a $end
$var wire 1 E# b $end
$var wire 1 K# out $end
$var wire 1 N# temp $end
$upscope $end
$scope module A3 $end
$var wire 1 D# a $end
$var wire 1 E# b $end
$var wire 1 J# out $end
$var wire 1 O# temp $end
$upscope $end
$scope module O1 $end
$var wire 1 L# a $end
$var wire 1 K# b $end
$var wire 1 I# out $end
$var wire 1 P# temp1 $end
$var wire 1 Q# temp2 $end
$upscope $end
$scope module O2 $end
$var wire 1 I# a $end
$var wire 1 J# b $end
$var wire 1 H# out $end
$var wire 1 R# temp1 $end
$var wire 1 S# temp2 $end
$upscope $end
$upscope $end
$scope module X1 $end
$var wire 1 C# a $end
$var wire 1 D# b $end
$var wire 1 T# na $end
$var wire 1 U# nb $end
$var wire 1 F# out $end
$var wire 1 V# temp1 $end
$var wire 1 W# temp2 $end
$upscope $end
$scope module X2 $end
$var wire 1 F# a $end
$var wire 1 E# b $end
$var wire 1 X# na $end
$var wire 1 Y# nb $end
$var wire 1 G# out $end
$var wire 1 Z# temp1 $end
$var wire 1 [# temp2 $end
$upscope $end
$upscope $end
$scope module F4 $end
$var wire 1 \# a $end
$var wire 1 ]# b $end
$var wire 1 ^# cin $end
$var wire 1 _# temp1 $end
$var wire 1 `# sum $end
$var wire 1 (# cout $end
$scope module M1 $end
$var wire 1 \# a $end
$var wire 1 ]# b $end
$var wire 1 ^# c $end
$var wire 1 a# temp4 $end
$var wire 1 b# temp3 $end
$var wire 1 c# temp2 $end
$var wire 1 d# temp1 $end
$var wire 1 (# out $end
$scope module A1 $end
$var wire 1 \# a $end
$var wire 1 ]# b $end
$var wire 1 d# out $end
$var wire 1 e# temp $end
$upscope $end
$scope module A2 $end
$var wire 1 \# a $end
$var wire 1 ^# b $end
$var wire 1 c# out $end
$var wire 1 f# temp $end
$upscope $end
$scope module A3 $end
$var wire 1 ]# a $end
$var wire 1 ^# b $end
$var wire 1 b# out $end
$var wire 1 g# temp $end
$upscope $end
$scope module O1 $end
$var wire 1 d# a $end
$var wire 1 c# b $end
$var wire 1 a# out $end
$var wire 1 h# temp1 $end
$var wire 1 i# temp2 $end
$upscope $end
$scope module O2 $end
$var wire 1 a# a $end
$var wire 1 b# b $end
$var wire 1 (# out $end
$var wire 1 j# temp1 $end
$var wire 1 k# temp2 $end
$upscope $end
$upscope $end
$scope module X1 $end
$var wire 1 \# a $end
$var wire 1 ]# b $end
$var wire 1 l# na $end
$var wire 1 m# nb $end
$var wire 1 _# out $end
$var wire 1 n# temp1 $end
$var wire 1 o# temp2 $end
$upscope $end
$scope module X2 $end
$var wire 1 _# a $end
$var wire 1 ^# b $end
$var wire 1 p# na $end
$var wire 1 q# nb $end
$var wire 1 `# out $end
$var wire 1 r# temp1 $end
$var wire 1 s# temp2 $end
$upscope $end
$upscope $end
$scope module H1 $end
$var wire 1 t# a $end
$var wire 1 u# b $end
$var wire 1 v# sum $end
$var wire 1 w# cout $end
$scope module A1 $end
$var wire 1 t# a $end
$var wire 1 u# b $end
$var wire 1 w# out $end
$var wire 1 x# temp $end
$upscope $end
$scope module X1 $end
$var wire 1 t# a $end
$var wire 1 u# b $end
$var wire 1 y# na $end
$var wire 1 z# nb $end
$var wire 1 v# out $end
$var wire 1 {# temp1 $end
$var wire 1 |# temp2 $end
$upscope $end
$upscope $end
$upscope $end
$scope module M1 $end
$var wire 4 }# a [3:0] $end
$var wire 1 ~# b $end
$var wire 4 !$ p [3:0] $end
$scope module A1 $end
$var wire 1 "$ a $end
$var wire 1 ~# b $end
$var wire 1 #$ out $end
$var wire 1 $$ temp $end
$upscope $end
$scope module A2 $end
$var wire 1 %$ a $end
$var wire 1 ~# b $end
$var wire 1 &$ out $end
$var wire 1 '$ temp $end
$upscope $end
$scope module A3 $end
$var wire 1 ($ a $end
$var wire 1 ~# b $end
$var wire 1 )$ out $end
$var wire 1 *$ temp $end
$upscope $end
$scope module A4 $end
$var wire 1 +$ a $end
$var wire 1 ~# b $end
$var wire 1 ,$ out $end
$var wire 1 -$ temp $end
$upscope $end
$upscope $end
$scope module M2 $end
$var wire 4 .$ a [3:0] $end
$var wire 1 /$ b $end
$var wire 4 0$ p [3:0] $end
$scope module A1 $end
$var wire 1 1$ a $end
$var wire 1 /$ b $end
$var wire 1 2$ out $end
$var wire 1 3$ temp $end
$upscope $end
$scope module A2 $end
$var wire 1 4$ a $end
$var wire 1 /$ b $end
$var wire 1 5$ out $end
$var wire 1 6$ temp $end
$upscope $end
$scope module A3 $end
$var wire 1 7$ a $end
$var wire 1 /$ b $end
$var wire 1 8$ out $end
$var wire 1 9$ temp $end
$upscope $end
$scope module A4 $end
$var wire 1 :$ a $end
$var wire 1 /$ b $end
$var wire 1 ;$ out $end
$var wire 1 <$ temp $end
$upscope $end
$upscope $end
$scope module M3 $end
$var wire 4 =$ a [3:0] $end
$var wire 1 >$ b $end
$var wire 4 ?$ p [3:0] $end
$scope module A1 $end
$var wire 1 @$ a $end
$var wire 1 >$ b $end
$var wire 1 A$ out $end
$var wire 1 B$ temp $end
$upscope $end
$scope module A2 $end
$var wire 1 C$ a $end
$var wire 1 >$ b $end
$var wire 1 D$ out $end
$var wire 1 E$ temp $end
$upscope $end
$scope module A3 $end
$var wire 1 F$ a $end
$var wire 1 >$ b $end
$var wire 1 G$ out $end
$var wire 1 H$ temp $end
$upscope $end
$scope module A4 $end
$var wire 1 I$ a $end
$var wire 1 >$ b $end
$var wire 1 J$ out $end
$var wire 1 K$ temp $end
$upscope $end
$upscope $end
$scope module M4 $end
$var wire 4 L$ a [3:0] $end
$var wire 1 M$ b $end
$var wire 4 N$ p [3:0] $end
$scope module A1 $end
$var wire 1 O$ a $end
$var wire 1 M$ b $end
$var wire 1 P$ out $end
$var wire 1 Q$ temp $end
$upscope $end
$scope module A2 $end
$var wire 1 R$ a $end
$var wire 1 M$ b $end
$var wire 1 S$ out $end
$var wire 1 T$ temp $end
$upscope $end
$scope module A3 $end
$var wire 1 U$ a $end
$var wire 1 M$ b $end
$var wire 1 V$ out $end
$var wire 1 W$ temp $end
$upscope $end
$scope module A4 $end
$var wire 1 X$ a $end
$var wire 1 M$ b $end
$var wire 1 Y$ out $end
$var wire 1 Z$ temp $end
$upscope $end
$upscope $end
$upscope $end
$upscope $end
$enddefinitions $end
#0
$dumpvars
1Z$
0Y$
0X$
1W$
0V$
0U$
1T$
0S$
0R$
1Q$
0P$
0O$
b0 N$
0M$
b0 L$
1K$
0J$
0I$
1H$
0G$
0F$
1E$
0D$
0C$
1B$
0A$
0@$
b0 ?$
0>$
b0 =$
1<$
0;$
0:$
19$
08$
07$
16$
05$
04$
13$
02$
01$
b0 0$
0/$
b0 .$
1-$
0,$
0+$
1*$
0)$
0($
1'$
0&$
0%$
1$$
0#$
0"$
b0 !$
0~#
b0 }#
1|#
1{#
1z#
1y#
1x#
0w#
0v#
0u#
0t#
1s#
1r#
1q#
1p#
1o#
1n#
1m#
1l#
1k#
1j#
1i#
1h#
1g#
1f#
1e#
0d#
0c#
0b#
0a#
0`#
0_#
0^#
0]#
0\#
1[#
1Z#
1Y#
1X#
1W#
1V#
1U#
1T#
1S#
1R#
1Q#
1P#
1O#
1N#
1M#
0L#
0K#
0J#
0I#
0H#
0G#
0F#
0E#
0D#
0C#
1B#
1A#
1@#
1?#
1>#
1=#
1<#
1;#
1:#
19#
18#
17#
16#
15#
14#
03#
02#
01#
00#
0/#
0.#
0-#
0,#
0+#
0*#
b0 )#
0(#
b0 '#
b0 &#
b0 %#
1$#
1##
1"#
1!#
1~"
0}"
0|"
0{"
0z"
1y"
1x"
1w"
1v"
1u"
1t"
1s"
1r"
1q"
1p"
1o"
1n"
1m"
1l"
1k"
0j"
0i"
0h"
0g"
0f"
0e"
0d"
0c"
0b"
1a"
1`"
1_"
1^"
1]"
1\"
1["
1Z"
1Y"
1X"
1W"
1V"
1U"
1T"
1S"
0R"
0Q"
0P"
0O"
0N"
0M"
0L"
0K"
0J"
0I"
1H"
1G"
1F"
1E"
1D"
1C"
1B"
1A"
1@"
1?"
1>"
1="
1<"
1;"
1:"
09"
08"
07"
06"
05"
04"
03"
02"
01"
00"
b0 /"
0."
b0 -"
b0 ,"
b0 +"
1*"
1)"
1("
1'"
1&"
0%"
0$"
0#"
0""
1!"
1~
1}
1|
1{
1z
1y
1x
1w
1v
1u
1t
1s
1r
1q
0p
0o
0n
0m
0l
0k
0j
0i
0h
1g
1f
1e
1d
1c
1b
1a
1`
1_
1^
1]
1\
1[
1Z
1Y
0X
0W
0V
0U
0T
0S
0R
0Q
0P
0O
1N
1M
1L
1K
1J
1I
1H
1G
1F
1E
1D
1C
1B
1A
1@
0?
0>
0=
0<
0;
0:
09
08
07
06
b0 5
04
b0 3
b0 2
b0 1
10
0/
0.
0-
b0 ,
b0 +
b0 *
b0 )
b0 (
b0 '
b0 &
b0 %
b0 $
b0 #
b0 "
b0 !
$end
#1000
1~#
1.
b1 #
b1 %
#2000
0~#
1/$
0.
b10 #
b10 %
#3000
1~#
1.
b11 #
b11 %
#4000
0~#
0/$
1>$
0.
b100 #
b100 %
#5000
1~#
1.
b101 #
b101 %
#6000
0~#
1/$
0.
b110 #
b110 %
#7000
1~#
1.
b111 #
b111 %
#8000
0~#
0/$
0>$
1M$
0.
b1000 #
b1000 %
#9000
1~#
1.
b1001 #
b1001 %
#10000
0~#
1/$
0.
b1010 #
b1010 %
#11000
1~#
1.
b1011 #
b1011 %
#12000
0~#
0/$
1>$
0.
b1100 #
b1100 %
#13000
1~#
1.
b1101 #
b1101 %
#14000
0~#
1/$
0.
b1110 #
b1110 %
#15000
1~#
1.
b1111 #
b1111 %
#16000
1-
1"$
11$
1@$
1O$
0~#
0/$
0>$
0M$
0.
b1 "
b1 $
b1 }#
b1 .$
b1 =$
b1 L$
b0 #
b0 %
#17000
b1 ,
b1 !$
1#$
b1 !
b1 &
1/
0$$
00
1~#
1.
b1 #
b1 %
#18000
b1 3
1$"
0("
0)"
1#"
b0 ,
b0 !$
0#$
b1 +
b1 5
b1 0$
12$
b10 !
b10 &
0/
1$$
03$
10
0~#
1/$
0.
b10 #
b10 %
#19000
b1 ,
b1 !$
1#$
b11 !
b11 &
1/
0$$
00
1~#
1.
b11 #
b11 %
#20000
b0 3
0$"
b1 -"
1|"
1("
1)"
0"#
0##
0#"
1{"
b0 ,
b0 !$
0#$
b0 +
b0 5
b0 0$
02$
b1 *
b1 /"
b1 ?$
1A$
b100 !
b100 &
0/
1$$
13$
0B$
10
0~#
0/$
1>$
0.
b100 #
b100 %
#21000
b1 ,
b1 !$
1#$
b101 !
b101 &
1/
0$$
00
1~#
1.
b101 #
b101 %
#22000
b1 3
1$"
0("
0)"
1#"
b0 ,
b0 !$
0#$
b1 +
b1 5
b1 0$
12$
b110 !
b110 &
0/
1$$
03$
10
0~#
1/$
0.
b110 #
b110 %
#23000
b1 ,
b1 !$
1#$
b111 !
b111 &
1/
0$$
00
1~#
1.
b111 #
b111 %
#24000
b0 3
0$"
b0 -"
0|"
b1 '#
1v#
1("
1)"
1"#
1##
0z#
0{#
0#"
0{"
1u#
b0 ,
b0 !$
0#$
b0 +
b0 5
b0 0$
02$
b0 *
b0 /"
b0 ?$
0A$
b1 )
b1 )#
b1 N$
1P$
b1000 !
b1000 &
0/
1$$
13$
1B$
0Q$
10
0~#
0/$
0>$
1M$
0.
b1000 #
b1000 %
#25000
b1 ,
b1 !$
1#$
b1001 !
b1001 &
1/
0$$
00
1~#
1.
b1001 #
b1001 %
#26000
b1 3
1$"
0("
0)"
1#"
b0 ,
b0 !$
0#$
b1 +
b1 5
b1 0$
12$
b1010 !
b1010 &
0/
1$$
03$
10
0~#
1/$
0.
b1010 #
b1010 %
