Lab2/Basic/2-1/Lab2_NAND_Implement.v
`timescale 1ns/1ps

module NOT(out, a);
    input a;
    output out;
    nand n1 (out, a, a);
endmodule

module AND(out, a, b);
    input a, b;
    output out;
    wire temp;
    nand n1 (temp, a, b);
    nand n2 (out, temp, temp);
endmodule

module OR(out, a, b);
    input a, b;
    output out;
    wire temp1, temp2;
    nand n1 (temp1, a, a);
    nand n2 (temp2, b, b);
    nand n3 (out, temp1, temp2);
endmodule

module NOR(out, a, b);
    input a, b;
    output out;
    wire temp1, temp2, temp3;
    nand n1 (temp1, a, a);
    nand n2 (temp2, b, b);
    nand n3 (temp3, temp1, temp2);
    nand n4 (out, temp3, temp3);
endmodule

module XOR(out, a, b);
    input a, b;
    output out;
    wire temp1, temp2, na, nb;
    nand n1 (na, a, a);
    nand n2 (nb, b, b);
    nand n3 (temp1, na, b);
    nand n4 (temp2, nb, a);
    nand n5 (out, temp1, temp2);
endmodule

module XNOR(out, a, b);
    input a, b;
    output out;
    wire temp1, temp2, na, nb;
    nand n1 (na, a, a);
    nand n2 (nb, b, b);
    nand n3 (temp1, na, nb);
    nand n4 (temp2, b, a);
    nand n5 (out, temp1, temp2);
endmodule

module Mux_2x1_1bit(a, b, sel, out);
    input a, b;
    input sel;
    output out;
    wire not_sel;
    wire newa, newb;
    NOT N1(not_sel, sel);
    AND A1(newa, not_sel, a);
    AND A2(newb, sel, b);
    OR O1(out, newa, newb);
endmodule

module Mux_8x1_1bit(a, b, c, d, e, f, g, h, sel, out);
    input a, b, c, d, e, f, g, h;
    input [2:0]sel;
    output out;
    wire temp1, temp2, temp3, temp4, temp5, temp6;
    Mux_2x1_1bit M1(a, b, sel[0], temp1);
    Mux_2x1_1bit M2(c, d, sel[0], temp2);
    Mux_2x1_1bit M3(e, f, sel[0], temp3);
    Mux_2x1_1bit M4(g, h, sel[0], temp4);
    Mux_2x1_1bit M5(temp1, temp2, sel[1], temp5);
    Mux_2x1_1bit M6(temp3, temp4, sel[1], temp6);
    Mux_2x1_1bit M7(temp5, temp6, sel[2], out);
endmodule

module NAND_Implement (a, b, sel, out);
    input a, b;
    input [3-1:0] sel;
    output out;
    wire my_NAND, my_AND, my_OR, my_NOR, my_XOR, my_XNOR, my_NOT;
    nand SEL0(my_NAND, a, b);
    AND SEL1(my_AND, a, b);
    OR SEL2(my_OR, a, b);
    NOR SEL3(my_NOR, a, b);
    XOR SEL4(my_XOR, a, b);
    XNOR SEL5(my_XNOR, a, b);
    NOT SEL6(my_NOT, a);
    Mux_8x1_1bit BM1(my_NAND, my_AND, my_OR, my_NOR, my_XOR, my_XNOR, my_NOT, my_NOT, sel, out);
endmodule

Lab2/Basic/2-1/NAND_Implement_t.v
`timescale 1ns/1ps
`include "Lab2_NAND_Implement.v"
module NAND_Implement_t;
reg a = 1'b0;
reg b = 1'b0;
reg [2:0] sel = 3'd0;
wire out;

NAND_Implement nand_i (
    .a (a),
    .b (b),
    .sel (sel),
    .out (out)
);

// uncommment and add "+access+r" to your nverilog command to dump fsdb waveform on NTHUCAD
// initial begin
//      $fsdbDumpfile("NAND_Implement.fsdb");
//      $fsdbDumpvars;
// end


initial begin
    $dumpfile("NAND_Implement.vcd");
    $dumpvars(0, NAND_Implement_t);
    repeat (2 ** 5) begin
        #1 {sel, a, b} = {sel, a, b} + 1'b1;
    end
    #1 $finish;
end
endmodule

Lab2/Basic/2-1/2-1.sim/sim_1/behav/xsim/NAND_Implement.vcd
$date
   Thu Oct 12 15:22:23 2023
$end
$version
  2020.2
$end
$timescale
  1ps
$end
$scope module NAND_Implement_t $end
$var reg 1 ! a $end
$var reg 1 " b $end
$var reg 3 # sel [2:0] $end
$var wire 1 $ out $end
$scope module nand_i $end
$var wire 1 % a $end
$var wire 1 & b $end
$var wire 3 ' sel [2:0] $end
$var wire 1 $ out $end
$var wire 1 ( my_NAND $end
$var wire 1 ) my_AND $end
$var wire 1 * my_OR $end
$var wire 1 + my_NOR $end
$var wire 1 , my_XOR $end
$var wire 1 - my_XNOR $end
$var wire 1 . my_NOT $end
$scope module SEL1 $end
$var wire 1 % a $end
$var wire 1 & b $end
$var wire 1 ) out $end
$var wire 1 / temp $end
$upscope $end
$scope module SEL2 $end
$var wire 1 % a $end
$var wire 1 & b $end
$var wire 1 * out $end
$var wire 1 0 temp1 $end
$var wire 1 1 temp2 $end
$upscope $end
$scope module SEL3 $end
$var wire 1 % a $end
$var wire 1 & b $end
$var wire 1 + out $end
$var wire 1 2 temp1 $end
$var wire 1 3 temp2 $end
$var wire 1 4 temp3 $end
$upscope $end
$scope module SEL4 $end
$var wire 1 % a $end
$var wire 1 & b $end
$var wire 1 , out $end
$var wire 1 5 temp1 $end
$var wire 1 6 temp2 $end
$var wire 1 7 na $end
$var wire 1 8 nb $end
$upscope $end
$scope module SEL5 $end
$var wire 1 % a $end
$var wire 1 & b $end
$var wire 1 - out $end
$var wire 1 9 temp1 $end
$var wire 1 : temp2 $end
$var wire 1 ; na $end
$var wire 1 < nb $end
$upscope $end
$scope module SEL6 $end
$var wire 1 % a $end
$var wire 1 . out $end
$upscope $end
$scope module BM1 $end
$var wire 1 ( a $end
$var wire 1 ) b $end
$var wire 1 * c $end
$var wire 1 + d $end
$var wire 1 , e $end
$var wire 1 - f $end
$var wire 1 . g $end
$var wire 1 . h $end
$var wire 3 ' sel [2:0] $end
$var wire 1 $ out $end
$var wire 1 = temp1 $end
$var wire 1 > temp2 $end
$var wire 1 ? temp3 $end
$var wire 1 @ temp4 $end
$var wire 1 A temp5 $end
$var wire 1 B temp6 $end
$scope module M1 $end
$var wire 1 ( a $end
$var wire 1 ) b $end
$var wire 1 C sel $end
$var wire 1 = out $end
$var wire 1 D not_sel $end
$var wire 1 E newa $end
$var wire 1 F newb $end
$scope module N1 $end
$var wire 1 C a $end
$var wire 1 D out $end
$upscope $end
$scope module A1 $end
$var wire 1 D a $end
$var wire 1 ( b $end
$var wire 1 E out $end
$var wire 1 G temp $end
$upscope $end
$scope module A2 $end
$var wire 1 C a $end
$var wire 1 ) b $end
$var wire 1 F out $end
$var wire 1 H temp $end
$upscope $end
$scope module O1 $end
$var wire 1 E a $end
$var wire 1 F b $end
$var wire 1 = out $end
$var wire 1 I temp1 $end
$var wire 1 J temp2 $end
$upscope $end
$upscope $end
$scope module M2 $end
$var wire 1 * a $end
$var wire 1 + b $end
$var wire 1 C sel $end
$var wire 1 > out $end
$var wire 1 K not_sel $end
$var wire 1 L newa $end
$var wire 1 M newb $end
$scope module N1 $end
$var wire 1 C a $end
$var wire 1 K out $end
$upscope $end
$scope module A1 $end
$var wire 1 K a $end
$var wire 1 * b $end
$var wire 1 L out $end
$var wire 1 N temp $end
$upscope $end
$scope module A2 $end
$var wire 1 C a $end
$var wire 1 + b $end
$var wire 1 M out $end
$var wire 1 O temp $end
$upscope $end
$scope module O1 $end
$var wire 1 L a $end
$var wire 1 M b $end
$var wire 1 > out $end
$var wire 1 P temp1 $end
$var wire 1 Q temp2 $end
$upscope $end
$upscope $end
$scope module M3 $end
$var wire 1 , a $end
$var wire 1 - b $end
$var wire 1 C sel $end
$var wire 1 ? out $end
$var wire 1 R not_sel $end
$var wire 1 S newa $end
$var wire 1 T newb $end
$scope module N1 $end
$var wire 1 C a $end
$var wire 1 R out $end
$upscope $end
$scope module A1 $end
$var wire 1 R a $end
$var wire 1 , b $end
$var wire 1 S out $end
$var wire 1 U temp $end
$upscope $end
$scope module A2 $end
$var wire 1 C a $end
$var wire 1 - b $end
$var wire 1 T out $end
$var wire 1 V temp $end
$upscope $end
$scope module O1 $end
$var wire 1 S a $end
$var wire 1 T b $end
$var wire 1 ? out $end
$var wire 1 W temp1 $end
$var wire 1 X temp2 $end
$upscope $end
$upscope $end
$scope module M4 $end
$var wire 1 . a $end
$var wire 1 . b $end
$var wire 1 C sel $end
$var wire 1 @ out $end
$var wire 1 Y not_sel $end
$var wire 1 Z newa $end
$var wire 1 [ newb $end
$scope module N1 $end
$var wire 1 C a $end
$var wire 1 Y out $end
$upscope $end
$scope module A1 $end
$var wire 1 Y a $end
$var wire 1 . b $end
$var wire 1 Z out $end
$var wire 1 \ temp $end
$upscope $end
$scope module A2 $end
$var wire 1 C a $end
$var wire 1 . b $end
$var wire 1 [ out $end
$var wire 1 ] temp $end
$upscope $end
$scope module O1 $end
$var wire 1 Z a $end
$var wire 1 [ b $end
$var wire 1 @ out $end
$var wire 1 ^ temp1 $end
$var wire 1 _ temp2 $end
$upscope $end
$upscope $end
$scope module M5 $end
$var wire 1 = a $end
$var wire 1 > b $end
$var wire 1 ` sel $end
$var wire 1 A out $end
$var wire 1 a not_sel $end
$var wire 1 b newa $end
$var wire 1 c newb $end
$scope module N1 $end
$var wire 1 ` a $end
$var wire 1 a out $end
$upscope $end
$scope module A1 $end
$var wire 1 a a $end
$var wire 1 = b $end
$var wire 1 b out $end
$var wire 1 d temp $end
$upscope $end
$scope module A2 $end
$var wire 1 ` a $end
$var wire 1 > b $end
$var wire 1 c out $end
$var wire 1 e temp $end
$upscope $end
$scope module O1 $end
$var wire 1 b a $end
$var wire 1 c b $end
$var wire 1 A out $end
$var wire 1 f temp1 $end
$var wire 1 g temp2 $end
$upscope $end
$upscope $end
$scope module M6 $end
$var wire 1 ? a $end
$var wire 1 @ b $end
$var wire 1 ` sel $end
$var wire 1 B out $end
$var wire 1 h not_sel $end
$var wire 1 i newa $end
$var wire 1 j newb $end
$scope module N1 $end
$var wire 1 ` a $end
$var wire 1 h out $end
$upscope $end
$scope module A1 $end
$var wire 1 h a $end
$var wire 1 ? b $end
$var wire 1 i out $end
$var wire 1 k temp $end
$upscope $end
$scope module A2 $end
$var wire 1 ` a $end
$var wire 1 @ b $end
$var wire 1 j out $end
$var wire 1 l temp $end
$upscope $end
$scope module O1 $end
$var wire 1 i a $end
$var wire 1 j b $end
$var wire 1 B out $end
$var wire 1 m temp1 $end
$var wire 1 n temp2 $end
$upscope $end
$upscope $end
$scope module M7 $end
$var wire 1 A a $end
$var wire 1 B b $end
$var wire 1 o sel $end
$var wire 1 $ out $end
$var wire 1 p not_sel $end
$var wire 1 q newa $end
$var wire 1 r newb $end
$scope module N1 $end
$var wire 1 o a $end
$var wire 1 p out $end
$upscope $end
$scope module A1 $end
$var wire 1 p a $end
$var wire 1 A b $end
$var wire 1 q out $end
$var wire 1 s temp $end
$upscope $end
$scope module A2 $end
$var wire 1 o a $end
$var wire 1 B b $end
$var wire 1 r out $end
$var wire 1 t temp $end
$upscope $end
$scope module O1 $end
$var wire 1 q a $end
$var wire 1 r b $end
$var wire 1 $ out $end
$var wire 1 u temp1 $end
$var wire 1 v temp2 $end
$upscope $end
$upscope $end
$upscope $end
$upscope $end
$upscope $end
$enddefinitions $end
#0
$dumpvars
0!
0"
b0 #
1$
0%
0&
b0 '
1(
0)
0*
1+
0,
1-
1.
1/
10
11
12
13
04
15
16
17
18
09
1:
1;
1<
1=
0>
0?
1@
1A
0B
0C
1D
1E
0F
0G
1H
0I
1J
1K
0L
0M
1N
1O
1P
1Q
1R
0S
0T
1U
1V
1W
1X
1Y
1Z
0[
0\
1]
0^
1_
0`
1a
1b
0c
0d
1e
0f
1g
1h
0i
0j
1k
1l
1m
1n
0o
1p
1q
0r
0s
1t
0u
1v
$end
#1000
1"
b0 #
1&
1(
1*
0+
1,
0-
1/
01
03
14
05
16
08
19
1:
0<
1>
1?
1B
1L
0N
1O
0P
1S
0U
1V
0W
1e
1i
0k
0m
1t
#2000
1!
0"
b0 #
1%
0&
1(
1*
1,
0.
1/
00
11
02
13
14
15
06
07
18
19
1:
0;
1<
0@
0Z
1\
1]
1^
1l
#3000
1!
1"
b0 #
0$
1&
0(
1)
1*
0,
1-
0/
01
03
14
15
16
08
19
0:
0<
0=
0?
0A
0B
0E
1G
1H
1I
0S
1U
1V
1W
0b
1d
1f
0i
1k
1m
0q
1s
1t
1u
#4000
0!
0"
b1 #
0$
0%
0&
b1 '
1(
0)
0*
1+
1-
1.
1/
10
11
12
13
04
15
16
17
18
09
1:
1;
1<
0=
1>
1?
1@
0A
1B
1C
0D
0F
1G
1H
1J
0K
0L
1M
1N
0O
1P
0Q
0R
1T
1U
0V
0X
0Y
1[
1\
0]
0_
0`
0b
1d
1e
1f
1i
0k
1l
0m
0o
0q
1s
1t
1u
#5000
0!
1"
b1 #
1&
1(
1*
0+
1,
0-
1/
01
03
14
05
16
08
19
1:
0<
0>
0?
0B
0M
1N
1O
1Q
0T
1U
1V
1X
1e
0i
1k
1m
1t
#6000
1!
0"
b1 #
1%
0&
1(
1*
1,
0.
1/
00
11
02
13
14
15
06
07
18
19
1:
0;
1<
0@
0[
1\
1]
1_
1l
#7000
1!
1"
b1 #
1$
1&
0(
1)
1*
0,
1-
0/
01
03
14
15
16
08
19
0:
0<
1=
1?
1A
1B
1F
1G
0H
0J
1T
1U
0V
0X
1b
0d
0f
1i
0k
0m
1q
0s
1t
0u
#8000
0!
0"
b10 #
0$
0%
0&
b10 '
1(
0)
0*
1+
1-
1.
1/
10
11
12
13
04
15
16
17
18
09
1:
1;
1<
1=
0>
0?
1@
0A
1B
0C
1D
1E
0F
0G
1H
0I
1J
1K
0L
1N
1O
1P
1R
0T
1U
1V
1X
1Y
1Z
0\
1]
0^
1`
0a
0b
0c
1d
1e
1f
1g
0h
0i
1j
1k
0l
1m
0n
0o
0q
1s
1t
1u
#9000
0!
1"
b10 #
1$
1&
1(
1*
0+
1,
0-
1/
01
03
14
05
16
08
19
1:
0<
1>
1?
1A
1L
0N
1O
0P
1S
0U
1V
0W
1c
0e
0g
1k
1q
0s
0u
#10000
1!
0"
b10 #
1%
0&
1(
1*
1,
0.
1/
00
11
02
13
14
15
06
07
18
19
1:
0;
1<
0@
0B
0Z
1\
1]
1^
0j
1l
1n
1t
#11000
1!
1"
b10 #
1&
0(
1)
1*
0,
1-
0/
01
03
14
15
16
08
19
0:
0<
0=
0?
0E
1G
1H
1I
0S
1U
1V
1W
1d
1k
#12000
0!
0"
b11 #
1$
0%
0&
b11 '
1(
0)
0*
1+
1-
1.
1/
10
11
12
13
04
15
16
17
18
09
1:
1;
1<
0=
1>
1?
1@
1A
1B
1C
0D
0F
1G
1H
1J
0K
0L
1M
1N
0O
1P
0Q
0R
1T
1U
0V
0X
0Y
1[
1\
0]
0_
1`
1c
1d
0e
0g
1j
1k
0l
0n
0o
1q
0s
1t
0u
#13000
0!
1"
b11 #
0$
1&
1(
1*
0+
1,
0-
1/
01
03
14
05
16
08
19
1:
0<
0>
0?
0A
0M
1N
1O
1Q
0T
1U
1V
1X
0c
1e
1g
1k
0q
1s
1u
#14000
1!
0"
b11 #
1%
0&
1(
1*
1,
0.
1/
00
11
02
13
14
15
06
07
18
19
1:
0;
1<
0@
0B
0[
1\
1]
1_
0j
1l
1n
1t
#15000
1!
1"
b11 #
1&
0(
1)
1*
0,
1-
0/
01
03
14
15
16
08
19
0:
0<
1=
1?
1F
1G
0H
0J
1T
1U
0V
0X
1d
1k
#16000
0!
0"
b100 #
0$
0%
0&
b100 '
1(
0)
0*
1+
1-
1.
1/
10
11
12
13
04
15
16
17
18
09
1:
1;
1<
1=
0>
0?
1@
1A
0B
0C
1D
1E
0F
0G
1H
0I
1J
1K
0L
1N
1O
1P
1R
0T
1U
1V
1X
1Y
1Z
0\
1]
0^
0`
1a
1b
0d
1e
0f
1h
0i
1k
1l
1m
1o
0p
0r
1s
1t
1v
#17000
0!
1"
b100 #
1$
1&
1(
1*
0+
1,
0-
1/
01
03
14
05
16
08
19
1:
0<
1>
1?
1B
1L
0N
1O
0P
1S
0U
1V
0W
1e
1i
0k
0m
1r
0t
0v
#18000
1!
0"
b100 #
1%
0&
1(
1*
1,
0.
1/
00
11
02
13
14
15
06
07
18
19
1:
0;
1<
0@
0Z
1\
1]
1^
1l
#19000
1!
1"
b100 #
0$
1&
0(
1)
1*
0,
1-
0/
01
03
14
15
16
08
19
0:
0<
0=
0?
0A
0B
0E
1G
1H
1I
0S
1U
1V
1W
0b
1d
1f
0i
1k
1m
0r
1s
1t
1v
#20000
0!
0"
b101 #
1$
0%
0&
b101 '
1(
0)
0*
1+
1-
1.
1/
10
11
12
13
04
15
16
17
18
09
1:
1;
1<
0=
1>
1?
1@
0A
1B
1C
0D
0F
1G
1H
1J
0K
0L
1M
1N
0O
1P
0Q
0R
1T
1U
0V
0X
0Y
1[
1\
0]
0_
0`
0b
1d
1e
1f
1i
0k
1l
0m
1o
1r
1s
0t
0v
#21000
0!
1"
b101 #
0$
1&
1(
1*
0+
1,
0-
1/
01
03
14
05
16
08
19
1:
0<
0>
0?
0B
0M
1N
1O
1Q
0T
1U
1V
1X
1e
0i
1k
1m
0r
1t
1v
#22000
1!
0"
b101 #
1%
0&
1(
1*
1,
0.
1/
00
11
02
13
14
15
06
07
18
19
1:
0;
1<
0@
0[
1\
1]
1_
1l
#23000
1!
1"
b101 #
1$
1&
0(
1)
1*
0,
1-
0/
01
03
14
15
16
08
19
0:
0<
1=
1?
1A
1B
1F
1G
0H
0J
1T
1U
0V
0X
1b
0d
0f
1i
0k
0m
1r
1s
0t
0v
#24000
0!
0"
b110 #
1$
0%
0&
b110 '
1(
0)
0*
1+
1-
1.
1/
10
11
12
13
04
15
16
17
18
09
1:
1;
1<
1=
0>
0?
1@
0A
1B
0C
1D
1E
0F
0G
1H
0I
1J
1K
0L
1N
1O
1P
1R
0T
1U
1V
1X
1Y
1Z
0\
1]
0^
1`
0a
0b
0c
1d
1e
1f
1g
0h
0i
1j
1k
0l
1m
0n
1o
1r
1s
0t
0v
#25000
0!
1"
b110 #
1&
1(
1*
0+
1,
0-
1/
01
03
14
05
16
08
19
1:
0<
1>
1?
1A
1L
0N
1O
0P
1S
0U
1V
0W
1c
0e
0g
1k
1s
#26000
1!
0"
b110 #
0$
1%
0&
1(
1*
1,
0.
1/
00
11
02
13
14
15
06
07
18
19
1:
0;
1<
0@
0B
0Z
1\
1]
1^
0j
1l
1n
0r
1t
1v
#27000
1!
1"
b110 #
1&
0(
1)
1*
0,
1-
0/
01
03
14
15
16
08
19
0:
0<
0=
0?
0E
1G
1H
1I
0S
1U
1V
1W
1d
1k
#28000
0!
0"
b111 #
1$
0%
0&
b111 '
1(
0)
0*
1+
1-
1.
1/
10
11
12
13
04
15
16
17
18
09
1:
1;
1<
0=
1>
1?
1@
1A
1B
1C
0D
0F
1G
1H
1J
0K
0L
1M
1N
0O
1P
0Q
0R
1T
1U
0V
0X
0Y
1[
1\
0]
0_
1`
1c
1d
0e
0g
1j
1k
0l
0n
1o
1r
1s
0t
0v
#29000
0!
1"
b111 #
1&
1(
1*
0+
1,
0-
1/
01
03
14
05
16
08
19
1:
0<
0>
0?
0A
0M
1N
1O
1Q
0T
1U
1V
1X
0c
1e
1g
1k
1s
#30000
1!
0"
b111 #
0$
1%
0&
1(
1*
1,
0.
1/
00
11
02
13
14
15
06
07
18
19
1:
0;
1<
0@
0B
0[
1\
1]
1_
0j
1l
1n
0r
1t
1v
#31000
1!
1"
b111 #
1&
0(
1)
1*
0,
1-
0/
01
03
14
15
16
08
19
0:
0<
1=
1?
1F
1G
0H
0J
1T
1U
0V
0X
1d
1k
#32000
0!
0"
b0 #
1$
0%
0&
b0 '
1(
0)
0*
1+
1-
1.
1/
10
11
12
13
04
15
16
17
18
09
1:
1;
1<
1=
0>
0?
1@
1A
0B
0C
1D
1E
0F
0G
1H
0I
1J
1K
0L
1N
1O
1P
1R
0T
1U
1V
1X
1Y
1Z
0\
1]
0^
0`
1a
1b
0d
1e
0f
1h
0i
1k
1l
1m
0o
1p
1q
0s
1t
0u
