Lab1/Advanced/1-3/Lab1_111062109_Crossbar_4x4_4bit.v
`timescale 1ns/1ps

module Dmux_1x2_4bit(in, a, b, sel);

input [4-1:0] in;
input sel;
output [4-1:0] a, b;
wire nsel;

not notsel(nsel, sel);
and anda1(a[0], in[0], nsel);
and anda2(a[1], in[1], nsel);
and anda3(a[2], in[2], nsel);
and anda4(a[3], in[3], nsel);

and andb1(b[0], in[0], sel);
and andb2(b[1], in[1], sel);
and andb3(b[2], in[2], sel);
and andb4(b[3], in[3], sel);

endmodule

module Mux_2x1_4bit(a, b, sel, f);
    input [4-1:0] a, b;
    input sel;
    output [4-1:0] f;

    wire not_sel;
    wire [4-1:0] newa, newb;
    not n1(not_sel, sel);
    and na1(newa[0], not_sel, a[0]);
    and na2(newa[1], not_sel, a[1]);
    and na3(newa[2], not_sel, a[2]);
    and na4(newa[3], not_sel, a[3]);
    and nb1(newb[0], sel, b[0]);
    and nb2(newb[1], sel, b[1]);
    and nb3(newb[2], sel, b[2]);
    and nb4(newb[3], sel, b[3]);
    or o1(f[0], newa[0], newb[0]);
    or o2(f[1], newa[1], newb[1]);
    or o3(f[2], newa[2], newb[2]);
    or o4(f[3], newa[3], newb[3]);

endmodule

module Crossbar_2x2_4bit(in1, in2, control, out1, out2);
input [4-1:0] in1, in2;
input control;
output [4-1:0] out1, out2;
wire [3:0] temp1, temp2, temp3, temp4;
wire ncontrol;

not notcontrol(ncontrol, control);
Dmux_1x2_4bit d1(.in(in1), .a(temp1), .b(temp2), .sel(control));
Dmux_1x2_4bit d2(.in(in2), .a(temp3), .b(temp4), .sel(ncontrol));

Mux_2x1_4bit m1(.a(temp1), .b(temp3), .sel(control), .f(out1));
Mux_2x1_4bit m2(.a(temp2), .b(temp4), .sel(ncontrol), .f(out2));

endmodule

module Crossbar_4x4_4bit(in1, in2, in3, in4, out1, out2, out3, out4, control);
input [4-1:0] in1, in2, in3, in4;
input [5-1:0] control;
output [4-1:0] out1, out2, out3, out4;

wire [4-1:0] temp1, temp2, temp3, temp4, temp5, temp6;

Crossbar_2x2_4bit c1(.in1(in1), .in2(in2), .control(control[0]), .out1(temp1), .out2(temp2));
Crossbar_2x2_4bit c2(.in1(in3), .in2(in4), .control(control[3]), .out1(temp3), .out2(temp4));
Crossbar_2x2_4bit c3(.in1(temp2), .in2(temp3), .control(control[2]), .out1(temp5), .out2(temp6));
Crossbar_2x2_4bit c4(.in1(temp1), .in2(temp5), .control(control[1]), .out1(out1), .out2(out2));
Crossbar_2x2_4bit c5(.in1(temp6), .in2(temp4), .control(control[4]), .out1(out3), .out2(out4));

endmodule

Lab1/Advanced/1-3/Lab1_111062109_Crossbar_4x4_4bit_t.v
`include "Lab1_111062109_Crossbar_4x4_4bit.v"
`timescale 1ns/1ps

module Crossbar_4x4_4bit_t;
reg [3:0] in1 = 4'b0001;
reg [3:0] in2 = 4'b0011;
reg [3:0] in3 = 4'b0101;
reg [3:0] in4 = 4'b0111;
reg [4:0] ctl = 5'b00000;
wire [3:0] o1, o2, o3, o4;

Crossbar_4x4_4bit C1(
    .in1 (in1), .in2 (in2), .in3 (in3), .in4 (in4),
    .control (ctl), 
    .out1 (o1), .out2 (o2), .out3 (o3), .out4 (o4)
);

initial begin
    repeat (2 ** 5) begin
        #1 ctl = ctl + 5'b00001;
        in1 = in1 + 4'b1;
        in2 = in2 + 4'b1;
        in3 = in3 + 4'b1;
        in4 = in4 + 4'b1;
    end
    #1 $finish;
end
endmodule

initial begin
     $dumpfile("Cbar_4x4.vcd");
     $dumpvars(0, Crossbar_4x4_4bit_t);
end

Lab1/Advanced/1-3/1-3.sim/sim_1/behav/xsim/Cbar_4x4.vcd
$date
   Thu Sep 28 10:52:04 2023
$end
$version
  2020.2
$end
$timescale
  1ps
$end
$scope module Crossbar_4x4_4bit_t $end
$var reg 4 ! in1 [3:0] $end
$var reg 4 " in2 [3:0] $end
$var reg 4 # in3 [3:0] $end
$var reg 4 $ in4 [3:0] $end
$var reg 5 % ctl [4:0] $end
$var wire 4 & o1 [3:0] $end
$var wire 4 ' o2 [3:0] $end
$var wire 4 ( o3 [3:0] $end
$var wire 4 ) o4 [3:0] $end
$scope module C1 $end
$var wire 4 * in1 [3:0] $end
$var wire 4 + in2 [3:0] $end
$var wire 4 , in3 [3:0] $end
$var wire 4 - in4 [3:0] $end
$var wire 5 . control [4:0] $end
$var wire 4 & out1 [3:0] $end
$var wire 4 ' out2 [3:0] $end
$var wire 4 ( out3 [3:0] $end
$var wire 4 ) out4 [3:0] $end
$var wire 4 / temp1 [3:0] $end
$var wire 4 0 temp2 [3:0] $end
$var wire 4 1 temp3 [3:0] $end
$var wire 4 2 temp4 [3:0] $end
$var wire 4 3 temp5 [3:0] $end
$var wire 4 4 temp6 [3:0] $end
$scope module c1 $end
$var wire 4 * in1 [3:0] $end
$var wire 4 + in2 [3:0] $end
$var wire 1 5 control $end
$var wire 4 / out1 [3:0] $end
$var wire 4 0 out2 [3:0] $end
$var wire 4 6 temp1 [3:0] $end
$var wire 4 7 temp2 [3:0] $end
$var wire 4 8 temp3 [3:0] $end
$var wire 4 9 temp4 [3:0] $end
$var wire 1 : ncontrol $end
$scope module d1 $end
$var wire 4 * in [3:0] $end
$var wire 1 5 sel $end
$var wire 4 6 a [3:0] $end
$var wire 4 7 b [3:0] $end
$var wire 1 ; nsel $end
$upscope $end
$scope module d2 $end
$var wire 4 + in [3:0] $end
$var wire 1 : sel $end
$var wire 4 8 a [3:0] $end
$var wire 4 9 b [3:0] $end
$var wire 1 < nsel $end
$upscope $end
$scope module m1 $end
$var wire 4 6 a [3:0] $end
$var wire 4 8 b [3:0] $end
$var wire 1 5 sel $end
$var wire 4 / f [3:0] $end
$var wire 1 = not_sel $end
$var wire 4 > newa [3:0] $end
$var wire 4 ? newb [3:0] $end
$upscope $end
$scope module m2 $end
$var wire 4 7 a [3:0] $end
$var wire 4 9 b [3:0] $end
$var wire 1 : sel $end
$var wire 4 0 f [3:0] $end
$var wire 1 @ not_sel $end
$var wire 4 A newa [3:0] $end
$var wire 4 B newb [3:0] $end
$upscope $end
$upscope $end
$scope module c2 $end
$var wire 4 , in1 [3:0] $end
$var wire 4 - in2 [3:0] $end
$var wire 1 C control $end
$var wire 4 1 out1 [3:0] $end
$var wire 4 2 out2 [3:0] $end
$var wire 4 D temp1 [3:0] $end
$var wire 4 E temp2 [3:0] $end
$var wire 4 F temp3 [3:0] $end
$var wire 4 G temp4 [3:0] $end
$var wire 1 H ncontrol $end
$scope module d1 $end
$var wire 4 , in [3:0] $end
$var wire 1 C sel $end
$var wire 4 D a [3:0] $end
$var wire 4 E b [3:0] $end
$var wire 1 I nsel $end
$upscope $end
$scope module d2 $end
$var wire 4 - in [3:0] $end
$var wire 1 H sel $end
$var wire 4 F a [3:0] $end
$var wire 4 G b [3:0] $end
$var wire 1 J nsel $end
$upscope $end
$scope module m1 $end
$var wire 4 D a [3:0] $end
$var wire 4 F b [3:0] $end
$var wire 1 C sel $end
$var wire 4 1 f [3:0] $end
$var wire 1 K not_sel $end
$var wire 4 L newa [3:0] $end
$var wire 4 M newb [3:0] $end
$upscope $end
$scope module m2 $end
$var wire 4 E a [3:0] $end
$var wire 4 G b [3:0] $end
$var wire 1 H sel $end
$var wire 4 2 f [3:0] $end
$var wire 1 N not_sel $end
$var wire 4 O newa [3:0] $end
$var wire 4 P newb [3:0] $end
$upscope $end
$upscope $end
$scope module c3 $end
$var wire 4 0 in1 [3:0] $end
$var wire 4 1 in2 [3:0] $end
$var wire 1 Q control $end
$var wire 4 3 out1 [3:0] $end
$var wire 4 4 out2 [3:0] $end
$var wire 4 R temp1 [3:0] $end
$var wire 4 S temp2 [3:0] $end
$var wire 4 T temp3 [3:0] $end
$var wire 4 U temp4 [3:0] $end
$var wire 1 V ncontrol $end
$scope module d1 $end
$var wire 4 0 in [3:0] $end
$var wire 1 Q sel $end
$var wire 4 R a [3:0] $end
$var wire 4 S b [3:0] $end
$var wire 1 W nsel $end
$upscope $end
$scope module d2 $end
$var wire 4 1 in [3:0] $end
$var wire 1 V sel $end
$var wire 4 T a [3:0] $end
$var wire 4 U b [3:0] $end
$var wire 1 X nsel $end
$upscope $end
$scope module m1 $end
$var wire 4 R a [3:0] $end
$var wire 4 T b [3:0] $end
$var wire 1 Q sel $end
$var wire 4 3 f [3:0] $end
$var wire 1 Y not_sel $end
$var wire 4 Z newa [3:0] $end
$var wire 4 [ newb [3:0] $end
$upscope $end
$scope module m2 $end
$var wire 4 S a [3:0] $end
$var wire 4 U b [3:0] $end
$var wire 1 V sel $end
$var wire 4 4 f [3:0] $end
$var wire 1 \ not_sel $end
$var wire 4 ] newa [3:0] $end
$var wire 4 ^ newb [3:0] $end
$upscope $end
$upscope $end
$scope module c4 $end
$var wire 4 / in1 [3:0] $end
$var wire 4 3 in2 [3:0] $end
$var wire 1 _ control $end
$var wire 4 & out1 [3:0] $end
$var wire 4 ' out2 [3:0] $end
$var wire 4 ` temp1 [3:0] $end
$var wire 4 a temp2 [3:0] $end
$var wire 4 b temp3 [3:0] $end
$var wire 4 c temp4 [3:0] $end
$var wire 1 d ncontrol $end
$scope module d1 $end
$var wire 4 / in [3:0] $end
$var wire 1 _ sel $end
$var wire 4 ` a [3:0] $end
$var wire 4 a b [3:0] $end
$var wire 1 e nsel $end
$upscope $end
$scope module d2 $end
$var wire 4 3 in [3:0] $end
$var wire 1 d sel $end
$var wire 4 b a [3:0] $end
$var wire 4 c b [3:0] $end
$var wire 1 f nsel $end
$upscope $end
$scope module m1 $end
$var wire 4 ` a [3:0] $end
$var wire 4 b b [3:0] $end
$var wire 1 _ sel $end
$var wire 4 & f [3:0] $end
$var wire 1 g not_sel $end
$var wire 4 h newa [3:0] $end
$var wire 4 i newb [3:0] $end
$upscope $end
$scope module m2 $end
$var wire 4 a a [3:0] $end
$var wire 4 c b [3:0] $end
$var wire 1 d sel $end
$var wire 4 ' f [3:0] $end
$var wire 1 j not_sel $end
$var wire 4 k newa [3:0] $end
$var wire 4 l newb [3:0] $end
$upscope $end
$upscope $end
$scope module c5 $end
$var wire 4 4 in1 [3:0] $end
$var wire 4 2 in2 [3:0] $end
$var wire 1 m control $end
$var wire 4 ( out1 [3:0] $end
$var wire 4 ) out2 [3:0] $end
$var wire 4 n temp1 [3:0] $end
$var wire 4 o temp2 [3:0] $end
$var wire 4 p temp3 [3:0] $end
$var wire 4 q temp4 [3:0] $end
$var wire 1 r ncontrol $end
$scope module d1 $end
$var wire 4 4 in [3:0] $end
$var wire 1 m sel $end
$var wire 4 n a [3:0] $end
$var wire 4 o b [3:0] $end
$var wire 1 s nsel $end
$upscope $end
$scope module d2 $end
$var wire 4 2 in [3:0] $end
$var wire 1 r sel $end
$var wire 4 p a [3:0] $end
$var wire 4 q b [3:0] $end
$var wire 1 t nsel $end
$upscope $end
$scope module m1 $end
$var wire 4 n a [3:0] $end
$var wire 4 p b [3:0] $end
$var wire 1 m sel $end
$var wire 4 ( f [3:0] $end
$var wire 1 u not_sel $end
$var wire 4 v newa [3:0] $end
$var wire 4 w newb [3:0] $end
$upscope $end
$scope module m2 $end
$var wire 4 o a [3:0] $end
$var wire 4 q b [3:0] $end
$var wire 1 r sel $end
$var wire 4 ) f [3:0] $end
$var wire 1 x not_sel $end
$var wire 4 y newa [3:0] $end
$var wire 4 z newb [3:0] $end
$upscope $end
$upscope $end
$upscope $end
$upscope $end
$enddefinitions $end
#0
$dumpvars
b1 !
b11 "
b101 #
b111 $
b0 %
b1 &
b11 '
b101 (
b111 )
b1 *
b11 +
b101 ,
b111 -
b0 .
b1 /
b11 0
b101 1
b111 2
b11 3
b101 4
05
b1 6
b0 7
b0 8
b11 9
1:
1;
0<
1=
b1 >
b0 ?
0@
b0 A
b11 B
0C
b101 D
b0 E
b0 F
b111 G
1H
1I
0J
1K
b101 L
b0 M
0N
b0 O
b111 P
0Q
b11 R
b0 S
b0 T
b101 U
1V
1W
0X
1Y
b11 Z
b0 [
0\
b0 ]
b101 ^
0_
b1 `
b0 a
b0 b
b11 c
1d
1e
0f
1g
b1 h
b0 i
0j
b0 k
b11 l
0m
b101 n
b0 o
b0 p
b111 q
1r
1s
0t
1u
b101 v
b0 w
0x
b0 y
b111 z
$end
#1000
b10 !
b100 "
b110 #
b1000 $
b1 %
b100 &
b10 '
b110 (
b1000 )
b10 *
b100 +
b110 ,
b1000 -
b1 .
b100 /
b10 0
b110 1
b1000 2
b10 3
b110 4
15
b0 6
b10 7
b100 8
b0 9
0:
0;
1<
0=
b0 >
b100 ?
1@
b10 A
b0 B
0C
b110 D
b0 E
b0 F
b1000 G
b110 L
b1000 P
0Q
b10 R
b0 S
b0 T
b110 U
b10 Z
b110 ^
0_
b100 `
b0 a
b0 b
b10 c
b100 h
b10 l
0m
b110 n
b0 o
b0 p
b1000 q
b110 v
b1000 z
#2000
b11 !
b101 "
b111 #
b1001 $
b10 %
b101 &
b11 '
b111 (
b1001 )
b11 *
b101 +
b111 ,
b1001 -
b10 .
b11 /
b101 0
b111 1
b1001 2
b101 3
b111 4
05
b11 6
b0 7
b0 8
b101 9
1:
1;
0<
1=
b11 >
b0 ?
0@
b0 A
b101 B
0C
b111 D
b0 E
b0 F
b1001 G
b111 L
b1001 P
0Q
b101 R
b0 S
b0 T
b111 U
b101 Z
b111 ^
1_
b0 `
b11 a
b101 b
b0 c
0d
0e
1f
0g
b0 h
b101 i
1j
b11 k
b0 l
0m
b111 n
b0 o
b0 p
b1001 q
b111 v
b1001 z
#3000
b100 !
b110 "
b1000 #
b1010 $
b11 %
b100 &
b110 '
b1000 (
b1010 )
b100 *
b110 +
b1000 ,
b1010 -
b11 .
b110 /
b100 0
b1000 1
b1010 2
b100 3
b1000 4
15
b0 6
b100 7
b110 8
b0 9
0:
0;
1<
0=
b0 >
b110 ?
1@
b100 A
b0 B
0C
b1000 D
b0 E
b0 F
b1010 G
b1000 L
b1010 P
0Q
b100 R
b0 S
b0 T
b1000 U
b100 Z
b1000 ^
1_
b0 `
b110 a
b100 b
b0 c
b100 i
b110 k
0m
b1000 n
b0 o
b0 p
b1010 q
b1000 v
b1010 z
#4000
b101 !
b111 "
b1001 #
b1011 $
b100 %
b101 &
b1001 '
b111 (
b1011 )
b101 *
b111 +
b1001 ,
b1011 -
b100 .
b101 /
b111 0
b1001 1
b1011 2
b1001 3
b111 4
05
b101 6
b0 7
b0 8
b111 9
1:
1;
0<
1=
b101 >
b0 ?
0@
b0 A
b111 B
0C
b1001 D
b0 E
b0 F
b1011 G
b1001 L
b1011 P
1Q
b0 R
b111 S
b1001 T
b0 U
0V
0W
1X
0Y
b0 Z
b1001 [
1\
b111 ]
b0 ^
0_
b101 `
b0 a
b0 b
b1001 c
1d
1e
0f
1g
b101 h
b0 i
0j
b0 k
b1001 l
0m
b111 n
b0 o
b0 p
b1011 q
b111 v
b1011 z
#5000
b110 !
b1000 "
b1010 #
b1100 $
b101 %
b1000 &
b1010 '
b110 (
b1100 )
b110 *
b1000 +
b1010 ,
b1100 -
b101 .
b1000 /
b110 0
b1010 1
b1100 2
b1010 3
b110 4
15
b0 6
b110 7
b1000 8
b0 9
0:
0;
1<
0=
b0 >
b1000 ?
1@
b110 A
b0 B
0C
b1010 D
b0 E
b0 F
b1100 G
b1010 L
b1100 P
1Q
b0 R
b110 S
b1010 T
b0 U
b1010 [
b110 ]
0_
b1000 `
b0 a
b0 b
b1010 c
b1000 h
b1010 l
0m
b110 n
b0 o
b0 p
b1100 q
b110 v
b1100 z
#6000
b111 !
b1001 "
b1011 #
b1101 $
b110 %
b1011 &
b111 '
b1001 (
b1101 )
b111 *
b1001 +
b1011 ,
b1101 -
b110 .
b111 /
b1001 0
b1011 1
b1101 2
b1011 3
b1001 4
05
b111 6
b0 7
b0 8
b1001 9
1:
1;
0<
1=
b111 >
b0 ?
0@
b0 A
b1001 B
0C
b1011 D
b0 E
b0 F
b1101 G
b1011 L
b1101 P
1Q
b0 R
b1001 S
b1011 T
b0 U
b1011 [
b1001 ]
1_
b0 `
b111 a
b1011 b
b0 c
0d
0e
1f
0g
b0 h
b1011 i
1j
b111 k
b0 l
0m
b1001 n
b0 o
b0 p
b1101 q
b1001 v
b1101 z
#7000
b1000 !
b1010 "
b1100 #
b1110 $
b111 %
b1100 &
b1010 '
b1000 (
b1110 )
b1000 *
b1010 +
b1100 ,
b1110 -
b111 .
b1010 /
b1000 0
b1100 1
b1110 2
b1100 3
b1000 4
15
b0 6
b1000 7
b1010 8
b0 9
0:
0;
1<
0=
b0 >
b1010 ?
1@
b1000 A
b0 B
0C
b1100 D
b0 E
b0 F
b1110 G
b1100 L
b1110 P
1Q
b0 R
b1000 S
b1100 T
b0 U
b1100 [
b1000 ]
1_
b0 `
b1010 a
b1100 b
b0 c
b1100 i
b1010 k
0m
b1000 n
b0 o
b0 p
b1110 q
b1000 v
b1110 z
#8000
b1001 !
b1011 "
b1101 #
b1111 $
b1000 %
b1001 &
b1011 '
b1111 (
b1101 )
b1001 *
b1011 +
b1101 ,
b1111 -
b1000 .
b1001 /
b1011 0
b1111 1
b1101 2
b1011 3
b1111 4
05
b1001 6
b0 7
b0 8
b1011 9
1:
1;
0<
1=
b1001 >
b0 ?
0@
b0 A
b1011 B
1C
b0 D
b1101 E
b1111 F
b0 G
0H
0I
1J
0K
b0 L
b1111 M
1N
b1101 O
b0 P
0Q
b1011 R
b0 S
b0 T
b1111 U
1V
1W
0X
1Y
b1011 Z
b0 [
0\
b0 ]
b1111 ^
0_
b1001 `
b0 a
b0 b
b1011 c
1d
1e
0f
1g
b1001 h
b0 i
0j
b0 k
b1011 l
0m
b1111 n
b0 o
b0 p
b1101 q
b1111 v
b1101 z
#9000
b1010 !
b1100 "
b1110 #
b0 $
b1001 %
b1100 &
b1010 '
b0 (
b1110 )
b1010 *
b1100 +
b1110 ,
b0 -
b1001 .
b1100 /
b1010 0
b0 1
b1110 2
b1010 3
b0 4
15
b0 6
b1010 7
b1100 8
b0 9
0:
0;
1<
0=
b0 >
b1100 ?
1@
b1010 A
b0 B
1C
b0 D
b1110 E
b0 F
b0 G
b0 M
b1110 O
0Q
b1010 R
b0 S
b0 T
b0 U
b1010 Z
b0 ^
0_
b1100 `
b0 a
b0 b
b1010 c
b1100 h
b1010 l
0m
b0 n
b0 o
b0 p
b1110 q
b0 v
b1110 z
#10000
b1011 !
b1101 "
b1111 #
b1 $
b1010 %
b1101 &
b1011 '
b1 (
b1111 )
b1011 *
b1101 +
b1111 ,
b1 -
b1010 .
b1011 /
b1101 0
b1 1
b1111 2
b1101 3
b1 4
05
b1011 6
b0 7
b0 8
b1101 9
1:
1;
0<
1=
b1011 >
b0 ?
0@
b0 A
b1101 B
1C
b0 D
b1111 E
b1 F
b0 G
b1 M
b1111 O
0Q
b1101 R
b0 S
b0 T
b1 U
b1101 Z
b1 ^
1_
b0 `
b1011 a
b1101 b
b0 c
0d
0e
1f
0g
b0 h
b1101 i
1j
b1011 k
b0 l
0m
b1 n
b0 o
b0 p
b1111 q
b1 v
b1111 z
#11000
b1100 !
b1110 "
b0 #
b10 $
b1011 %
b1100 &
b1110 '
b10 (
b0 )
b1100 *
b1110 +
b0 ,
b10 -
b1011 .
b1110 /
b1100 0
b10 1
b0 2
b1100 3
b10 4
15
b0 6
b1100 7
b1110 8
b0 9
0:
0;
1<
0=
b0 >
b1110 ?
1@
b1100 A
b0 B
1C
b0 D
b0 E
b10 F
b0 G
b10 M
b0 O
0Q
b1100 R
b0 S
b0 T
b10 U
b1100 Z
b10 ^
1_
b0 `
b1110 a
b1100 b
b0 c
b1100 i
b1110 k
0m
b10 n
b0 o
b0 p
b0 q
b10 v
b0 z
#12000
b1101 !
b1111 "
b1 #
b11 $
b1100 %
b1101 &
b11 '
b1111 (
b1 )
b1101 *
b1111 +
b1 ,
b11 -
b1100 .
b1101 /
b1111 0
b11 1
b1 2
b11 3
b1111 4
05
b1101 6
b0 7
b0 8
b1111 9
1:
1;
0<
1=
b1101 >
b0 ?
0@
b0 A
b1111 B
1C
b0 D
b1 E
b11 F
b0 G
b11 M
b1 O
1Q
b0 R
b1111 S
b11 T
b0 U
0V
0W
1X
0Y
b0 Z
b11 [
1\
b1111 ]
b0 ^
0_
b1101 `
b0 a
b0 b
b11 c
1d
1e
0f
1g
b1101 h
b0 i
0j
b0 k
b11 l
0m
b1111 n
b0 o
b0 p
b1 q
b1111 v
b1 z
#13000
b1110 !
b0 "
b10 #
b100 $
b1101 %
b0 &
b100 '
b1110 (
b10 )
b1110 *
b0 +
b10 ,
b100 -
b1101 .
b0 /
b1110 0
b100 1
b10 2
b100 3
b1110 4
15
b0 6
b1110 7
b0 8
b0 9
0:
0;
1<
0=
b0 >
b0 ?
1@
b1110 A
b0 B
1C
b0 D
b10 E
b100 F
b0 G
b100 M
b10 O
1Q
b0 R
b1110 S
b100 T
b0 U
b100 [
b1110 ]
0_
b0 `
b0 a
b0 b
b100 c
b0 h
b100 l
0m
b1110 n
b0 o
b0 p
b10 q
b1110 v
b10 z
#14000
b1111 !
b1 "
b11 #
b101 $
b1110 %
b101 &
b1111 '
b1 (
b11 )
b1111 *
b1 +
b11 ,
b101 -
b1110 .
b1111 /
b1 0
b101 1
b11 2
b101 3
b1 4
05
b1111 6
b0 7
b0 8
b1 9
1:
1;
0<
1=
b1111 >
b0 ?
0@
b0 A
b1 B
1C
b0 D
b11 E
b101 F
b0 G
b101 M
b11 O
1Q
b0 R
b1 S
b101 T
b0 U
b101 [
b1 ]
1_
b0 `
b1111 a
b101 b
b0 c
0d
0e
1f
0g
b0 h
b101 i
1j
b1111 k
b0 l
0m
b1 n
b0 o
b0 p
b11 q
b1 v
b11 z
#15000
b0 !
b10 "
b100 #
b110 $
b1111 %
b110 &
b10 '
b0 (
b100 )
b0 *
b10 +
b100 ,
b110 -
b1111 .
b10 /
b0 0
b110 1
b100 2
b110 3
b0 4
15
b0 6
b0 7
b10 8
b0 9
0:
0;
1<
0=
b0 >
b10 ?
1@
b0 A
b0 B
1C
b0 D
b100 E
b110 F
b0 G
b110 M
b100 O
1Q
b0 R
b0 S
b110 T
b0 U
b110 [
b0 ]
1_
b0 `
b10 a
b110 b
b0 c
b110 i
b10 k
0m
b0 n
b0 o
b0 p
b100 q
b0 v
b100 z
#16000
b1 !
b11 "
b101 #
b111 $
b10000 %
b1 &
b11 '
b111 (
b101 )
b1 *
b11 +
b101 ,
b111 -
b10000 .
b1 /
b11 0
b101 1
b111 2
b11 3
b101 4
05
b1 6
b0 7
b0 8
b11 9
1:
1;
0<
1=
b1 >
b0 ?
0@
b0 A
b11 B
0C
b101 D
b0 E
b0 F
b111 G
1H
1I
0J
1K
b101 L
b0 M
0N
b0 O
b111 P
0Q
b11 R
b0 S
b0 T
b101 U
1V
1W
0X
1Y
b11 Z
b0 [
0\
b0 ]
b101 ^
0_
b1 `
b0 a
b0 b
b11 c
1d
1e
0f
1g
b1 h
b0 i
0j
b0 k
b11 l
1m
b0 n
b101 o
b111 p
b0 q
0r
0s
1t
0u
b0 v
b111 w
1x
b101 y
b0 z
#17000
b10 !
b100 "
b110 #
b1000 $
b10001 %
b100 &
b10 '
b1000 (
b110 )
b10 *
b100 +
b110 ,
b1000 -
b10001 .
b100 /
b10 0
b110 1
b1000 2
b10 3
b110 4
15
b0 6
b10 7
b100 8
b0 9
0:
0;
1<
0=
b0 >
b100 ?
1@
b10 A
b0 B
0C
b110 D
b0 E
b0 F
b1000 G
b110 L
b1000 P
0Q
b10 R
b0 S
b0 T
b110 U
b10 Z
b110 ^
0_
b100 `
b0 a
b0 b
b10 c
b100 h
b10 l
1m
b0 n
b110 o
b1000 p
b0 q
b1000 w
b110 y
#18000
b11 !
b101 "
b111 #
b1001 $
b10010 %
b101 &
b11 '
b1001 (
b111 )
b11 *
b101 +
b111 ,
b1001 -
b10010 .
b11 /
b101 0
b111 1
b1001 2
b101 3
b111 4
05
b11 6
b0 7
b0 8
b101 9
1:
1;
0<
1=
b11 >
b0 ?
0@
b0 A
b101 B
0C
b111 D
b0 E
b0 F
b1001 G
b111 L
b1001 P
0Q
b101 R
b0 S
b0 T
b111 U
b101 Z
b111 ^
1_
b0 `
b11 a
b101 b
b0 c
0d
0e
1f
0g
b0 h
b101 i
1j
b11 k
b0 l
1m
b0 n
b111 o
b1001 p
b0 q
b1001 w
b111 y
#19000
b100 !
b110 "
b1000 #
b1010 $
b10011 %
b100 &
b110 '
b1010 (
b1000 )
b100 *
b110 +
b1000 ,
b1010 -
b10011 .
b110 /
b100 0
b1000 1
b1010 2
b100 3
b1000 4
15
b0 6
b100 7
b110 8
b0 9
0:
0;
1<
0=
b0 >
b110 ?
1@
b100 A
b0 B
0C
b1000 D
b0 E
b0 F
b1010 G
b1000 L
b1010 P
0Q
b100 R
b0 S
b0 T
b1000 U
b100 Z
b1000 ^
1_
b0 `
b110 a
b100 b
b0 c
b100 i
b110 k
1m
b0 n
b1000 o
b1010 p
b0 q
b1010 w
b1000 y
#20000
b101 !
b111 "
b1001 #
b1011 $
b10100 %
b101 &
b1001 '
b1011 (
b111 )
b101 *
b111 +
b1001 ,
b1011 -
b10100 .
b101 /
b111 0
b1001 1
b1011 2
b1001 3
b111 4
05
b101 6
b0 7
b0 8
b111 9
1:
1;
0<
1=
b101 >
b0 ?
0@
b0 A
b111 B
0C
b1001 D
b0 E
b0 F
b1011 G
b1001 L
b1011 P
1Q
b0 R
b111 S
b1001 T
b0 U
0V
0W
1X
0Y
b0 Z
b1001 [
1\
b111 ]
b0 ^
0_
b101 `
b0 a
b0 b
b1001 c
1d
1e
0f
1g
b101 h
b0 i
0j
b0 k
b1001 l
1m
b0 n
b111 o
b1011 p
b0 q
b1011 w
b111 y
#21000
b110 !
b1000 "
b1010 #
b1100 $
b10101 %
b1000 &
b1010 '
b1100 (
b110 )
b110 *
b1000 +
b1010 ,
b1100 -
b10101 .
b1000 /
b110 0
b1010 1
b1100 2
b1010 3
b110 4
15
b0 6
b110 7
b1000 8
b0 9
0:
0;
1<
0=
b0 >
b1000 ?
1@
b110 A
b0 B
0C
b1010 D
b0 E
b0 F
b1100 G
b1010 L
b1100 P
1Q
b0 R
b110 S
b1010 T
b0 U
b1010 [
b110 ]
0_
b1000 `
b0 a
b0 b
b1010 c
b1000 h
b1010 l
1m
b0 n
b110 o
b1100 p
b0 q
b1100 w
b110 y
#22000
b111 !
b1001 "
b1011 #
b1101 $
b10110 %
b1011 &
b111 '
b1101 (
b1001 )
b111 *
b1001 +
b1011 ,
b1101 -
b10110 .
b111 /
b1001 0
b1011 1
b1101 2
b1011 3
b1001 4
05
b111 6
b0 7
b0 8
b1001 9
1:
1;
0<
1=
b111 >
b0 ?
0@
b0 A
b1001 B
0C
b1011 D
b0 E
b0 F
b1101 G
b1011 L
b1101 P
1Q
b0 R
b1001 S
b1011 T
b0 U
b1011 [
b1001 ]
1_
b0 `
b111 a
b1011 b
b0 c
0d
0e
1f
0g
b0 h
b1011 i
1j
b111 k
b0 l
1m
b0 n
b1001 o
b1101 p
b0 q
b1101 w
b1001 y
#23000
b1000 !
b1010 "
b1100 #
b1110 $
b10111 %
b1100 &
b1010 '
b1110 (
b1000 )
b1000 *
b1010 +
b1100 ,
b1110 -
b10111 .
b1010 /
b1000 0
b1100 1
b1110 2
b1100 3
b1000 4
15
b0 6
b1000 7
b1010 8
b0 9
0:
0;
1<
0=
b0 >
b1010 ?
1@
b1000 A
b0 B
0C
b1100 D
b0 E
b0 F
b1110 G
b1100 L
b1110 P
1Q
b0 R
b1000 S
b1100 T
b0 U
b1100 [
b1000 ]
1_
b0 `
b1010 a
b1100 b
b0 c
b1100 i
b1010 k
1m
b0 n
b1000 o
b1110 p
b0 q
b1110 w
b1000 y
#24000
b1001 !
b1011 "
b1101 #
b1111 $
b11000 %
b1001 &
b1011 '
b1101 (
b1111 )
b1001 *
b1011 +
b1101 ,
b1111 -
b11000 .
b1001 /
b1011 0
b1111 1
b1101 2
b1011 3
b1111 4
05
b1001 6
b0 7
b0 8
b1011 9
1:
1;
0<
1=
b1001 >
b0 ?
0@
b0 A
b1011 B
1C
b0 D
b1101 E
b1111 F
b0 G
0H
0I
1J
0K
b0 L
b1111 M
1N
b1101 O
b0 P
0Q
b1011 R
b0 S
b0 T
b1111 U
1V
1W
0X
1Y
b1011 Z
b0 [
0\
b0 ]
b1111 ^
0_
b1001 `
b0 a
b0 b
b1011 c
1d
1e
0f
1g
b1001 h
b0 i
0j
b0 k
b1011 l
1m
b0 n
b1111 o
b1101 p
b0 q
b1101 w
b1111 y
#25000
b1010 !
b1100 "
b1110 #
b0 $
b11001 %
b1100 &
b1010 '
b1110 (
b0 )
b1010 *
b1100 +
b1110 ,
b0 -
b11001 .
b1100 /
b1010 0
b0 1
b1110 2
b1010 3
b0 4
15
b0 6
b1010 7
b1100 8
b0 9
0:
0;
1<
0=
b0 >
b1100 ?
1@
b1010 A
b0 B
1C
b0 D
b1110 E
b0 F
b0 G
b0 M
b1110 O
0Q
b1010 R
b0 S
b0 T
b0 U
b1010 Z
b0 ^
0_
b1100 `
b0 a
b0 b
b1010 c
b1100 h
b1010 l
1m
b0 n
b0 o
b1110 p
b0 q
b1110 w
b0 y
