Lab2/Advanced/2-5/Ripple_Carry_Adder.v
`timescale 1ns/1ps
module AND(out, a, b);
    input a, b;
    output out;
    wire temp;
    nand n1 (temp, a, b);
    nand n2 (out, temp, temp);
endmodule

module OR(out, a, b);
    input a, b;
    output out;
    wire temp1, temp2;
    nand n1 (temp1, a, a);
    nand n2 (temp2, b, b);
    nand n3 (out, temp1, temp2);
endmodule

module XOR(out, a, b);
    input a, b;
    output out;
    wire temp1, temp2, na, nb;
    nand n1 (na, a, a);
    nand n2 (nb, b, b);
    nand n3 (temp1, na, b);
    nand n4 (temp2, nb, a);
    nand n5 (out, temp1, temp2);
endmodule

module Majority(a, b, c, out);
    input a, b, c;
    output out;
    wire temp1, temp2, temp3, temp4, temp5, temp6;
    AND A1 (temp1, a, b);
    AND A2 (temp2, a, c);
    AND A3 (temp3, b, c);
    OR O1 (temp4, temp1, temp2);
    OR O2 (out, temp4, temp3);
endmodule

module Full_Adder (a, b, cin, cout, sum);
    input a, b, cin;
    output cout, sum;
    wire temp1;
    Majority M1 (a, b, cin, cout);
    XOR X1 (temp1, a, b);
    XOR X2 (sum, temp1, cin);
endmodule

module Ripple_Carry_Adder(a, b, cin, cout, sum);
    input [4-1:0] a, b;
    input cin;
    output cout;
    wire eater;
    output [4-1:0] sum;
    wire [3-1:0] tempcin;
    Full_Adder F1 (a[0], b[0], cin, tempcin[0], sum[0]);
    Full_Adder F2 (a[1], b[1], tempcin[0], tempcin[1], sum[1]);
    Full_Adder F3 (a[2], b[2], tempcin[0], tempcin[2], sum[2]);
    Full_Adder F4 (a[3], b[3], tempcin[2], cout, sum[3]);
endmodule

Lab2/Advanced/2-5/Lab2_111062109_Exhausted_Testing.v
`timescale 1ns/1ps

module Exhausted_Testing(a, b, cin, error, done);
output [4-1:0] a, b;
output cin;
output error;
output done;

// input signal to the test instance.
reg [4-1:0] a = 4'b0000;
reg [4-1:0] b = 4'b0000;
reg cin = 1'b0;

// initial value for the done and error indicator: not done, no error
reg done = 1'b0;
reg error = 1'b0;

// output from the test instance.
wire [4-1:0] sum;
wire cout;

// instantiate the test instance.
Ripple_Carry_Adder rca(
    .a (a), 
    .b (b), 
    .cin (cin),
    .cout (cout),
    .sum (sum)
);

reg [4:0] testsum;

initial begin
    repeat(16) begin
        repeat(16) begin
            #1 testsum = a + b + cin;
            if ({cout, sum} === testsum ) begin
                error = 1'b0;
            end
            else begin
                error = 1'b1;
            end
            #4 b = b + 1;
        end
        a = a + 1;
    end
    done = 1'b1;
    #5 done = 1'b0;
end

endmodule

Lab2/Advanced/2-5/Exhausted_Testing.vcd
$date
	Sun Oct  8 11:02:50 2023
$end
$version
	Icarus Verilog
$end
$timescale
	1ps
$end
$scope module Exhausted_Testing $end
$var wire 4 ! sum [3:0] $end
$var wire 1 " cout $end
$var reg 4 # a [3:0] $end
$var reg 4 $ b [3:0] $end
$var reg 1 % cin $end
$var reg 1 & done $end
$var reg 1 ' error $end
$var reg 5 ( testsum [4:0] $end
$scope module rca $end
$var wire 4 ) a [3:0] $end
$var wire 4 * b [3:0] $end
$var wire 1 % cin $end
$var wire 3 + tempcin [2:0] $end
$var wire 4 , sum [3:0] $end
$var wire 1 " cout $end
$scope module F1 $end
$var wire 1 - a $end
$var wire 1 . b $end
$var wire 1 % cin $end
$var wire 1 / temp1 $end
$var wire 1 0 sum $end
$var wire 1 1 cout $end
$scope module M1 $end
$var wire 1 - a $end
$var wire 1 . b $end
$var wire 1 % c $end
$var wire 1 2 temp4 $end
$var wire 1 3 temp3 $end
$var wire 1 4 temp2 $end
$var wire 1 5 temp1 $end
$var wire 1 1 out $end
$scope module A1 $end
$var wire 1 - a $end
$var wire 1 . b $end
$var wire 1 5 out $end
$var wire 1 6 temp $end
$upscope $end
$scope module A2 $end
$var wire 1 - a $end
$var wire 1 % b $end
$var wire 1 4 out $end
$var wire 1 7 temp $end
$upscope $end
$scope module A3 $end
$var wire 1 . a $end
$var wire 1 % b $end
$var wire 1 3 out $end
$var wire 1 8 temp $end
$upscope $end
$scope module O1 $end
$var wire 1 5 a $end
$var wire 1 4 b $end
$var wire 1 2 out $end
$var wire 1 9 temp1 $end
$var wire 1 : temp2 $end
$upscope $end
$scope module O2 $end
$var wire 1 2 a $end
$var wire 1 3 b $end
$var wire 1 1 out $end
$var wire 1 ; temp1 $end
$var wire 1 < temp2 $end
$upscope $end
$upscope $end
$scope module X1 $end
$var wire 1 - a $end
$var wire 1 . b $end
$var wire 1 = na $end
$var wire 1 > nb $end
$var wire 1 / out $end
$var wire 1 ? temp1 $end
$var wire 1 @ temp2 $end
$upscope $end
$scope module X2 $end
$var wire 1 / a $end
$var wire 1 % b $end
$var wire 1 A na $end
$var wire 1 B nb $end
$var wire 1 0 out $end
$var wire 1 C temp1 $end
$var wire 1 D temp2 $end
$upscope $end
$upscope $end
$scope module F2 $end
$var wire 1 E a $end
$var wire 1 F b $end
$var wire 1 G cin $end
$var wire 1 H temp1 $end
$var wire 1 I sum $end
$var wire 1 J cout $end
$scope module M1 $end
$var wire 1 E a $end
$var wire 1 F b $end
$var wire 1 G c $end
$var wire 1 K temp4 $end
$var wire 1 L temp3 $end
$var wire 1 M temp2 $end
$var wire 1 N temp1 $end
$var wire 1 J out $end
$scope module A1 $end
$var wire 1 E a $end
$var wire 1 F b $end
$var wire 1 N out $end
$var wire 1 O temp $end
$upscope $end
$scope module A2 $end
$var wire 1 E a $end
$var wire 1 G b $end
$var wire 1 M out $end
$var wire 1 P temp $end
$upscope $end
$scope module A3 $end
$var wire 1 F a $end
$var wire 1 G b $end
$var wire 1 L out $end
$var wire 1 Q temp $end
$upscope $end
$scope module O1 $end
$var wire 1 N a $end
$var wire 1 M b $end
$var wire 1 K out $end
$var wire 1 R temp1 $end
$var wire 1 S temp2 $end
$upscope $end
$scope module O2 $end
$var wire 1 K a $end
$var wire 1 L b $end
$var wire 1 J out $end
$var wire 1 T temp1 $end
$var wire 1 U temp2 $end
$upscope $end
$upscope $end
$scope module X1 $end
$var wire 1 E a $end
$var wire 1 F b $end
$var wire 1 V na $end
$var wire 1 W nb $end
$var wire 1 H out $end
$var wire 1 X temp1 $end
$var wire 1 Y temp2 $end
$upscope $end
$scope module X2 $end
$var wire 1 H a $end
$var wire 1 G b $end
$var wire 1 Z na $end
$var wire 1 [ nb $end
$var wire 1 I out $end
$var wire 1 \ temp1 $end
$var wire 1 ] temp2 $end
$upscope $end
$upscope $end
$scope module F3 $end
$var wire 1 ^ a $end
$var wire 1 _ b $end
$var wire 1 ` cin $end
$var wire 1 a temp1 $end
$var wire 1 b sum $end
$var wire 1 c cout $end
$scope module M1 $end
$var wire 1 ^ a $end
$var wire 1 _ b $end
$var wire 1 ` c $end
$var wire 1 d temp4 $end
$var wire 1 e temp3 $end
$var wire 1 f temp2 $end
$var wire 1 g temp1 $end
$var wire 1 c out $end
$scope module A1 $end
$var wire 1 ^ a $end
$var wire 1 _ b $end
$var wire 1 g out $end
$var wire 1 h temp $end
$upscope $end
$scope module A2 $end
$var wire 1 ^ a $end
$var wire 1 ` b $end
$var wire 1 f out $end
$var wire 1 i temp $end
$upscope $end
$scope module A3 $end
$var wire 1 _ a $end
$var wire 1 ` b $end
$var wire 1 e out $end
$var wire 1 j temp $end
$upscope $end
$scope module O1 $end
$var wire 1 g a $end
$var wire 1 f b $end
$var wire 1 d out $end
$var wire 1 k temp1 $end
$var wire 1 l temp2 $end
$upscope $end
$scope module O2 $end
$var wire 1 d a $end
$var wire 1 e b $end
$var wire 1 c out $end
$var wire 1 m temp1 $end
$var wire 1 n temp2 $end
$upscope $end
$upscope $end
$scope module X1 $end
$var wire 1 ^ a $end
$var wire 1 _ b $end
$var wire 1 o na $end
$var wire 1 p nb $end
$var wire 1 a out $end
$var wire 1 q temp1 $end
$var wire 1 r temp2 $end
$upscope $end
$scope module X2 $end
$var wire 1 a a $end
$var wire 1 ` b $end
$var wire 1 s na $end
$var wire 1 t nb $end
$var wire 1 b out $end
$var wire 1 u temp1 $end
$var wire 1 v temp2 $end
$upscope $end
$upscope $end
$scope module F4 $end
$var wire 1 w a $end
$var wire 1 x b $end
$var wire 1 y cin $end
$var wire 1 z temp1 $end
$var wire 1 { sum $end
$var wire 1 " cout $end
$scope module M1 $end
$var wire 1 w a $end
$var wire 1 x b $end
$var wire 1 y c $end
$var wire 1 | temp4 $end
$var wire 1 } temp3 $end
$var wire 1 ~ temp2 $end
$var wire 1 !" temp1 $end
$var wire 1 " out $end
$scope module A1 $end
$var wire 1 w a $end
$var wire 1 x b $end
$var wire 1 !" out $end
$var wire 1 "" temp $end
$upscope $end
$scope module A2 $end
$var wire 1 w a $end
$var wire 1 y b $end
$var wire 1 ~ out $end
$var wire 1 #" temp $end
$upscope $end
$scope module A3 $end
$var wire 1 x a $end
$var wire 1 y b $end
$var wire 1 } out $end
$var wire 1 $" temp $end
$upscope $end
$scope module O1 $end
$var wire 1 !" a $end
$var wire 1 ~ b $end
$var wire 1 | out $end
$var wire 1 %" temp1 $end
$var wire 1 &" temp2 $end
$upscope $end
$scope module O2 $end
$var wire 1 | a $end
$var wire 1 } b $end
$var wire 1 " out $end
$var wire 1 '" temp1 $end
$var wire 1 (" temp2 $end
$upscope $end
$upscope $end
$scope module X1 $end
$var wire 1 w a $end
$var wire 1 x b $end
$var wire 1 )" na $end
$var wire 1 *" nb $end
$var wire 1 z out $end
$var wire 1 +" temp1 $end
$var wire 1 ," temp2 $end
$upscope $end
$scope module X2 $end
$var wire 1 z a $end
$var wire 1 y b $end
$var wire 1 -" na $end
$var wire 1 ." nb $end
$var wire 1 { out $end
$var wire 1 /" temp1 $end
$var wire 1 0" temp2 $end
$upscope $end
$upscope $end
$upscope $end
$upscope $end
$enddefinitions $end
#0
$dumpvars
10"
1/"
1."
1-"
1,"
1+"
1*"
1)"
1("
1'"
1&"
1%"
1$"
1#"
1""
0!"
0~
0}
0|
0{
0z
0y
0x
0w
1v
1u
1t
1s
1r
1q
1p
1o
1n
1m
1l
1k
1j
1i
1h
0g
0f
0e
0d
0c
0b
0a
0`
0_
0^
1]
1\
1[
1Z
1Y
1X
1W
1V
1U
1T
1S
1R
1Q
1P
1O
0N
0M
0L
0K
0J
0I
0H
0G
0F
0E
1D
1C
1B
1A
1@
1?
1>
1=
1<
1;
1:
19
18
17
16
05
04
03
02
01
00
0/
0.
0-
b0 ,
b0 +
b0 *
b0 )
bx (
0'
0&
0%
b0 $
b0 #
0"
b0 !
$end
#1000
b0 (
#5000
b1 !
b1 ,
10
0A
0D
1/
0>
0?
1.
b1 $
b1 *
#6000
b1 (
#10000
00
b10 !
b10 ,
1I
1A
1D
0Z
0]
0/
1H
1>
1?
0W
0X
0.
1F
b10 $
b10 *
#11000
b10 (
#15000
b11 !
b11 ,
10
0A
0D
1/
0>
0?
1.
b11 $
b11 *
#16000
b11 (
#20000
00
0I
b100 !
b100 ,
1b
1A
1D
1Z
1]
0s
0v
0/
0H
1a
1>
1?
1W
1X
0p
0q
0.
0F
1_
b100 $
b100 *
#21000
b100 (
#25000
b101 !
b101 ,
10
0A
0D
1/
0>
0?
1.
b101 $
b101 *
#26000
b101 (
#30000
00
b110 !
b110 ,
1I
1A
1D
0Z
0]
0/
1H
1>
1?
0W
0X
0.
1F
b110 $
b110 *
#31000
b110 (
#35000
b111 !
b111 ,
10
0A
0D
1/
0>
0?
1.
b111 $
b111 *
#36000
b111 (
#40000
00
0I
0b
b1000 !
b1000 ,
1{
1A
1D
1Z
1]
1s
1v
0-"
00"
0/
0H
0a
1z
1>
1?
1W
1X
1p
1q
0*"
0+"
0.
0F
0_
1x
b1000 $
b1000 *
#41000
b1000 (
#45000
b1001 !
b1001 ,
10
0A
0D
1/
0>
0?
1.
b1001 $
b1001 *
#46000
b1001 (
#50000
00
b1010 !
b1010 ,
1I
1A
1D
0Z
0]
0/
1H
1>
1?
0W
0X
0.
1F
b1010 $
b1010 *
#51000
b1010 (
#55000
b1011 !
b1011 ,
10
0A
0D
1/
0>
0?
1.
b1011 $
b1011 *
#56000
b1011 (
#60000
00
0I
b1100 !
b1100 ,
1b
1A
1D
1Z
1]
0s
0v
0/
0H
1a
1>
1?
1W
1X
0p
0q
0.
0F
1_
b1100 $
b1100 *
#61000
b1100 (
#65000
b1101 !
b1101 ,
10
0A
0D
1/
0>
0?
1.
b1101 $
b1101 *
#66000
b1101 (
#70000
00
b1110 !
b1110 ,
1I
1A
1D
0Z
0]
0/
1H
1>
1?
0W
0X
0.
1F
b1110 $
b1110 *
#71000
b1110 (
#75000
b1111 !
b1111 ,
10
0A
0D
1/
0>
0?
1.
b1111 $
b1111 *
#76000
b1111 (
#80000
0I
0b
b1 !
b1 ,
0{
1Z
1]
1s
1v
1-"
10"
0H
0a
0z
0=
0@
1>
1?
1W
1X
1p
1q
1*"
1+"
1-
0.
0F
0_
0x
b1 #
b1 )
b0 $
b0 *
#81000
b1 (
#85000
1b
1I
0t
0u
0[
0\
1`
1G
b1 +
11
0;
b110 !
b110 ,
00
12
1A
1D
09
0/
15
1@
06
0>
1.
b1 $
b1 *
#86000
1'
b10 (
#90000
0b
0]
1t
1u
1[
0`
0G
01
1;
10
b11 !
b11 ,
1I
02
0A
0D
b0 +
0J
1\
19
1/
1U
0Z
05
0@
0L
1H
16
1>
1Q
0W
0X
0.
1F
b10 $
b10 *
#91000
0'
b11 (
#95000
1J
0U
0I
1b
1L
1]
0t
0u
0Q
0[
1`
1G
b11 +
11
0;
b100 !
b100 ,
00
12
1A
1D
09
0/
15
1@
06
0>
1.
b11 $
b11 *
#96000
b100 (
#100000
0v
1t
1[
0`
0G
0{
01
1."
1/"
1;
10
0I
0y
b101 !
b101 ,
1b
02
0A
0D
0J
1\
b0 +
0c
1u
19
1/
1U
1Z
1n
0s
05
0@
0L
0H
0e
1a
16
1>
1Q
1W
1X
1j
0p
0q
0.
0F
1_
b100 $
b100 *
#101000
b101 (
#105000
1{
0."
0/"
1y
1c
0n
0b
1e
1v
1I
0j
0t
0[
0\
1`
1G
b101 +
11
0;
b1010 !
b1010 ,
00
12
1A
1D
09
0/
15
1@
06
0>
1.
b101 $
b101 *
#106000
1'
b110 (
#110000
0{
1."
1/"
0y
0c
1n
1b
0e
0v
0]
1j
1t
1[
0`
0G
01
1;
10
b111 !
b111 ,
1I
02
0A
0D
b0 +
0J
1\
19
1/
1U
0Z
05
0@
0L
1H
16
1>
1Q
0W
0X
0.
1F
b110 $
b110 *
#111000
0'
b111 (
#115000
1{
0."
0/"
1y
1c
1J
0n
0b
0U
0I
1e
1v
1L
1]
0j
0t
0Q
0[
1`
1G
b111 +
11
0;
b1000 !
b1000 ,
00
12
1A
1D
09
0/
15
1@
06
0>
1.
b111 $
b111 *
#116000
b1000 (
#120000
1t
1[
0`
0G
00"
01
1."
1;
10
0I
0y
0b
b1001 !
b1001 ,
1{
02
0A
0D
0J
1\
b0 +
0c
1u
0"
1/"
19
1/
1U
1Z
1n
1s
1("
0-"
05
0@
0L
0H
0e
0a
0}
1z
16
1>
1Q
1W
1X
1j
1p
1q
1$"
0*"
0+"
0.
0F
0_
1x
b1000 $
b1000 *
#121000
b1001 (
#125000
1b
1I
0t
0u
0[
0\
1`
1G
b1 +
11
0;
b1110 !
b1110 ,
00
12
1A
1D
09
0/
15
1@
06
0>
1.
b1001 $
b1001 *
#126000
1'
b1010 (
#130000
0b
0]
1t
1u
1[
0`
0G
01
1;
10
b1011 !
b1011 ,
1I
02
0A
0D
b0 +
0J
1\
19
1/
1U
0Z
05
0@
0L
1H
16
1>
1Q
0W
0X
0.
1F
b1010 $
b1010 *
#131000
0'
b1011 (
#135000
1J
0U
0I
1b
1L
1]
0t
0u
0Q
0[
1`
1G
b11 +
11
0;
b1100 !
b1100 ,
00
12
1A
1D
09
0/
15
1@
06
0>
1.
b1011 $
b1011 *
#136000
b1100 (
#140000
0v
0"
1t
1[
1("
1{
0`
0G
0}
00"
01
1$"
1."
1;
10
0I
0y
b1101 !
b1101 ,
1b
02
0A
0D
0J
1\
b0 +
0c
1u
19
1/
1U
1Z
1n
0s
05
0@
0L
0H
0e
1a
16
1>
1Q
1W
1X
1j
0p
0q
0.
0F
1_
b1100 $
b1100 *
#141000
b1101 (
#145000
1"
0("
0{
1}
10"
0$"
0."
1y
1c
0n
0b
1e
1v
1I
0j
0t
0[
0\
1`
1G
b101 +
11
0;
b10 !
b10 ,
00
12
1A
1D
09
0/
15
1@
06
0>
1.
b1101 $
b1101 *
#146000
1'
b1110 (
#150000
0"
1("
1{
0}
00"
1$"
1."
0y
0c
1n
1b
0e
0v
0]
1j
1t
1[
0`
0G
01
1;
10
b1111 !
b1111 ,
1I
02
0A
0D
b0 +
0J
1\
19
1/
1U
0Z
05
0@
0L
1H
16
1>
1Q
0W
0X
0.
1F
b1110 $
b1110 *
#151000
0'
b1111 (
#155000
1"
0("
0{
1}
10"
0$"
0."
1y
1c
1J
0n
0b
0U
0I
1e
1v
1L
1]
0j
0t
0Q
0[
1`
1G
b111 +
11
0;
b0 !
b0 ,
00
12
1A
1D
09
0/
15
1@
06
0>
1.
b1111 $
b1111 *
#156000
b10000 (
#160000
1I
0]
1t
1[
0`
0G
01
1."
1T
1;
0y
0b
b10 !
b10 ,
0{
0K
02
0J
b0 +
0c
1u
0"
1/"
1S
19
1U
1n
1s
1("
1-"
0M
05
0L
0e
0a
0}
0z
1=
1P
0V
0Y
16
1>
1Q
1W
1X
1j
1p
1q
1$"
1*"
1+"
0-
1E
0.
0F
0_
0x
b10 #
b10 )
b0 $
b0 *
#161000
b10 (
#165000
b11 !
b11 ,
10
0A
0D
1/
0>
0?
1.
b1 $
b1 *
#166000
b11 (
#170000
b10 +
1J
0T
0I
b0 !
b0 ,
00
1K
1Z
1]
1A
1D
0R
0H
0/
1N
1Y
1>
1?
0O
0W
0.
1F
b10 $
b10 *
#171000
1'
b100 (
#175000
b1 !
b1 ,
10
0A
0D
1/
0>
0?
1.
b11 $
b11 *
#176000
b101 (
#180000
b0 +
0J
1T
1I
00
0K
0Z
0]
b110 !
b110 ,
1b
1A
1D
1R
1H
0s
0v
0/
0N
0Y
1a
1>
1?
1O
1W
0p
0q
0.
0F
1_
b100 $
b100 *
#181000
0'
b110 (
#185000
b111 !
b111 ,
10
0A
0D
1/
0>
0?
1.
b101 $
b101 *
#186000
b111 (
#190000
b10 +
1J
0T
0I
b100 !
b100 ,
00
1K
1Z
1]
1A
1D
0R
0H
0/
1N
1Y
1>
1?
0O
0W
0.
1F
b110 $
b110 *
#191000
1'
b1000 (
#195000
b101 !
b101 ,
10
0A
0D
1/
0>
0?
1.
b111 $
b111 *
#196000
b1001 (
#200000
b0 +
0J
1T
1I
00
0K
0Z
0]
0b
b1010 !
b1010 ,
1{
1A
1D
1R
1H
1s
1v
0-"
00"
0/
0N
0Y
0a
1z
1>
1?
1O
1W
1p
1q
0*"
0+"
0.
0F
0_
1x
b1000 $
b1000 *
#201000
0'
b1010 (
#205000
b1011 !
b1011 ,
10
0A
0D
1/
0>
0?
1.
b1001 $
b1001 *
#206000
b1011 (
#210000
b10 +
1J
0T
0I
b1000 !
b1000 ,
00
1K
1Z
1]
1A
1D
0R
0H
0/
1N
1Y
1>
1?
0O
0W
0.
1F
b1010 $
b1010 *
#211000
1'
b1100 (
#215000
b1001 !
b1001 ,
10
0A
0D
1/
0>
0?
1.
b1011 $
b1011 *
#216000
b1101 (
#220000
b0 +
0J
1T
1I
00
0K
0Z
0]
b1110 !
b1110 ,
1b
1A
1D
1R
1H
0s
0v
0/
0N
0Y
1a
1>
1?
1O
1W
0p
0q
0.
0F
1_
b1100 $
b1100 *
#221000
0'
b1110 (
#225000
b1111 !
b1111 ,
10
0A
0D
1/
0>
0?
1.
b1101 $
b1101 *
#226000
b1111 (
#230000
b10 +
1J
0T
0I
b1100 !
b1100 ,
00
1K
1Z
1]
1A
1D
0R
0H
0/
1N
1Y
1>
1?
0O
0W
0.
1F
b1110 $
b1110 *
#231000
1'
b10000 (
#235000
b1101 !
b1101 ,
10
0A
0D
1/
0>
0?
1.
b1111 $
b1111 *
#236000
b10001 (
#240000
b0 +
0J
1T
1I
0K
0Z
0]
0b
b11 !
b11 ,
0{
1R
1H
1s
1v
1-"
10"
0N
0Y
0a
0z
0=
0@
1>
1?
1O
1W
1p
1q
1*"
1+"
1-
0.
0F
0_
0x
b11 #
b11 )
b0 $
b0 *
#241000
0'
b11 (
#245000
1J
0T
1K
0S
0I
1b
1M
1]
0t
0u
0P
0[
1`
1G
b11 +
11
0;
b100 !
b100 ,
00
12
1A
1D
09
0/
15
1@
06
0>
1.
b1 $
b1 *
#246000
b100 (
#250000
1S
0b
0M
1t
1u
1P
1[
0`
0G
b10 +
01
0I
1;
b1 !
b1 ,
10
1\
02
0A
0D
1Z
19
1/
0R
1U
0H
05
0@
1N
0L
1Y
16
1>
0O
1Q
0W
0.
1F
b10 $
b10 *
#251000
1'
b101 (
#255000
0S
0U
1b
1M
1L
1I
0t
0u
0P
0Q
0[
0\
1`
1G
b11 +
11
0;
b110 !
b110 ,
00
12
1A
1D
09
0/
15
1@
06
0>
1.
b11 $
b11 *
#256000
0'
b110 (
#260000
0J
1T
0K
1S
0v
0M
0]
1t
1P
1[
0`
0G
0{
01
1I
1."
1/"
1;
10
1\
0y
b111 !
b111 ,
1b
02
0A
0D
0Z
b0 +
0c
1u
19
1/
1R
1U
1H
1n
0s
05
0@
0N
0L
0Y
0e
1a
16
1>
1O
1Q
1W
1j
0p
0q
0.
0F
1_
b100 $
b100 *
#261000
b111 (
#265000
1{
0."
0/"
1J
1y
0T
1c
1K
0n
0b
0S
0I
1e
1v
1M
1]
0j
0t
0P
0[
1`
1G
b111 +
11
0;
b1000 !
b1000 ,
00
12
1A
1D
09
0/
15
1@
06
0>
1.
b101 $
b101 *
#266000
b1000 (
#270000
0{
1."
1/"
0y
0c
1n
1b
1S
0e
0v
0M
1j
1t
1P
1[
0`
0G
b10 +
01
0I
1;
b101 !
b101 ,
10
1\
02
0A
0D
1Z
19
1/
0R
1U
0H
05
0@
1N
0L
1Y
16
1>
0O
1Q
0W
0.
1F
b110 $
b110 *
#271000
1'
b1001 (
#275000
1{
0."
0/"
1y
1c
0n
0b
0S
0U
1e
1v
1M
1L
1I
0j
0t
0P
0Q
0[
0\
1`
1G
b111 +
11
0;
b1010 !
b1010 ,
00
12
1A
1D
09
0/
15
1@
06
0>
1.
b111 $
b111 *
#276000
0'
b1010 (
#280000
0J
1T
0K
1S
0M
0]
1t
1P
1[
0`
0G
00"
01
1I
1."
1;
10
1\
0y
0b
b1011 !
b1011 ,
1{
02
0A
0D
0Z
b0 +
0c
1u
0"
1/"
19
1/
1R
1U
1H
1n
1s
1("
0-"
05
0@
0N
0L
0Y
0e
0a
0}
1z
16
1>
1O
1Q
1W
1j
1p
1q
1$"
0*"
0+"
0.
0F
0_
1x
b1000 $
b1000 *
#281000
b1011 (
#285000
1J
0T
1K
0S
0I
1b
1M
1]
0t
0u
0P
0[
1`
1G
b11 +
11
0;
b1100 !
b1100 ,
00
12
1A
1D
09
0/
15
1@
06
0>
1.
b1001 $
b1001 *
#286000
b1100 (
#290000
1S
0b
0M
1t
1u
1P
1[
0`
0G
b10 +
01
0I
1;
b1001 !
b1001 ,
10
1\
02
0A
0D
1Z
19
1/
0R
1U
0H
05
0@
1N
0L
1Y
16
1>
0O
1Q
0W
0.
1F
b1010 $
b1010 *
#291000
1'
b1101 (
#295000
0S
0U
1b
1M
1L
1I
0t
0u
0P
0Q
0[
0\
1`
1G
b11 +
11
0;
b1110 !
b1110 ,
00
12
1A
1D
09
0/
15
1@
06
0>
1.
b1011 $
b1011 *
#296000
0'
b1110 (
#300000
0J
1T
0K
1S
0v
0M
0]
0"
1t
1P
1[
1("
1{
0`
0G
0}
00"
01
1I
1$"
1."
1;
10
1\
0y
b1111 !
b1111 ,
1b
02
0A
0D
0Z
b0 +
0c
1u
19
1/
1R
1U
1H
1n
0s
05
0@
0N
0L
0Y
0e
1a
16
1>
1O
1Q
1W
1j
0p
0q
0.
0F
1_
b1100 $
b1100 *
#301000
b1111 (
#305000
1"
0("
0{
1}
10"
0$"
0."
1J
1y
0T
1c
1K
0n
0b
0S
0I
1e
1v
1M
1]
0j
0t
0P
0[
1`
1G
b111 +
11
0;
b0 !
b0 ,
00
12
1A
1D
09
0/
15
1@
06
0>
1.
b1101 $
b1101 *
#306000
b10000 (
#310000
0"
1("
1{
0}
00"
1$"
1."
0y
0c
1n
1b
1S
0e
0v
0M
1j
1t
1P
1[
0`
0G
b10 +
01
0I
1;
b1101 !
b1101 ,
10
1\
02
0A
0D
1Z
19
1/
0R
1U
0H
05
0@
1N
0L
1Y
16
1>
0O
1Q
0W
0.
1F
b1110 $
b1110 *
#311000
1'
b10001 (
#315000
1"
0("
0{
1}
10"
0$"
0."
1y
1c
0n
0b
0S
0U
1e
1v
1M
1L
1I
0j
0t
0P
0Q
0[
0\
1`
1G
b111 +
11
0;
b10 !
b10 ,
00
12
1A
1D
09
0/
15
1@
06
0>
1.
b1111 $
b1111 *
#316000
0'
b10010 (
#320000
1b
0v
0I
1t
1[
1\
0`
0G
01
0J
1."
1m
1;
1T
0y
b100 !
b100 ,
0{
0d
02
0K
b0 +
0c
0"
1/"
1S
1l
19
1R
1U
1n
1("
1-"
0M
0f
05
0N
0L
0e
0}
0z
1=
1P
1V
1i
0o
0r
16
1>
1O
1Q
1W
1j
1p
1q
1$"
1*"
1+"
0-
0E
1^
0.
0F
0_
0x
b100 #
b100 )
b0 $
b0 *
#321000
b100 (
#325000
b101 !
b101 ,
10
0A
0D
1/
0>
0?
1.
b1 $
b1 *
#326000
b101 (
#330000
00
b110 !
b110 ,
1I
1A
1D
0Z
0]
0/
1H
1>
1?
0W
0X
0.
1F
b10 $
b10 *
#331000
b110 (
#335000
b111 !
b111 ,
10
0A
0D
1/
0>
0?
1.
b11 $
b11 *
#336000
b111 (
#340000
1{
0."
0/"
1y
b100 +
1c
0m
0b
00
b1000 !
b1000 ,
0I
1d
1s
1v
1A
1D
1Z
1]
0k
0a
0/
0H
1g
1r
1>
1?
1W
1X
0h
0p
0.
0F
1_
b100 $
b100 *
#341000
b1000 (
#345000
b1001 !
b1001 ,
10
0A
0D
1/
0>
0?
1.
b101 $
b101 *
#346000
b1001 (
#350000
00
b1010 !
b1010 ,
1I
1A
1D
0Z
0]
0/
1H
1>
1?
0W
0X
0.
1F
b110 $
b110 *
#351000
b1010 (
#355000
b1011 !
b1011 ,
10
0A
0D
1/
0>
0?
1.
b111 $
b111 *
#356000
b1011 (
#360000
00"
1."
0y
b0 +
0c
1m
1b
1{
00
b1100 !
b1100 ,
0I
0d
0s
0v
0"
1/"
1A
1D
1Z
1]
1k
1a
1("
0-"
0/
0H
0g
0r
0}
1z
1>
1?
1W
1X
1h
1p
1$"
0*"
0+"
0.
0F
0_
1x
b1000 $
b1000 *
#361000
b1100 (
#365000
b1101 !
b1101 ,
10
0A
0D
1/
0>
0?
1.
b1001 $
b1001 *
#366000
b1101 (
#370000
00
b1110 !
b1110 ,
1I
1A
1D
0Z
0]
0/
1H
1>
1?
0W
0X
0.
1F
b1010 $
b1010 *
#371000
b1110 (
#375000
b1111 !
b1111 ,
10
0A
0D
1/
0>
0?
1.
b1011 $
b1011 *
#376000
b1111 (
#380000
1"
0("
0{
1}
10"
0$"
0."
1y
b100 +
1c
0m
0b
00
b0 !
b0 ,
0I
1d
1s
1v
1A
1D
1Z
1]
0k
0a
0/
0H
1g
1r
1>
1?
1W
1X
0h
0p
0.
0F
1_
b1100 $
b1100 *
#381000
b10000 (
#385000
b1 !
b1 ,
10
0A
0D
1/
0>
0?
1.
b1101 $
b1101 *
#386000
b10001 (
#390000
00
b10 !
b10 ,
1I
1A
1D
0Z
0]
0/
1H
1>
1?
0W
0X
0.
1F
b1110 $
b1110 *
#391000
b10010 (
#395000
b11 !
b11 ,
10
0A
0D
1/
0>
0?
1.
b1111 $
b1111 *
#396000
b10011 (
#400000
1."
0y
b0 +
0c
1m
1b
0{
b101 !
b101 ,
0I
0d
0s
0v
0"
1/"
1Z
1]
1k
1a
1("
1-"
0H
0g
0r
0}
0z
0=
0@
1>
1?
1W
1X
1h
1p
1$"
1*"
1+"
1-
0.
0F
0_
0x
b101 #
b101 )
b0 $
b0 *
#401000
b101 (
#405000
1{
0."
0/"
1y
1c
0m
1d
0l
0b
1f
1v
1I
0i
0t
0[
0\
1`
1G
b101 +
11
0;
b1010 !
b1010 ,
00
12
1A
1D
09
0/
15
1@
06
0>
1.
b1 $
b1 *
#406000
1'
b110 (
#410000
0{
1."
1/"
0y
0c
1m
0d
1l
1b
0f
0v
0]
1i
1t
1[
0`
0G
01
1;
10
b111 !
b111 ,
1I
02
0A
0D
b0 +
0J
1\
19
1/
1U
0Z
05
0@
0L
1H
16
1>
1Q
0W
0X
0.
1F
b10 $
b10 *
#411000
0'
b111 (
#415000
1{
0."
0/"
1y
1c
0m
1d
1J
0l
0b
0U
0I
1f
1v
1L
1]
0i
0t
0Q
0[
1`
1G
b111 +
11
0;
b1000 !
b1000 ,
00
12
1A
1D
09
0/
15
1@
06
0>
1.
b11 $
b11 *
#416000
b1000 (
#420000
1l
0f
1i
1t
1[
0`
0G
01
0b
1;
10
b1001 !
b1001 ,
0I
1u
02
0A
0D
b100 +
0J
1\
1s
19
1/
1U
1Z
0k
1n
0a
05
0@
0L
0H
1g
0e
1r
16
1>
1Q
1W
1X
0h
1j
0p
0.
0F
1_
b100 $
b100 *
#421000
b1001 (
