Lab2/Advanced/2-3/Lab2_111062109_Carry_Look_Ahead_Adder_8bit.v
`timescale 1ns/1ps
module AND(out, a, b);
    input a, b;
    output out;
    wire temp;
    nand n1 (temp, a, b);
    nand n2 (out, temp, temp);
endmodule

module OR(out, a, b);
    input a, b;
    output out;
    wire temp1, temp2;
    nand n1 (temp1, a, a);
    nand n2 (temp2, b, b);
    nand n3 (out, temp1, temp2);
endmodule

module XOR(out, a, b);
    input a, b;
    output out;
    wire temp1, temp2, na, nb;
    nand n1 (na, a, a);
    nand n2 (nb, b, b);
    nand n3 (temp1, na, b);
    nand n4 (temp2, nb, a);
    nand n5 (out, temp1, temp2);
endmodule

module Carry_Look_Ahead_Generator_2bit(p, g, cin, cout);
    input [2-1:0]p, g;
    input cin;
    output [2-1:0] cout;
    wire [5-1:0]temp;
    AND a1 (temp[0], p[0], cin);
    OR o1 (cout[0], g[0], temp[0]);

    AND a2 (temp[1], p[1], g[0]);
    AND a3 (temp[2], p[1], p[0]);
    AND a4 (temp[3], cin, temp[2]);
    OR o2 (temp[4], temp[1], temp[3]);
    OR o3 (cout[1], g[1], temp[4]);
endmodule


module Carry_Look_Ahead_Generator_4bit(p, g, cin, cout, p03, g03);
    input [4-1:0] p, g;
    input cin;
    output [2:0]cout;
    output p03, g03;
    wire p01, p02;
    wire [13:0] temp;

    AND a1(p01, p[0], p[1]);
    AND a2(p02, p01, p[2]);
    AND a3(p03, p02, p[3]);

    AND a7(temp[0], p[0], cin);
    OR o1(cout[0], g[0], temp[0]);

    AND a8(temp[1], p01, cin);
    AND a9(temp[2], g[0], p[1]);
    OR o2(temp[3], g[1], temp[2]);
    OR o3(cout[1], temp[1], temp[3]);

    AND a10(temp[4], p02, cin);
    AND a11(temp[5], temp[3], p[2]);
    OR o5(temp[6], g[2], temp[5]);
    OR o6(cout[2], temp[4], temp[6]);

    AND a13(temp[7], temp[6], p[3]);
    OR o7(g03, g[3], temp[7]);
endmodule


module Carry_Look_Ahead_Adder_8bit(a, b, c0, s, c8);
    input [8-1:0] a, b;
    input c0;
    output [8-1:0] s;
    output c8;
    wire [8-1:0] p, g, c;
    wire [8-1:0] cout;
    wire p03, g03, p47, g47;
    XOR x1[7:0] (p, a, b);
    AND a1[7:0] (g, a, b);
    AND a2(cout[0], c0, c0);
    Carry_Look_Ahead_Generator_4bit c1 (p[3:0], g[3:0], c0, cout[3:1], p03, g03);
    Carry_Look_Ahead_Generator_4bit c2 (p[7:4], g[7:4], cout[4], cout[7:5], p47, g47);
    Carry_Look_Ahead_Generator_2bit c3 ({p47,p03}, {g47,g03}, c0, {c8,cout[4]});
    
    XOR x2[7:0] (s, cout, p);
endmodule

Lab2/Advanced/2-3/Lab2_111062109_Carry_Look_Ahead_Adder_8bit_t.v
`timescale 1ns/1ps
`include "Lab2_111062109_Carry_Look_Ahead_Adder_8bit.v"
module Carry_Look_Ahead_Adder_8bit_t;
reg [8-1:0] a = 8'b00000000;
reg [8-1:0] b = 8'b00000001;
wire [8-1:0] sum;
reg cin = 1'b0;
wire cout;

Carry_Look_Ahead_Adder_8bit adder (a,b,cin,sum,cout);

initial begin
    $dumpfile("Carry_Look_Ahead_Adder_8bit_t.vcd");
    $dumpvars(0, Carry_Look_Ahead_Adder_8bit_t);
    repeat(20) begin
        #1 a = $random;
        b = $random;
        cin = $random;
    end
    $finish;
end

endmodule

Lab2/Advanced/2-3/Carry_Look_Ahead_Adder_8bit_t.vcd
$date
	Sun Oct  8 16:41:55 2023
$end
$version
	Icarus Verilog
$end
$timescale
	1ps
$end
$scope module Carry_Look_Ahead_Adder_8bit_t $end
$var wire 8 ! sum [7:0] $end
$var wire 1 " cout $end
$var reg 8 # a [7:0] $end
$var reg 8 $ b [7:0] $end
$var reg 1 % cin $end
$scope module adder $end
$var wire 8 & a [7:0] $end
$var wire 8 ' b [7:0] $end
$var wire 1 % c0 $end
$var wire 8 ( s [7:0] $end
$var wire 1 ) p47 $end
$var wire 1 * p03 $end
$var wire 8 + p [7:0] $end
$var wire 1 , g47 $end
$var wire 1 - g03 $end
$var wire 8 . g [7:0] $end
$var wire 8 / cout [7:0] $end
$var wire 1 " c8 $end
$scope module a1[0] $end
$var wire 1 0 a $end
$var wire 1 1 b $end
$var wire 1 2 out $end
$var wire 1 3 temp $end
$upscope $end
$scope module a1[1] $end
$var wire 1 4 a $end
$var wire 1 5 b $end
$var wire 1 6 out $end
$var wire 1 7 temp $end
$upscope $end
$scope module a1[2] $end
$var wire 1 8 a $end
$var wire 1 9 b $end
$var wire 1 : out $end
$var wire 1 ; temp $end
$upscope $end
$scope module a1[3] $end
$var wire 1 < a $end
$var wire 1 = b $end
$var wire 1 > out $end
$var wire 1 ? temp $end
$upscope $end
$scope module a1[4] $end
$var wire 1 @ a $end
$var wire 1 A b $end
$var wire 1 B out $end
$var wire 1 C temp $end
$upscope $end
$scope module a1[5] $end
$var wire 1 D a $end
$var wire 1 E b $end
$var wire 1 F out $end
$var wire 1 G temp $end
$upscope $end
$scope module a1[6] $end
$var wire 1 H a $end
$var wire 1 I b $end
$var wire 1 J out $end
$var wire 1 K temp $end
$upscope $end
$scope module a1[7] $end
$var wire 1 L a $end
$var wire 1 M b $end
$var wire 1 N out $end
$var wire 1 O temp $end
$upscope $end
$scope module a2 $end
$var wire 1 % a $end
$var wire 1 % b $end
$var wire 1 P out $end
$var wire 1 Q temp $end
$upscope $end
$scope module c1 $end
$var wire 1 % cin $end
$var wire 4 R g [3:0] $end
$var wire 4 S p [3:0] $end
$var wire 14 T temp [13:0] $end
$var wire 1 * p03 $end
$var wire 1 U p02 $end
$var wire 1 V p01 $end
$var wire 1 - g03 $end
$var wire 3 W cout [2:0] $end
$scope module a1 $end
$var wire 1 X a $end
$var wire 1 Y b $end
$var wire 1 V out $end
$var wire 1 Z temp $end
$upscope $end
$scope module a10 $end
$var wire 1 % b $end
$var wire 1 [ out $end
$var wire 1 \ temp $end
$var wire 1 U a $end
$upscope $end
$scope module a11 $end
$var wire 1 ] a $end
$var wire 1 ^ b $end
$var wire 1 _ out $end
$var wire 1 ` temp $end
$upscope $end
$scope module a13 $end
$var wire 1 a a $end
$var wire 1 b b $end
$var wire 1 c out $end
$var wire 1 d temp $end
$upscope $end
$scope module a2 $end
$var wire 1 V a $end
$var wire 1 e b $end
$var wire 1 U out $end
$var wire 1 f temp $end
$upscope $end
$scope module a3 $end
$var wire 1 U a $end
$var wire 1 g b $end
$var wire 1 * out $end
$var wire 1 h temp $end
$upscope $end
$scope module a7 $end
$var wire 1 i a $end
$var wire 1 % b $end
$var wire 1 j out $end
$var wire 1 k temp $end
$upscope $end
$scope module a8 $end
$var wire 1 V a $end
$var wire 1 % b $end
$var wire 1 l out $end
$var wire 1 m temp $end
$upscope $end
$scope module a9 $end
$var wire 1 n a $end
$var wire 1 o b $end
$var wire 1 p out $end
$var wire 1 q temp $end
$upscope $end
$scope module o1 $end
$var wire 1 r a $end
$var wire 1 s b $end
$var wire 1 t out $end
$var wire 1 u temp1 $end
$var wire 1 v temp2 $end
$upscope $end
$scope module o2 $end
$var wire 1 w a $end
$var wire 1 x b $end
$var wire 1 y out $end
$var wire 1 z temp1 $end
$var wire 1 { temp2 $end
$upscope $end
$scope module o3 $end
$var wire 1 | a $end
$var wire 1 } b $end
$var wire 1 ~ out $end
$var wire 1 !" temp1 $end
$var wire 1 "" temp2 $end
$upscope $end
$scope module o5 $end
$var wire 1 #" a $end
$var wire 1 $" b $end
$var wire 1 %" out $end
$var wire 1 &" temp1 $end
$var wire 1 '" temp2 $end
$upscope $end
$scope module o6 $end
$var wire 1 (" a $end
$var wire 1 )" b $end
$var wire 1 *" out $end
$var wire 1 +" temp1 $end
$var wire 1 ," temp2 $end
$upscope $end
$scope module o7 $end
$var wire 1 -" a $end
$var wire 1 ." b $end
$var wire 1 - out $end
$var wire 1 /" temp1 $end
$var wire 1 0" temp2 $end
$upscope $end
$upscope $end
$scope module c2 $end
$var wire 1 1" cin $end
$var wire 4 2" g [3:0] $end
$var wire 4 3" p [3:0] $end
$var wire 14 4" temp [13:0] $end
$var wire 1 ) p03 $end
$var wire 1 5" p02 $end
$var wire 1 6" p01 $end
$var wire 1 , g03 $end
$var wire 3 7" cout [2:0] $end
$scope module a1 $end
$var wire 1 8" a $end
$var wire 1 9" b $end
$var wire 1 6" out $end
$var wire 1 :" temp $end
$upscope $end
$scope module a10 $end
$var wire 1 1" b $end
$var wire 1 ;" out $end
$var wire 1 <" temp $end
$var wire 1 5" a $end
$upscope $end
$scope module a11 $end
$var wire 1 =" a $end
$var wire 1 >" b $end
$var wire 1 ?" out $end
$var wire 1 @" temp $end
$upscope $end
$scope module a13 $end
$var wire 1 A" a $end
$var wire 1 B" b $end
$var wire 1 C" out $end
$var wire 1 D" temp $end
$upscope $end
$scope module a2 $end
$var wire 1 6" a $end
$var wire 1 E" b $end
$var wire 1 5" out $end
$var wire 1 F" temp $end
$upscope $end
$scope module a3 $end
$var wire 1 5" a $end
$var wire 1 G" b $end
$var wire 1 ) out $end
$var wire 1 H" temp $end
$upscope $end
$scope module a7 $end
$var wire 1 I" a $end
$var wire 1 1" b $end
$var wire 1 J" out $end
$var wire 1 K" temp $end
$upscope $end
$scope module a8 $end
$var wire 1 6" a $end
$var wire 1 1" b $end
$var wire 1 L" out $end
$var wire 1 M" temp $end
$upscope $end
$scope module a9 $end
$var wire 1 N" a $end
$var wire 1 O" b $end
$var wire 1 P" out $end
$var wire 1 Q" temp $end
$upscope $end
$scope module o1 $end
$var wire 1 R" a $end
$var wire 1 S" b $end
$var wire 1 T" out $end
$var wire 1 U" temp1 $end
$var wire 1 V" temp2 $end
$upscope $end
$scope module o2 $end
$var wire 1 W" a $end
$var wire 1 X" b $end
$var wire 1 Y" out $end
$var wire 1 Z" temp1 $end
$var wire 1 [" temp2 $end
$upscope $end
$scope module o3 $end
$var wire 1 \" a $end
$var wire 1 ]" b $end
$var wire 1 ^" out $end
$var wire 1 _" temp1 $end
$var wire 1 `" temp2 $end
$upscope $end
$scope module o5 $end
$var wire 1 a" a $end
$var wire 1 b" b $end
$var wire 1 c" out $end
$var wire 1 d" temp1 $end
$var wire 1 e" temp2 $end
$upscope $end
$scope module o6 $end
$var wire 1 f" a $end
$var wire 1 g" b $end
$var wire 1 h" out $end
$var wire 1 i" temp1 $end
$var wire 1 j" temp2 $end
$upscope $end
$scope module o7 $end
$var wire 1 k" a $end
$var wire 1 l" b $end
$var wire 1 , out $end
$var wire 1 m" temp1 $end
$var wire 1 n" temp2 $end
$upscope $end
$upscope $end
$scope module c3 $end
$var wire 1 % cin $end
$var wire 2 o" g [1:0] $end
$var wire 2 p" p [1:0] $end
$var wire 5 q" temp [4:0] $end
$var wire 2 r" cout [1:0] $end
$scope module a1 $end
$var wire 1 s" a $end
$var wire 1 % b $end
$var wire 1 t" out $end
$var wire 1 u" temp $end
$upscope $end
$scope module a2 $end
$var wire 1 v" a $end
$var wire 1 w" b $end
$var wire 1 x" out $end
$var wire 1 y" temp $end
$upscope $end
$scope module a3 $end
$var wire 1 z" a $end
$var wire 1 {" b $end
$var wire 1 |" out $end
$var wire 1 }" temp $end
$upscope $end
$scope module a4 $end
$var wire 1 % a $end
$var wire 1 ~" b $end
$var wire 1 !# out $end
$var wire 1 "# temp $end
$upscope $end
$scope module o1 $end
$var wire 1 ## a $end
$var wire 1 $# b $end
$var wire 1 %# out $end
$var wire 1 &# temp1 $end
$var wire 1 '# temp2 $end
$upscope $end
$scope module o2 $end
$var wire 1 (# a $end
$var wire 1 )# b $end
$var wire 1 *# out $end
$var wire 1 +# temp1 $end
$var wire 1 ,# temp2 $end
$upscope $end
$scope module o3 $end
$var wire 1 -# a $end
$var wire 1 .# b $end
$var wire 1 /# out $end
$var wire 1 0# temp1 $end
$var wire 1 1# temp2 $end
$upscope $end
$upscope $end
$scope module x1[0] $end
$var wire 1 2# a $end
$var wire 1 3# b $end
$var wire 1 4# na $end
$var wire 1 5# nb $end
$var wire 1 6# out $end
$var wire 1 7# temp1 $end
$var wire 1 8# temp2 $end
$upscope $end
$scope module x1[1] $end
$var wire 1 9# a $end
$var wire 1 :# b $end
$var wire 1 ;# na $end
$var wire 1 <# nb $end
$var wire 1 =# out $end
$var wire 1 ># temp1 $end
$var wire 1 ?# temp2 $end
$upscope $end
$scope module x1[2] $end
$var wire 1 @# a $end
$var wire 1 A# b $end
$var wire 1 B# na $end
$var wire 1 C# nb $end
$var wire 1 D# out $end
$var wire 1 E# temp1 $end
$var wire 1 F# temp2 $end
$upscope $end
$scope module x1[3] $end
$var wire 1 G# a $end
$var wire 1 H# b $end
$var wire 1 I# na $end
$var wire 1 J# nb $end
$var wire 1 K# out $end
$var wire 1 L# temp1 $end
$var wire 1 M# temp2 $end
$upscope $end
$scope module x1[4] $end
$var wire 1 N# a $end
$var wire 1 O# b $end
$var wire 1 P# na $end
$var wire 1 Q# nb $end
$var wire 1 R# out $end
$var wire 1 S# temp1 $end
$var wire 1 T# temp2 $end
$upscope $end
$scope module x1[5] $end
$var wire 1 U# a $end
$var wire 1 V# b $end
$var wire 1 W# na $end
$var wire 1 X# nb $end
$var wire 1 Y# out $end
$var wire 1 Z# temp1 $end
$var wire 1 [# temp2 $end
$upscope $end
$scope module x1[6] $end
$var wire 1 \# a $end
$var wire 1 ]# b $end
$var wire 1 ^# na $end
$var wire 1 _# nb $end
$var wire 1 `# out $end
$var wire 1 a# temp1 $end
$var wire 1 b# temp2 $end
$upscope $end
$scope module x1[7] $end
$var wire 1 c# a $end
$var wire 1 d# b $end
$var wire 1 e# na $end
$var wire 1 f# nb $end
$var wire 1 g# out $end
$var wire 1 h# temp1 $end
$var wire 1 i# temp2 $end
$upscope $end
$scope module x2[0] $end
$var wire 1 j# a $end
$var wire 1 k# b $end
$var wire 1 l# na $end
$var wire 1 m# nb $end
$var wire 1 n# out $end
$var wire 1 o# temp1 $end
$var wire 1 p# temp2 $end
$upscope $end
$scope module x2[1] $end
$var wire 1 q# a $end
$var wire 1 r# b $end
$var wire 1 s# na $end
$var wire 1 t# nb $end
$var wire 1 u# out $end
$var wire 1 v# temp1 $end
$var wire 1 w# temp2 $end
$upscope $end
$scope module x2[2] $end
$var wire 1 x# a $end
$var wire 1 y# b $end
$var wire 1 z# na $end
$var wire 1 {# nb $end
$var wire 1 |# out $end
$var wire 1 }# temp1 $end
$var wire 1 ~# temp2 $end
$upscope $end
$scope module x2[3] $end
$var wire 1 !$ a $end
$var wire 1 "$ b $end
$var wire 1 #$ na $end
$var wire 1 $$ nb $end
$var wire 1 %$ out $end
$var wire 1 &$ temp1 $end
$var wire 1 '$ temp2 $end
$upscope $end
$scope module x2[4] $end
$var wire 1 ($ a $end
$var wire 1 )$ b $end
$var wire 1 *$ na $end
$var wire 1 +$ nb $end
$var wire 1 ,$ out $end
$var wire 1 -$ temp1 $end
$var wire 1 .$ temp2 $end
$upscope $end
$scope module x2[5] $end
$var wire 1 /$ a $end
$var wire 1 0$ b $end
$var wire 1 1$ na $end
$var wire 1 2$ nb $end
$var wire 1 3$ out $end
$var wire 1 4$ temp1 $end
$var wire 1 5$ temp2 $end
$upscope $end
$scope module x2[6] $end
$var wire 1 6$ a $end
$var wire 1 7$ b $end
$var wire 1 8$ na $end
$var wire 1 9$ nb $end
$var wire 1 :$ out $end
$var wire 1 ;$ temp1 $end
$var wire 1 <$ temp2 $end
$upscope $end
$scope module x2[7] $end
$var wire 1 =$ a $end
$var wire 1 >$ b $end
$var wire 1 ?$ na $end
$var wire 1 @$ nb $end
$var wire 1 A$ out $end
$var wire 1 B$ temp1 $end
$var wire 1 C$ temp2 $end
$upscope $end
$upscope $end
$upscope $end
$enddefinitions $end
#0
$dumpvars
1C$
1B$
0A$
1@$
1?$
0>$
0=$
1<$
1;$
0:$
19$
18$
07$
06$
15$
14$
03$
12$
11$
00$
0/$
1.$
1-$
0,$
1+$
1*$
0)$
0($
1'$
1&$
0%$
1$$
1#$
0"$
0!$
1~#
1}#
0|#
1{#
1z#
0y#
0x#
1w#
1v#
0u#
1t#
1s#
0r#
0q#
1p#
0o#
1n#
0m#
1l#
1k#
0j#
1i#
1h#
0g#
1f#
1e#
0d#
0c#
1b#
1a#
0`#
1_#
1^#
0]#
0\#
1[#
1Z#
0Y#
1X#
1W#
0V#
0U#
1T#
1S#
0R#
1Q#
1P#
0O#
0N#
1M#
1L#
0K#
1J#
1I#
0H#
0G#
1F#
1E#
0D#
1C#
1B#
0A#
0@#
1?#
1>#
0=#
1<#
1;#
0:#
09#
18#
07#
16#
05#
14#
13#
02#
11#
10#
0/#
0.#
0-#
1,#
1+#
0*#
0)#
0(#
1'#
1&#
0%#
0$#
0##
1"#
0!#
0~"
1}"
0|"
0{"
0z"
1y"
0x"
0w"
0v"
1u"
0t"
0s"
b0 r"
b0 q"
b0 p"
b0 o"
1n"
1m"
0l"
0k"
1j"
1i"
0h"
0g"
0f"
1e"
1d"
0c"
0b"
0a"
1`"
1_"
0^"
0]"
0\"
1["
1Z"
0Y"
0X"
0W"
1V"
1U"
0T"
0S"
0R"
1Q"
0P"
0O"
0N"
1M"
0L"
1K"
0J"
0I"
1H"
0G"
1F"
0E"
1D"
0C"
0B"
0A"
1@"
0?"
0>"
0="
1<"
0;"
1:"
09"
08"
b0 7"
06"
05"
bz00000000 4"
b0 3"
b0 2"
01"
10"
1/"
0."
0-"
1,"
1+"
0*"
0)"
0("
1'"
1&"
0%"
0$"
0#"
1""
1!"
0~
0}
0|
1{
1z
0y
0x
0w
1v
1u
0t
0s
0r
1q
0p
0o
0n
1m
0l
1k
0j
1i
1h
0g
1f
0e
1d
0c
0b
0a
1`
0_
0^
0]
1\
0[
1Z
0Y
1X
b0 W
0V
0U
bz00000000 T
b1 S
b0 R
1Q
0P
1O
0N
0M
0L
1K
0J
0I
0H
1G
0F
0E
0D
1C
0B
0A
0@
1?
0>
0=
0<
1;
0:
09
08
17
06
05
04
13
02
11
00
b0 /
b0 .
0-
0,
b1 +
0*
0)
b1 (
b1 '
b0 &
0%
b1 $
b0 #
0"
b1 !
$end
#1000
1u#
0s#
0w#
0n#
1q#
1A$
1|#
b10100110 !
b10100110 (
13$
1o#
b1 W
1t
0@$
0B$
1e
1^
0{#
0}#
19"
1G"
1O"
1B"
02$
04$
0l#
0v
1>$
b101 S
1y#
b1010 3"
10$
1j#
1s
1g#
1D#
b10100101 +
1Y#
b11 /
1P
bz00000001 T
1j
0f#
0h#
0B#
0F#
0W#
0[#
0Q
0k
1d#
1M
1@#
1U#
18
1D
1%
b10000001 $
b10000001 '
b100100 #
b100100 &
#2000
0&#
1##
1w"
b1 o"
1-
1,$
00"
0*$
0.$
1."
1($
11"
1c
0d
0,"
b1 r"
1%#
1a
1)"
1'#
0#$
0|#
1%"
0$#
1!$
1}#
0'"
b0 q"
0t"
1*"
0z#
1$"
1u"
1+"
1x#
1_
0s"
0{"
0("
b11111 /
b111 W
1~
0`
0""
b0 p"
0*
0[
1!"
1]
1}
1v
1h
1\
0|
1y
0s
0U
0l
0{
0j
1n#
1f
1m
1x
1k
0p#
0V
0u#
bz11101100 T
1p
0%$
0A$
0X
0i
1m#
1Z
1w#
b1110001 !
b1110001 (
1:$
0u
0q
0$$
1&$
1@$
1B$
0k#
1Y
1g
1o
1b
0t#
1E"
0G"
1>"
0B"
09$
0;$
1r
1n
1"$
0>$
06#
b1110 S
1r#
b110 3"
17$
b1 R
1K#
0g#
17#
1=#
b1101110 +
1`#
b1 .
12
0C#
0E#
0J#
0L#
1f#
1h#
04#
0;#
0?#
1B#
1F#
0^#
0b#
03
1A#
1H#
0d#
19
1=
0M
12#
19#
0@#
1\#
10
14
08
1H
b1101 $
b1101 '
b1100011 #
b1100011 &
#3000
0-$
0A$
1*$
1?$
1C$
1:$
0#$
0($
01"
0=$
0;$
0+"
1!$
0h"
18$
13$
1("
1*"
b0 r"
0%#
1i"
06$
04$
1[
0!"
1,"
1&#
0f"
0^"
11$
1""
0\
1|
0a
0)"
0##
0w"
0;"
1_"
0/$
0u#
0]
0}
1U
1l
0v
0%"
b0 o"
0-
1<"
0\"
b0 7"
0T"
1v#
0y
0f
0m
1s
1'"
10"
15"
0L"
1V"
0s#
1{
0n#
1V
1j
0$"
0."
0F"
1M"
0S"
1q#
0x
1p#
0Z
0k
0|#
0_
0c
1%$
16"
bz00000000 4"
0J"
b1111000 !
b1111000 (
1,$
b1111 /
b111 W
1t
bz00010011 T
0p
0m#
1X
1i
1~#
1`
1d
0'$
0:"
1K"
1.$
1u
1q
1k#
0{#
1e
0g
1^
0b
1$$
18"
1I"
0+$
0r
0n
16#
1y#
b111 S
0"$
b111 3"
1)$
b0 R
08#
0F#
1D#
0K#
b1110111 +
1R#
b0 .
02
15#
0<#
0>#
1C#
1E#
1J#
1L#
0Q#
0S#
13
1;#
1?#
0B#
03#
1:#
0A#
0H#
1O#
01
15
09
0=
1A
09#
1@#
04
18
b10010 $
b10010 '
b1100101 #
b1100101 &
#4000
03$
0:$
1A$
14$
1;$
0?$
0C$
01$
08$
1=$
1/$
16$
1h"
1T"
b111 7"
1^"
0i"
0V"
0_"
0,$
1f"
1S"
1\"
1-$
1;"
1J"
bz00010011 4"
1L"
0*$
0<"
0K"
0M"
0&#
1($
11"
1##
1w"
b11111111 /
b1 o"
1-
b1 r"
1%#
1+"
00"
1'#
0("
1."
0$#
0[
1c
b0 q"
0t"
1\
0d
0,"
1u"
0U
1|#
1a
1)"
0s"
0{"
1f
0~#
bz11000011 T
1%"
b0 p"
0*
b10000100 !
b10000100 (
0%$
0e
0^
1{#
0&"
1h
1'$
0y#
1#"
1g
1b
0$$
0D#
b100 R
b1011 S
1"$
1F#
b100 .
1:
b1111011 +
1K#
0C#
0X#
0Z#
0_#
0a#
0;
0I#
0M#
1W#
1[#
1^#
1b#
1A#
1V#
1]#
19
1E
1I
1G#
0U#
0\#
1<
0D
0H
b1110110 $
b1110110 '
b1101 #
b1101 &
#5000
0|#
0;$
11#
1z#
1~#
18$
1?$
0.#
0x#
06$
0=$
0*#
04$
b101 W
0~
0^"
0h"
1+#
11$
1!"
1_"
1i"
0(#
0/$
1"
0|
0\"
0f"
b0 q"
0x"
b11011 /
b0 7"
0T"
b11 r"
1/#
0l
10"
0L"
0;"
1y"
1V"
00#
1m
0."
1%$
1M"
1<"
0v"
0z"
0S"
1-#
0V
bz01000001 T
0c
1u#
0'$
1,$
13$
1:$
06"
05"
b0 p"
0)
bz00000000 4"
0J"
b1111010 !
b1111010 (
0A$
b11 o"
1,
1Z
1d
0w#
1$$
0.$
15$
1<$
0/"
1:"
1F"
1H"
1K"
1C$
0m"
0Y
0g
0o
0b
1t#
0"$
1+$
02$
09$
1-"
08"
19"
1E"
0G"
0I"
1O"
1>"
0B"
1@$
1k"
b1 S
0r#
0K#
0)$
10$
17$
b1100 R
b110 3"
0>$
b1000 2"
0=#
1M#
0R#
0[#
1Y#
0b#
1`#
1>
b1100001 +
0g#
b10001100 .
1N
1<#
1>#
0J#
1Q#
1S#
1X#
1Z#
1_#
1a#
0f#
0?
0W#
0^#
0e#
1i#
0O
0:#
1H#
0O#
0V#
0]#
1d#
05
1=
0A
0E
0I
1M
1U#
1\#
1c#
1D
1H
1L
b10001100 $
b10001100 '
b11101101 #
b11101101 &
#6000
0,$
1A$
1*$
1.$
0?$
0C$
0($
01"
1=$
b100 7"
1h"
b10 r"
0%#
0j"
1&#
0v#
1A"
1g"
0##
0w"
1s#
0:$
bz01000000 4"
1c"
1V
1u#
b10 o"
0-
1n#
0q#
0E"
0>"
19$
1;$
0d"
0Z
1w#
b10001011 !
b10001011 (
03$
1/"
0o#
b100 W
0t
07$
1a"
1Y
1o
0t#
09"
0O"
12$
14$
0-"
1l#
1v
0`#
b1100 2"
b11 S
1r#
b0 3"
00$
b100 R
0j#
0s
1b#
1J
1=#
b11 +
0Y#
b11000100 .
0>
b10001000 /
0P
bz01000000 T
0j
05#
07#
1J#
0_#
0K
14#
18#
0;#
0?#
1I#
1W#
1[#
1?
1Q
1k
13#
0H#
1]#
11
0=
1I
02#
19#
0G#
0U#
00
14
0<
0D
0%
b11000101 $
b11000101 '
b11000110 #
b11000110 &
#7000
1|#
0z#
0~#
1x#
1~
1:$
0""
08$
0<$
0u#
1]
1}
16$
1"
0n"
1v#
1y
b110 7"
1^"
b10 r"
1/#
1l"
0s#
0{
0`"
00#
1C"
0A$
0V
1q#
1x
1="
1]"
1-#
0D"
1C$
1Z
0n#
06"
b11001110 /
b111 W
1t
bz01001100 T
1p
bz11001000 4"
1Y"
b10 o"
1,
1,$
1G"
1B"
0@$
0X
0i
1m#
1o#
1:"
b1011100 !
b1011100 (
03$
0u
0q
0Z"
1m"
0+$
0-$
1>$
b10 S
0k#
18"
09"
1I"
0O"
12$
14$
1r
1n
1W"
0k"
1)$
1g#
06#
b1001 3"
00$
b101 R
b110 2"
1R#
0i#
0N
17#
b10010010 +
0Y#
12
b1100101 .
1F
0<#
0>#
0Q#
0S#
0X#
1f#
1O
04#
1;#
1?#
0W#
1[#
03
0G
1:#
1O#
1V#
0d#
15
1A
1E
0M
12#
09#
1U#
10
04
1D
b1110111 $
b1110111 '
b11100101 #
b11100101 &
#8000
01$
1/$
1T"
0i"
0V"
0_"
0,$
1f"
1S"
1\"
1-$
1;"
1J"
1L"
0*$
0<"
0K"
0M"
1($
11"
b11 r"
1%#
1&$
1;$
0&#
0#$
08$
0?$
1##
1w"
1!$
16$
1=$
0'"
b11 o"
1-
15"
1e"
1n"
1*"
1^"
b111 7"
1h"
1$"
00"
0F"
0b"
0l"
1s#
1{
0,"
1`"
1j"
0|#
1A$
1_
0u#
1."
16"
0?"
0C"
0:$
0q#
0x
1a
1)"
0="
0]"
0A"
0g"
1n#
1~#
0C$
0`
1w#
1c
0%$
b10000001 !
b10000001 (
03$
0:"
1@"
1D"
1<$
b11111100 /
b110 W
0t
0p
bz11101000 T
1%"
0Y"
bz00010011 4"
0c"
0m#
0o#
0{#
1@$
1X
0Y
1e
1i
0o
1^
1t#
0d
1'$
02$
14$
19"
1E"
0G"
1O"
1>"
0B"
09$
1u
1q
0z
1&"
1Z"
1d"
0m"
1k#
1y#
0>$
0r#
1g
1b
0$$
10$
b111 3"
17$
0r
0n
1w
0#"
0W"
0a"
1k"
16#
1D#
0g#
0=#
b1101 S
1"$
1Y#
1`#
b10 R
b1000 2"
08#
0F#
1i#
02
0:
1N
1>#
b1111101 +
1K#
0Z#
0a#
16
0F
b10000010 .
0J
15#
1C#
0f#
13
1;
0O
0;#
0I#
0M#
1W#
1^#
07
1G
1K
03#
0A#
1d#
01
09
1M
19#
1G#
0U#
0\#
14
1<
0D
0H
b11110010 $
b11110010 '
b10001111 #
b10001111 &
#9000
1*$
0($
01"
b10 r"
0%#
1&#
0##
0w"
1%$
b10 o"
0-
0&$
10"
1#$
0."
0!$
0c
0*"
1d
1,"
18$
0a
0)"
1|#
06$
04$
0%"
0}#
0^"
11$
1'"
1z#
1_"
1i"
0/$
0$"
0x#
0\"
0f"
b100 7"
0T"
0_
b10000000 /
b0 W
0~
0L"
0;"
1V"
1`
1""
0j"
1M"
1<"
0S"
0:$
0]
0}
1A"
1g"
0,$
06"
05"
0J"
b10101101 !
b10101101 (
13$
1<$
bz00000000 T
0y
bz01000000 4"
1c"
1.$
1:"
1F"
1K"
15$
19$
1z
0d"
1+$
08"
19"
0E"
0I"
1O"
0>"
02$
07$
0w
1a"
0)$
b10 3"
10$
0`#
b0 R
b1100 2"
0R#
0[#
b101101 +
1Y#
1a#
06
b11000000 .
1J
05#
07#
1<#
0C#
0E#
1Q#
1S#
1X#
1Z#
14#
18#
1;#
1B#
1F#
0W#
0^#
17
0K
13#
0:#
1A#
0O#
0V#
11
05
19
0A
0E
02#
09#
0@#
1U#
1\#
00
04
08
1D
1H
b11000101 $
b11000101 '
b11101000 #
b11101000 &
#10000
01$
05$
1/$
1T"
0V"
1S"
1J"
0*$
0K"
1:$
0B$
0#$
0'$
1($
11"
08$
0<$
1?$
1!$
16$
0=$
0"
1n"
1*"
1%#
1^"
b11 7"
0h"
b1 r"
0/#
0l"
0,"
0&#
0`"
1j"
10#
1u#
0C"
1A$
1a
1)"
1##
1w"
1="
1]"
0A"
0g"
0-#
0s#
0w#
1%$
13$
1D"
1C$
0p#
0|#
06"
1%"
1-
1Y"
bz00001001 4"
0c"
b1 o"
0,
1n#
1q#
1$$
1&$
12$
14$
09"
1G"
0O"
1B"
0@$
1m#
0X
0e
0g
0i
0^
0b
1{#
1}#
1:"
b11101011 !
b11101011 (
0,$
0u
0&"
0/"
0Z"
1d"
1m"
1o#
b101 W
1t
0"$
00$
1>$
0k#
b0 S
0y#
18"
1I"
0+$
1-$
1r
1n
1#"
1-"
1W"
0a"
0k"
0l#
1v
0K#
0Y#
1g#
06#
0D#
b1001 3"
1)$
b1101 R
b10 2"
1j#
0s
1M#
1[#
0i#
1>
1F
0N
17#
1E#
b10010000 +
1R#
12
1:
b101101 .
0J
b1111011 /
1P
bz01000000 T
0j
0J#
0X#
1_#
1f#
0?
0G
1O
04#
0B#
0P#
0T#
1^#
03
0;
1K
0Q
1k
1H#
1V#
0]#
0d#
1=
1E
0I
0M
12#
1@#
1N#
0\#
10
18
1@
0H
1%
b101101 $
b101101 '
b10111101 #
b10111101 &
