Lab3/Basic/3-1/clock_divider.v
module clock_divider(clk, rst, sel, clk1_2, clk1_3, clk1_4, clk1_8, dclk);
    input clk;
    input rst;
    input [1:0] sel;
    output reg clk1_2, clk1_3, clk1_4, clk1_8;
    output reg dclk;
    reg counter_2 = 1'b0;
    reg [1:0] counter_3 = 2'b00;
    reg [1:0] counter_4 = 2'b00;
    reg [2:0] counter_8 = 3'b000;

    always @(posedge clk or negedge rst) begin
        if (!rst) begin
            clk1_2 <= 1'b1;
            clk1_3 <= 1'b1;
            clk1_4 <= 1'b1;
            clk1_8 <= 1'b1;
            counter_2 <= 1'b0;
            counter_3 <= 2'b00;
            counter_4 <= 2'b00;
            counter_8 <= 3'b000;
        end
        else begin
            if (counter_2 == 1'b1) begin
                clk1_2 <= 1;
                counter_2 <= 0;
            end
            else begin
                clk1_2 <= 0;
                counter_2 <= 1;
            end
            if (counter_3 == 2'b10) begin
                clk1_3 <= 1;
                counter_3 <= 2'b00;
            end
            else begin
                clk1_3 <= 0;
                counter_3 <= counter_3 + 1'b1;
            end
            if (counter_4 == 2'b11) begin
                clk1_4 <= 1;
                counter_4 <= 2'b00;
            end
            else begin
                clk1_4 <= 0;
                counter_4 <= counter_4 + 1'b1;
            end
            if (counter_8 == 3'b111) begin
                clk1_8 <= 1;
                counter_8 <= 3'b000;
            end
            else begin
                clk1_8 <= 0;
                counter_8 <= counter_8 + 1'b1;
            end
        end
    end
    always @(*) begin
        case (sel)
            2'b00: begin
                dclk = clk1_3;
            end
            2'b01: begin
                dclk = clk1_2;
            end
            2'b10: begin
                dclk = clk1_4;
            end
            2'b11: begin
                dclk = clk1_8;
            end
        endcase
    end
endmodule

Lab3/Basic/3-1/clock_divider_t.v
`timescale 1ns / 1ps
`include "clock_divider.v"
module clock_divider_t;
    reg clk;
    reg rst;
    reg [1:0] sel;
    wire clk1_2;
    wire clk1_3;
    wire clk1_4;
    wire clk1_8;
    wire dclk;

    clock_divider uut (
        .clk(clk),
        .rst(rst),
        .sel(sel),
        .clk1_2(clk1_2),
        .clk1_3(clk1_3),
        .clk1_4(clk1_4),
        .clk1_8(clk1_8),
        .dclk(dclk)
    );

    initial begin
        $dumpfile("clock_divider.vcd");
        $dumpvars(0, clock_divider_t);
        clk = 0;
        rst = 0;
        sel = 0;
        #10 rst = 1;
        #10 sel = 1;
        #10 sel = 0;
        #10 sel = 2;
        #10 sel = 3;
        #10 $finish;
    end

    always begin
        #2 clk = ~clk;
    end
endmodule

Lab3/Basic/3-1/clock_divider.vcd
$date
	Thu Oct 19 01:24:33 2023
$end
$version
	Icarus Verilog
$end
$timescale
	1ps
$end
$scope module clock_divider_t $end
$var wire 1 ! dclk $end
$var wire 1 " clk1_8 $end
$var wire 1 # clk1_4 $end
$var wire 1 $ clk1_3 $end
$var wire 1 % clk1_2 $end
$var reg 1 & clk $end
$var reg 1 ' rst $end
$var reg 2 ( sel [1:0] $end
$scope module uut $end
$var wire 1 & clk $end
$var wire 1 ' rst $end
$var wire 2 ) sel [1:0] $end
$var reg 1 % clk1_2 $end
$var reg 1 $ clk1_3 $end
$var reg 1 # clk1_4 $end
$var reg 1 " clk1_8 $end
$var reg 1 * counter_2 $end
$var reg 2 + counter_3 [1:0] $end
$var reg 2 , counter_4 [1:0] $end
$var reg 3 - counter_8 [2:0] $end
$var reg 1 ! dclk $end
$upscope $end
$upscope $end
$enddefinitions $end
#0
$dumpvars
b0 -
b0 ,
b0 +
0*
b0 )
b0 (
0'
0&
1%
1$
1#
1"
1!
$end
#2000
1&
#4000
0&
#6000
1&
#8000
0&
#10000
0!
b1 -
0"
b1 ,
0#
b1 +
0$
1*
0%
1&
1'
#12000
0&
#14000
b10 -
b10 ,
b10 +
0*
1%
1&
#16000
0&
#18000
1!
b11 -
b11 ,
b0 +
1$
1*
0%
1&
#20000
0!
0&
b1 (
b1 )
#22000
1!
b100 -
b0 ,
1#
b1 +
0$
0*
1%
1&
#24000
0&
#26000
0!
b101 -
b1 ,
0#
b10 +
1*
0%
1&
#28000
0&
#30000
1!
b110 -
b10 ,
b0 +
1$
0*
1%
1&
b0 (
b0 )
#32000
0&
#34000
0!
b111 -
b11 ,
b1 +
0$
1*
0%
1&
#36000
0&
#38000
b0 -
1"
b0 ,
1#
b10 +
0*
1%
1&
#40000
1!
0&
b10 (
b10 )
#42000
0!
b1 -
0"
b1 ,
0#
b0 +
1$
1*
0%
1&
#44000
0&
#46000
b10 -
b10 ,
b1 +
0$
0*
1%
1&
#48000
0&
#50000
b11 -
b11 ,
b10 +
1*
0%
1&
b11 (
b11 )
#52000
0&
#54000
b100 -
b0 ,
1#
b0 +
1$
0*
1%
1&
#56000
0&
#58000
b101 -
b1 ,
0#
b1 +
0$
1*
0%
1&
