Lab4/Advanced/4-3/Lab4_111062109_Built_In_Self_Test.v
`timescale 1ns/1ps

module Scan_DFF(clk, rst_n, scan_in, scan_en, data, out);
    input clk;
    input rst_n;
    input scan_in;
    input scan_en;
    input data;
    output reg out;


    always @(posedge clk) begin
        if(!rst_n) begin
            out <= 1'b0;
        end
        else begin
            if(scan_en) begin
                out <= scan_in;
            end
            else begin
                out <= data;
            end
        end
    end
endmodule

module Scan_Chain_Design(clk, rst_n, scan_in, scan_en, scan_out);
    input clk;
    input rst_n;
    input scan_in;
    input scan_en;
    output scan_out;

    
    wire [3:0] a, b;
    wire [7:0] p;
    assign p = a * b;

    Scan_DFF dff1(clk, rst_n, b[1], scan_en, p[0], b[0]);
    Scan_DFF dff2(clk, rst_n, b[2], scan_en, p[1], b[1]);
    Scan_DFF dff3(clk, rst_n, b[3], scan_en, p[2], b[2]);
    Scan_DFF dff4(clk, rst_n, a[0], scan_en, p[3], b[3]);
    Scan_DFF dff5(clk, rst_n, a[1], scan_en, p[4], a[0]);
    Scan_DFF dff6(clk, rst_n, a[2], scan_en, p[5], a[1]);
    Scan_DFF dff7(clk, rst_n, a[3], scan_en, p[6], a[2]);
    Scan_DFF dff8(clk, rst_n, scan_in, scan_en, p[7], a[3]);
    
    assign scan_out = b[0];

endmodule

module Many_To_One_LFSR(clk, rst_n, out);
    input clk;
    input rst_n;
    output out;
    reg [8-1:0] DFF;
    wire [8-1:0] next_DFF;
    always @(posedge clk) begin
        if(!rst_n) begin
            DFF <= 8'b10111101;
        end
        else begin
            DFF <= next_DFF;
        end
    end
    assign next_DFF = {DFF[6:0] , (DFF[7] ^ DFF[3]) ^ (DFF[1] ^ DFF[2])};
    assign out = DFF[7];
endmodule

module Built_In_Self_Test(clk, rst_n, scan_en, scan_in, scan_out);
    input clk;
    input rst_n;
    input scan_en;
    output scan_in;
    output scan_out;

    Many_To_One_LFSR MTOL(clk, rst_n, scan_in);
    Scan_Chain_Design SCD(clk, rst_n, scan_in, scan_en, scan_out);

endmodule

Lab4/Advanced/4-3/Lab4_111062109_Built_In_Self_Test_t.v
`timescale 1ns/1ps
`include "Lab4_111062109_Built_In_Self_Test.v"

module Built_In_Self_Test_t;
    reg clk;
    reg rst_n;
    reg scan_en;
    wire scan_in;
    wire scan_out;

    Built_In_Self_Test Built_In_Self_Test(clk, rst_n, scan_en, scan_in, scan_out);
    initial begin
        $dumpfile("Built_In_Self_Test_t.vcd");
        $dumpvars(0, Built_In_Self_Test_t);
        clk = 0;
        rst_n = 0;
        scan_en = 0;
        #10 rst_n = 1;
        scan_en = 1; 
        #80 scan_en = 0;
        #10 scan_en = 1;
        #80 scan_en = 0;
        #10 $finish;
    end

    always #5 clk = ~clk;
endmodule

Lab4/Advanced/4-3/Built_In_Self_Test_t.vcd
$date
	Mon Oct 30 17:59:52 2023
$end
$version
	Icarus Verilog
$end
$timescale
	1ps
$end
$scope module Built_In_Self_Test_t $end
$var wire 1 ! scan_out $end
$var wire 1 " scan_in $end
$var reg 1 # clk $end
$var reg 1 $ rst_n $end
$var reg 1 % scan_en $end
$scope module Built_In_Self_Test $end
$var wire 1 # clk $end
$var wire 1 $ rst_n $end
$var wire 1 % scan_en $end
$var wire 1 ! scan_out $end
$var wire 1 " scan_in $end
$scope module MTOL $end
$var wire 1 # clk $end
$var wire 1 $ rst_n $end
$var wire 1 " out $end
$var wire 8 & next_DFF [7:0] $end
$var reg 8 ' DFF [7:0] $end
$upscope $end
$scope module SCD $end
$var wire 1 # clk $end
$var wire 1 $ rst_n $end
$var wire 1 % scan_en $end
$var wire 1 " scan_in $end
$var wire 1 ! scan_out $end
$var wire 8 ( p [7:0] $end
$var wire 4 ) b [3:0] $end
$var wire 4 * a [3:0] $end
$scope module dff1 $end
$var wire 1 # clk $end
$var wire 1 + data $end
$var wire 1 $ rst_n $end
$var wire 1 % scan_en $end
$var wire 1 , scan_in $end
$var reg 1 - out $end
$upscope $end
$scope module dff2 $end
$var wire 1 # clk $end
$var wire 1 . data $end
$var wire 1 $ rst_n $end
$var wire 1 % scan_en $end
$var wire 1 / scan_in $end
$var reg 1 0 out $end
$upscope $end
$scope module dff3 $end
$var wire 1 # clk $end
$var wire 1 1 data $end
$var wire 1 $ rst_n $end
$var wire 1 % scan_en $end
$var wire 1 2 scan_in $end
$var reg 1 3 out $end
$upscope $end
$scope module dff4 $end
$var wire 1 # clk $end
$var wire 1 4 data $end
$var wire 1 $ rst_n $end
$var wire 1 % scan_en $end
$var wire 1 5 scan_in $end
$var reg 1 6 out $end
$upscope $end
$scope module dff5 $end
$var wire 1 # clk $end
$var wire 1 7 data $end
$var wire 1 $ rst_n $end
$var wire 1 % scan_en $end
$var wire 1 8 scan_in $end
$var reg 1 9 out $end
$upscope $end
$scope module dff6 $end
$var wire 1 # clk $end
$var wire 1 : data $end
$var wire 1 $ rst_n $end
$var wire 1 % scan_en $end
$var wire 1 ; scan_in $end
$var reg 1 < out $end
$upscope $end
$scope module dff7 $end
$var wire 1 # clk $end
$var wire 1 = data $end
$var wire 1 $ rst_n $end
$var wire 1 % scan_en $end
$var wire 1 > scan_in $end
$var reg 1 ? out $end
$upscope $end
$scope module dff8 $end
$var wire 1 # clk $end
$var wire 1 @ data $end
$var wire 1 $ rst_n $end
$var wire 1 % scan_en $end
$var wire 1 " scan_in $end
$var reg 1 A out $end
$upscope $end
$upscope $end
$upscope $end
$upscope $end
$enddefinitions $end
#0
$dumpvars
xA
x@
x?
x>
x=
x<
x;
x:
x9
x8
x7
x6
x5
x4
x3
x2
x1
x0
x/
x.
x-
x,
x+
bx *
bx )
bx (
bx '
bx &
0%
0$
0#
x"
x!
$end
#5000
b1111011 &
1"
0!
0+
0.
01
04
07
0:
0=
0@
0,
0/
02
05
08
0;
0>
b10111101 '
b0 (
0-
00
03
b0 )
06
09
0<
0?
b0 *
0A
1#
#10000
0#
1%
1$
#15000
1>
b11110110 &
0"
b1000 *
1A
b1111011 '
1#
#20000
0#
#25000
b11101101 &
1"
1;
0>
b11110110 '
1?
b100 *
0A
1#
#30000
0#
#35000
1>
0;
18
b11011011 &
1A
0?
b1010 *
1<
b11101101 '
1#
#40000
0#
#45000
b10110111 &
15
08
1;
b11011011 '
19
0<
b1101 *
1?
1#
#50000
0#
#55000
18
17
05
12
1:
1=
b1101111 &
1<
b1110 *
09
b1110000 (
b1000 )
16
b10110111 '
1#
#60000
0#
#65000
b11011111 &
0"
1/
11
02
0=
15
14
b1101111 '
13
b100 )
06
b111100 (
b1111 *
19
1#
#70000
0#
#75000
0>
07
12
04
0/
1,
1.
0:
1=
b10111110 &
1"
b111 *
0A
16
03
b1000110 (
b1010 )
10
b11011111 '
1#
#80000
0#
#85000
b1111100 &
1!
1+
0,
1/
0;
14
1>
0=
1@
b10111110 '
1-
00
b1101 )
13
0?
b10001111 (
b1011 *
1A
1#
#90000
0#
0%
#95000
08
01
1=
0@
05
0+
17
1,
0.
1:
b11111000 &
0"
0<
b1000 *
09
b1111000 (
b1111 )
10
b1111100 '
1#
#100000
0#
1%
#105000
b11110000 &
1"
02
1;
11
0>
0:
0=
b11111000 '
b111 )
06
1?
b11100 (
b100 *
0A
1#
#110000
0#
#115000
1>
0;
18
1.
0/
b11100001 &
1A
0?
b1010 *
1<
b11110 (
b11 )
03
b11110000 '
1#
#120000
0#
#125000
b11000011 &
0,
15
1+
08
0.
1;
07
b11100001 '
b1 )
00
19
0<
b1101 (
b1101 *
1?
1#
#130000
0#
#135000
18
17
05
12
1:
1=
0!
0+
01
04
b10000110 &
1<
b1110 *
09
16
b1110000 (
b1000 )
0-
b11000011 '
1#
#140000
0#
#145000
b1101 &
1/
11
02
0=
15
14
b10000110 '
13
b100 )
06
b111100 (
b1111 *
19
1#
#150000
0#
#155000
12
04
1@
0/
1,
1.
0:
b11010 &
0"
16
03
b10010110 (
b1010 )
10
b1101 '
1#
#160000
0#
#165000
b110100 &
1!
1+
14
0,
1/
01
0>
1=
0@
b11010 '
1-
00
b1101 )
13
b1011011 (
b111 *
0A
1#
#170000
0#
#175000
0;
0=
1,
07
1:
0!
0+
b1101001 &
b11 *
0?
10
b101010 (
b1110 )
0-
b110100 '
1#
#180000
0#
0%
#185000
b11010011 &
0/
04
05
0.
11
17
0:
b1101001 '
b1010 )
03
b10100 (
b10 *
09
1#
