Lab4/Basic/4-4/Lab4_One_To_Many_LFSR.v
`timescale 1ns/1ps

module One_TO_Many_LFSR(clk, rst_n, out);
    input clk;
    input rst_n;
    output reg [8-1:0] out;
    wire [8-1:0] next_DFF;

    always @(posedge clk) begin
        if(!rst_n) begin
            out <= 8'b10111101;
        end
        else begin
            out <= next_DFF;
        end
    end

    assign next_DFF = {out[6:4], out[7] ^ out[3], out[7] ^ out[2], out[7] ^ out[1], out[0], out[7]};
endmodule

Lab4/Basic/4-4/One_to_many_LFSR_t.v
`timescale 1ns/1ps
`include "Lab4_One_To_Many_LFSR.v"
module One_To_Many_LFSR_t;
reg clk = 0;
reg rst_n = 1;
wire [7:0] out;

// specify duration of a clock cycle.
parameter cyc = 10;

// generate clock.
always#(cyc/2)clk = !clk;

One_TO_Many_LFSR one2mlfsr(
    .clk(clk),
    .rst_n(rst_n),
    .out(out)
);

// uncommment and add "+access+r" to your nverilog command to dump fsdb waveform on NTHUCAD
// initial begin
//     $fsdbDumpfile("One_To_Many_LFSR.fsdb");
//     $fsdbDumpvars;
// end

initial begin
    $dumpfile("One_To_Many_LFSR.vcd");
    $dumpvars(0, One_To_Many_LFSR_t);
    @(negedge clk)
    rst_n = 1'b0;
    @(negedge clk)
    rst_n = 1'b1;
    #(cyc * 16)
    $finish;
end
endmodule

Lab4/Basic/4-4/One_to_many_LFSR.vcd
$date
	Thu Oct 26 16:14:18 2023
$end
$version
	Icarus Verilog
$end
$timescale
	1ps
$end
$scope module One_To_Many_LFSR_t $end
$var wire 8 ! out [7:0] $end
$var reg 1 " clk $end
$var reg 1 # rst_n $end
$scope module one2mlfsr $end
$var wire 1 " clk $end
$var wire 1 # rst_n $end
$var wire 8 $ next_DFF [7:0] $end
$var reg 8 % out [7:0] $end
$upscope $end
$upscope $end
$enddefinitions $end
#0
$dumpvars
bx %
bx $
1#
0"
bx !
$end
#5000
1"
#10000
0#
0"
#15000
b1100111 $
b10111101 !
b10111101 %
1"
#20000
1#
0"
#25000
b11001110 $
b1100111 !
b1100111 %
1"
#30000
0"
#35000
b10000001 $
b11001110 !
b11001110 %
1"
#40000
0"
#45000
b11111 $
b10000001 !
b10000001 %
1"
#50000
0"
#55000
b111110 $
b11111 !
b11111 %
1"
#60000
0"
#65000
b1111100 $
b111110 !
b111110 %
1"
#70000
0"
#75000
b11111000 $
b1111100 !
b1111100 %
1"
#80000
0"
#85000
b11101101 $
b11111000 !
b11111000 %
1"
#90000
0"
#95000
b11000111 $
b11101101 !
b11101101 %
1"
#100000
0"
#105000
b10010011 $
b11000111 !
b11000111 %
1"
#110000
0"
#115000
b111011 $
b10010011 !
b10010011 %
1"
#120000
0"
#125000
b1110110 $
b111011 !
b111011 %
1"
#130000
0"
#135000
b11101100 $
b1110110 !
b1110110 %
1"
#140000
0"
#145000
b11000101 $
b11101100 !
b11101100 %
1"
#150000
0"
#155000
b10010111 $
b11000101 !
b11000101 %
1"
#160000
0"
#165000
b110011 $
b10010111 !
b10010111 %
1"
#170000
0"
#175000
b1100110 $
b110011 !
b110011 %
1"
