Lab2/Basic/2-3/Lab2_Adders.v
`timescale 1ns/1ps
module AND(out, a, b);
    input a, b;
    output out;
    wire temp;
    nand n1 (temp, a, b);
    nand n2 (out, temp, temp);
endmodule

module OR(out, a, b);
    input a, b;
    output out;
    wire temp1, temp2;
    nand n1 (temp1, a, a);
    nand n2 (temp2, b, b);
    nand n3 (out, temp1, temp2);
endmodule

module XOR(out, a, b);
    input a, b;
    output out;
    wire temp1, temp2, na, nb;
    nand n1 (na, a, a);
    nand n2 (nb, b, b);
    nand n3 (temp1, na, b);
    nand n4 (temp2, nb, a);
    nand n5 (out, temp1, temp2);
endmodule

module Majority(a, b, c, out);
input a, b, c;
output out;
wire temp1, temp2, temp3, temp4, temp5, temp6;
AND A1 (temp1, a, b);
AND A2 (temp2, a, c);
AND A3 (temp3, b, c);
OR O1 (temp4, temp1, temp2);
OR O2 (out, temp4, temp3);
endmodule

module Half_Adder(a, b, cout, sum);
input a, b;
output cout, sum;

XOR X1 (sum, a, b);
AND A1 (cout, a, b);
endmodule

module Full_Adder (a, b, cin, cout, sum);
input a, b, cin;
output cout, sum;
wire temp1;
Majority M1 (a, b, cin, cout);
XOR X1 (temp1, a, b);
XOR X2 (sum, temp1, cin);
endmodule

Lab2/Basic/2-3/Adders_t.v
`timescale 1ns/1ps
`include "Lab2_Adders.v"
module Adders_t;
reg a = 1'b0;
reg b = 1'b0;
reg cin = 1'b0;
wire ha_sum, ha_cout;
wire fa_sum, fa_cout;

Half_Adder ha(
    .a (a),
    .b (b),
    .cout (ha_cout),
    .sum (ha_sum)
);

Full_Adder fa(
    .a (a),
    .b (b),
    .cin (cin),
    .cout (fa_cout),
    .sum (fa_sum)
);

// uncommment and add "+access+r" to your nverilog command to dump fsdb waveform on NTHUCAD
// initial begin
//      $fsdbDumpfile("Adders.fsdb");
//      $fsdbDumpvars;
// end

initial begin
    $dumpfile("Adders.vcd");
    $dumpvars(0, Adders_t);
    repeat (2 ** 3) begin
        #1 {a, b, cin} = {a, b, cin} + 1'b1;
    end
    #1 $finish;
end
endmodule

Lab2/Basic/2-3/2-3.sim/sim_1/behav/xsim/Adders.vcd
$date
   Thu Oct 12 15:23:40 2023
$end
$version
  2020.2
$end
$timescale
  1ps
$end
$scope module Adders_t $end
$var reg 1 ! a $end
$var reg 1 " b $end
$var reg 1 # cin $end
$var wire 1 $ ha_sum $end
$var wire 1 % ha_cout $end
$var wire 1 & fa_sum $end
$var wire 1 ' fa_cout $end
$scope module ha $end
$var wire 1 ( a $end
$var wire 1 ) b $end
$var wire 1 % cout $end
$var wire 1 $ sum $end
$scope module X1 $end
$var wire 1 ( a $end
$var wire 1 ) b $end
$var wire 1 $ out $end
$var wire 1 * temp1 $end
$var wire 1 + temp2 $end
$var wire 1 , na $end
$var wire 1 - nb $end
$upscope $end
$scope module A1 $end
$var wire 1 ( a $end
$var wire 1 ) b $end
$var wire 1 % out $end
$var wire 1 . temp $end
$upscope $end
$upscope $end
$scope module fa $end
$var wire 1 / a $end
$var wire 1 0 b $end
$var wire 1 1 cin $end
$var wire 1 ' cout $end
$var wire 1 & sum $end
$var wire 1 2 temp1 $end
$scope module M1 $end
$var wire 1 / a $end
$var wire 1 0 b $end
$var wire 1 1 c $end
$var wire 1 ' out $end
$var wire 1 3 temp1 $end
$var wire 1 4 temp2 $end
$var wire 1 5 temp3 $end
$var wire 1 6 temp4 $end
$var wire 1 7 temp5 $end
$var wire 1 8 temp6 $end
$scope module A1 $end
$var wire 1 / a $end
$var wire 1 0 b $end
$var wire 1 3 out $end
$var wire 1 9 temp $end
$upscope $end
$scope module A2 $end
$var wire 1 / a $end
$var wire 1 1 b $end
$var wire 1 4 out $end
$var wire 1 : temp $end
$upscope $end
$scope module A3 $end
$var wire 1 0 a $end
$var wire 1 1 b $end
$var wire 1 5 out $end
$var wire 1 ; temp $end
$upscope $end
$scope module O1 $end
$var wire 1 3 a $end
$var wire 1 4 b $end
$var wire 1 6 out $end
$var wire 1 < temp1 $end
$var wire 1 = temp2 $end
$upscope $end
$scope module O2 $end
$var wire 1 6 a $end
$var wire 1 5 b $end
$var wire 1 ' out $end
$var wire 1 > temp1 $end
$var wire 1 ? temp2 $end
$upscope $end
$upscope $end
$scope module X1 $end
$var wire 1 / a $end
$var wire 1 0 b $end
$var wire 1 2 out $end
$var wire 1 @ temp1 $end
$var wire 1 A temp2 $end
$var wire 1 B na $end
$var wire 1 C nb $end
$upscope $end
$scope module X2 $end
$var wire 1 2 a $end
$var wire 1 1 b $end
$var wire 1 & out $end
$var wire 1 D temp1 $end
$var wire 1 E temp2 $end
$var wire 1 F na $end
$var wire 1 G nb $end
$upscope $end
$upscope $end
$upscope $end
$enddefinitions $end
#0
$dumpvars
0!
0"
0#
0$
0%
0&
0'
0(
0)
1*
1+
1,
1-
1.
0/
00
01
02
03
04
05
06
z7
z8
19
1:
1;
1<
1=
1>
1?
1@
1A
1B
1C
1D
1E
1F
1G
$end
#1000
0!
1#
1&
11
1:
1;
0D
1E
0G
#2000
0!
1"
0#
1$
1)
0*
1+
0-
1.
10
01
12
19
1:
1;
0@
1A
0C
1D
0E
0F
1G
#3000
0!
1"
1#
0&
1'
11
15
1:
0;
0?
1D
1E
0G
#4000
1!
0"
0#
1&
0'
1(
0)
1*
0+
0,
1-
1.
1/
00
01
12
05
19
1:
1;
1?
1@
0A
0B
1C
1D
0E
1G
#5000
1!
0"
1#
0&
1'
11
14
16
0:
1;
0=
0>
1D
1E
0G
#6000
1!
1"
0#
0$
1%
0&
1)
1*
1+
0-
0.
10
01
02
13
04
16
09
1:
1;
0<
1=
1@
1A
0C
1D
1E
1F
1G
#7000
1!
1"
1#
1&
11
14
15
16
0:
0;
0=
0?
0D
1E
0G
#8000
0!
0"
0#
0%
0&
0'
0(
0)
1*
1+
1,
1-
1.
0/
00
01
03
04
05
06
19
1:
1;
1<
1=
1>
1?
1@
1A
1B
1C
1D
1E
1G
