Lab3/Advanced/3-5FPGA/Lab3_111062109_Parameterized_Ping_Pong_Counter_fpga.v
module clock_divider1(clk, rst, clk_out);
    input clk;
    input rst;
    output clk_out;
    reg [27-1:0] counter;

    always @(posedge clk) begin
        if(rst)  counter <= 0;
        else counter <= counter + 1;
    end
    assign clk_out = (~counter == 27'd0) ? 1:0;
endmodule

module clock_divider2(clk, rst, clk_out);
    input clk;
    input rst;
    output clk_out;
    reg [16-1:0] counter;

    always @(posedge clk) begin
        if(rst)  counter <= 0;
        else counter <= counter + 1;
    end
    assign clk_out = (~counter == 16'd0) ? 1:0;
endmodule

module debounce(clk, button, button_debounced);
    input clk;
    input button;
    output button_debounced;
    reg [15:0] counter;
    always @(posedge clk) begin
        counter[15:1] <= counter[14:0];
        counter[0] <= button;
    end
    assign button_debounced = (counter == ~16'd0) ? 1:0;
endmodule

module one_pulse(clk, signal, pulse);
    input clk;
    input signal;
    output reg pulse;
    reg A;
    always @(negedge clk) begin
        A <= signal;
        pulse <= signal & ~A;
    end
endmodule

module seven_segment(clk, num, direction, AN, out);
    input clk;
    input direction;
    input [4-1:0] num;
    output [4-1:0] AN;
    output [7-1:0] out;
    reg [7-1:0] out;
    reg [1:0] counter = 0;
    reg [4-1:0] AN;

    always @(posedge clk) begin
        counter <= counter + 1;
    end

    always @(*)begin
        case (counter)
        2'b00: begin
            AN = 4'b1110;
            if(direction == 1'b1) out = 7'b1011100;
            else out = 7'b1100011;
        end
        2'b01: begin
            AN = 4'b1101;
            if(direction == 1'b1) out = 7'b1011100;
            else out = 7'b1100011;
        end
        2'b10: begin
            AN = 4'b1011;
            case (num)
            4'b0000: out = 7'b1000000;
            4'b0001: out = 7'b1111001;
            4'b0010: out = 7'b0100100;
            4'b0011: out = 7'b0110000;
            4'b0100: out = 7'b0011001;
            4'b0101: out = 7'b0010010;
            4'b0110: out = 7'b0000010;
            4'b0111: out = 7'b1111000;
            4'b1000: out = 7'b0000000;
            4'b1001: out = 7'b0010000;
            4'b1010: out = 7'b1000000;
            4'b1011: out = 7'b1111001;
            4'b1100: out = 7'b0100100;
            4'b1101: out = 7'b0110000;
            4'b1110: out = 7'b0011001;
            4'b1111: out = 7'b0010010;
            endcase
        end
        2'b11: begin
            AN = 4'b0111;
            if(num > 4'b1001) out = 7'b1111001;
            else out = 7'b1000000;
        end
        endcase
    end
endmodule

module Parameterized_Ping_Pong_Counter_FPGA (clk, rst_n, enable, flip, max, min, AN, segs);
    input clk, rst_n;
    input enable;
    input flip;
    input [4-1:0] max;
    input [4-1:0] min;
    output [4-1:0] AN;
    output [7-1:0] segs;

    reg direction;
    reg [4-1:0] out;
    wire _enable;
    wire clk_s, clk_seg;
    wire rst_debounced, rst_enable;
    wire flip_debounced, flip_enable;
    clock_divider1 cd1( .clk(clk), .rst(rst_enable), .clk_out(clk_s));
    clock_divider2 cd2( .clk(clk), .rst(rst_enable), .clk_out(clk_seg));
    debounce db(.clk(clk), .button(rst_n), .button_debounced(rst_debounced));
    debounce db2(.clk(clk), .button(flip), .button_debounced(flip_debounced));
    one_pulse op(.clk(clk), .signal(rst_debounced), .pulse(rst_enable));
    one_pulse op2(.clk(clk), .signal(flip_debounced), .pulse(flip_enable));
    seven_segment ss(.clk(clk_seg), .num(out), .direction(direction), .AN(AN), .out(segs));
    assign _enable = enable && !(out > max || out < min || (out == max && out == min));
    always @(posedge clk) begin
        if(rst_enable)begin
            out <= min;
            direction <= 1;
        end
        else if(_enable && clk_s) begin
            if(out===max) begin
                out <= out - 1;
                direction <= 1'b0;
            end
            else if(out===min) begin
                out <= out + 1;
                direction <= 1'b1;
            end
            else if(flip_enable) begin
                out <= (direction) ? out - 1 : out + 1;
                direction <= ~direction;
            end
            else begin
                out <= (direction) ? out + 1 : out - 1;
            end
        end
        else if(flip_enable && _enable) begin
            direction <= ~direction;
        end
    end
endmodule

Lab3/Advanced/3-5FPGA/Lab3_111062109_Parameterized_Ping_Pong_Counter_fpga_t.v
`timescale 1ns/1ps
`include "Lab3_111062109_Parameterized_Ping_Pong_Counter_fpga.v" 

module Parameterized_Ping_Pong_Counter_t;
reg clk;
reg rst_n;
reg enable;
reg flip;
reg [4-1:0] max;
reg [4-1:0] min;
wire [4-1:0] AN;
wire [7-1:0] segs;

Parameterized_Ping_Pong_Counter_FPGA uut (
    .clk(clk), 
    .rst_n(rst_n), 
    .enable(enable), 
    .flip(flip), 
    .max(max), 
    .min(min), 
    .AN(AN),
    .segs(segs)
);

initial begin
    $dumpfile("Parameterized_Ping_Pong_Counter.vcd");
    $dumpvars(0, Parameterized_Ping_Pong_Counter_t);
    rst_n = 0;
    clk = 0;
    enable = 1;
    flip = 0;
    max = 4;
    min = 0;
    #100 rst_n = 1;
    #900 rst_n = 0;
    $finish;
    #200 rst_n = 1;
    #300 flip = 1;
    #100 flip = 0;
    #500 rst_n = 0;
    #10;
   
    /*
    #200 rst_n = 1;
    #300 flip = 1;
    #100 flip = 0;
    #100 flip = 1;
    #100 flip = 0;
    #300 rst_n = 0;
    
    #200 rst_n = 1;
    max = 3;
    #500 flip = 1;
    min = 1;
    #100 flip = 0;
    min = 3;
    #200 min = 2; max = 2;
    #300 min = 1; max = 3;
    #300 rst_n = 0;
    $finish;
    */
end

always #5 clk = ~clk;

endmodule

Lab3/Advanced/3-5FPGA/Parameterized_Ping_Pong_Counter.vcd
$date
	Tue Oct 24 13:25:07 2023
$end
$version
	Icarus Verilog
$end
$timescale
	1ps
$end
$scope module Parameterized_Ping_Pong_Counter_t $end
$var wire 7 ! segs [6:0] $end
$var wire 4 " AN [3:0] $end
$var reg 1 # clk $end
$var reg 1 $ enable $end
$var reg 1 % flip $end
$var reg 4 & max [3:0] $end
$var reg 4 ' min [3:0] $end
$var reg 1 ( rst_n $end
$scope module uut $end
$var wire 1 ) _enable $end
$var wire 1 # clk $end
$var wire 1 $ enable $end
$var wire 1 % flip $end
$var wire 4 * max [3:0] $end
$var wire 4 + min [3:0] $end
$var wire 1 ( rst_n $end
$var wire 7 , segs [6:0] $end
$var wire 1 - rst_enable $end
$var wire 1 . rst_debounced $end
$var wire 1 / flip_enable $end
$var wire 1 0 flip_debounced $end
$var wire 1 1 clk_seg $end
$var wire 1 2 clk_s $end
$var wire 4 3 AN [3:0] $end
$var reg 1 4 direction $end
$var reg 4 5 out [3:0] $end
$scope module cd1 $end
$var wire 1 # clk $end
$var wire 1 - rst $end
$var wire 1 2 clk_out $end
$var reg 27 6 counter [26:0] $end
$upscope $end
$scope module cd2 $end
$var wire 1 # clk $end
$var wire 1 - rst $end
$var wire 1 1 clk_out $end
$var reg 16 7 counter [15:0] $end
$upscope $end
$scope module db $end
$var wire 1 ( button $end
$var wire 1 # clk $end
$var wire 1 . button_debounced $end
$var reg 16 8 counter [15:0] $end
$upscope $end
$scope module db2 $end
$var wire 1 % button $end
$var wire 1 # clk $end
$var wire 1 0 button_debounced $end
$var reg 16 9 counter [15:0] $end
$upscope $end
$scope module op $end
$var wire 1 # clk $end
$var wire 1 . signal $end
$var reg 1 : A $end
$var reg 1 - pulse $end
$upscope $end
$scope module op2 $end
$var wire 1 # clk $end
$var wire 1 0 signal $end
$var reg 1 ; A $end
$var reg 1 / pulse $end
$upscope $end
$scope module ss $end
$var wire 1 1 clk $end
$var wire 1 4 direction $end
$var wire 4 < num [3:0] $end
$var reg 4 = AN [3:0] $end
$var reg 2 > counter [1:0] $end
$var reg 7 ? out [6:0] $end
$upscope $end
$upscope $end
$upscope $end
$enddefinitions $end
#0
$dumpvars
b1100011 ?
b0 >
b1110 =
bx <
z;
z:
bx 9
bx 8
bx 7
bx 6
bx 5
x4
b1110 3
x2
x1
x0
x/
x.
x-
b1100011 ,
b0 +
b100 *
x)
0(
b0 '
b100 &
0%
1$
0#
b1110 "
b1100011 !
$end
#5000
0.
00
bx0 8
bx0 9
1#
#10000
0/
0;
0-
0:
0#
#15000
bx00 9
bx00 8
1#
#20000
0#
#25000
bx000 8
bx000 9
1#
#30000
0#
#35000
bx0000 9
bx0000 8
1#
#40000
0#
#45000
bx00000 8
bx00000 9
1#
#50000
0#
#55000
bx000000 9
bx000000 8
1#
#60000
0#
#65000
bx0000000 8
bx0000000 9
1#
#70000
0#
#75000
bx00000000 9
bx00000000 8
1#
#80000
0#
#85000
bx000000000 8
bx000000000 9
1#
#90000
0#
#95000
bx0000000000 9
bx0000000000 8
1#
#100000
0#
1(
#105000
bx00000000001 8
bx00000000000 9
1#
#110000
0#
#115000
bx000000000000 9
bx000000000011 8
1#
#120000
0#
#125000
bx0000000000111 8
bx0000000000000 9
1#
#130000
0#
#135000
bx00000000000000 9
bx00000000001111 8
1#
#140000
0#
#145000
bx000000000011111 8
bx000000000000000 9
1#
#150000
0#
#155000
b0 9
b111111 8
1#
#160000
0#
#165000
b1111111 8
1#
#170000
0#
#175000
b11111111 8
1#
#180000
0#
#185000
b111111111 8
1#
#190000
0#
#195000
b1111111111 8
1#
#200000
0#
#205000
b11111111111 8
1#
#210000
0#
#215000
b111111111111 8
1#
#220000
0#
#225000
b1111111111111 8
1#
#230000
0#
#235000
b11111111111111 8
1#
#240000
0#
#245000
b111111111111111 8
1#
#250000
0#
#255000
1.
b1111111111111111 8
1#
#260000
1-
1:
0#
#265000
02
01
1)
b1011100 !
b1011100 ,
b1011100 ?
b0 6
b0 7
14
b0 5
b0 <
1#
#270000
0-
0#
#275000
b1 7
b1 6
1#
#280000
0#
#285000
b10 6
b10 7
1#
#290000
0#
#295000
b11 7
b11 6
1#
#300000
0#
#305000
b100 6
b100 7
1#
#310000
0#
#315000
b101 7
b101 6
1#
#320000
0#
#325000
b110 6
b110 7
1#
#330000
0#
#335000
b111 7
b111 6
1#
#340000
0#
#345000
b1000 6
b1000 7
1#
#350000
0#
#355000
b1001 7
b1001 6
1#
#360000
0#
#365000
b1010 6
b1010 7
1#
#370000
0#
#375000
b1011 7
b1011 6
1#
#380000
0#
#385000
b1100 6
b1100 7
1#
#390000
0#
#395000
b1101 7
b1101 6
1#
#400000
0#
#405000
b1110 6
b1110 7
1#
#410000
0#
#415000
b1111 7
b1111 6
1#
#420000
0#
#425000
b10000 6
b10000 7
1#
#430000
0#
#435000
b10001 7
b10001 6
1#
#440000
0#
#445000
b10010 6
b10010 7
1#
#450000
0#
#455000
b10011 7
b10011 6
1#
#460000
0#
#465000
b10100 6
b10100 7
1#
#470000
0#
#475000
b10101 7
b10101 6
1#
#480000
0#
#485000
b10110 6
b10110 7
1#
#490000
0#
#495000
b10111 7
b10111 6
1#
#500000
0#
#505000
b11000 6
b11000 7
1#
#510000
0#
#515000
b11001 7
b11001 6
1#
#520000
0#
#525000
b11010 6
b11010 7
1#
#530000
0#
#535000
b11011 7
b11011 6
1#
#540000
0#
#545000
b11100 6
b11100 7
1#
#550000
0#
#555000
b11101 7
b11101 6
1#
#560000
0#
#565000
b11110 6
b11110 7
1#
#570000
0#
#575000
b11111 7
b11111 6
1#
#580000
0#
#585000
b100000 6
b100000 7
1#
#590000
0#
#595000
b100001 7
b100001 6
1#
#600000
0#
#605000
b100010 6
b100010 7
1#
#610000
0#
#615000
b100011 7
b100011 6
1#
#620000
0#
#625000
b100100 6
b100100 7
1#
#630000
0#
#635000
b100101 7
b100101 6
1#
#640000
0#
#645000
b100110 6
b100110 7
1#
#650000
0#
#655000
b100111 7
b100111 6
1#
#660000
0#
#665000
b101000 6
b101000 7
1#
#670000
0#
#675000
b101001 7
b101001 6
1#
#680000
0#
#685000
b101010 6
b101010 7
1#
#690000
0#
#695000
b101011 7
b101011 6
1#
#700000
0#
#705000
b101100 6
b101100 7
1#
#710000
0#
#715000
b101101 7
b101101 6
1#
#720000
0#
#725000
b101110 6
b101110 7
1#
#730000
0#
#735000
b101111 7
b101111 6
1#
#740000
0#
#745000
b110000 6
b110000 7
1#
#750000
0#
#755000
b110001 7
b110001 6
1#
#760000
0#
#765000
b110010 6
b110010 7
1#
#770000
0#
#775000
b110011 7
b110011 6
1#
#780000
0#
#785000
b110100 6
b110100 7
1#
#790000
0#
#795000
b110101 7
b110101 6
1#
#800000
0#
#805000
b110110 6
b110110 7
1#
#810000
0#
#815000
b110111 7
b110111 6
1#
#820000
0#
#825000
b111000 6
b111000 7
1#
#830000
0#
#835000
b111001 7
b111001 6
1#
#840000
0#
#845000
b111010 6
b111010 7
1#
#850000
0#
#855000
b111011 7
b111011 6
1#
#860000
0#
#865000
b111100 6
b111100 7
1#
#870000
0#
#875000
b111101 7
b111101 6
1#
#880000
0#
#885000
b111110 6
b111110 7
1#
#890000
0#
#895000
b111111 7
b111111 6
1#
#900000
0#
#905000
b1000000 6
b1000000 7
1#
#910000
0#
#915000
b1000001 7
b1000001 6
1#
#920000
0#
#925000
b1000010 6
b1000010 7
1#
#930000
0#
#935000
b1000011 7
b1000011 6
1#
#940000
0#
#945000
b1000100 6
b1000100 7
1#
#950000
0#
#955000
b1000101 7
b1000101 6
1#
#960000
0#
#965000
b1000110 6
b1000110 7
1#
#970000
0#
#975000
b1000111 7
b1000111 6
1#
#980000
0#
#985000
b1001000 6
b1001000 7
1#
#990000
0#
#995000
b1001001 7
b1001001 6
1#
#1000000
0#
0(
