Lab4/Basic/4-2/Lab4_Mealy.v
`timescale 1ns/1ps

module Mealy (clk, rst_n, in, out, state);
    input clk, rst_n;
    input in;
    output out;
    output [3-1:0] state;

    reg out;
    reg [3-1:0] state;
    reg [3-1:0] next_state;

    parameter S0 = 3'b000;
    parameter S1 = 3'b001;
    parameter S2 = 3'b010;
    parameter S3 = 3'b011;
    parameter S4 = 3'b100;
    parameter S5 = 3'b101;
    always @(posedge clk) begin
        if(!rst_n) begin
            state <= S0;
        end
        else begin
            state <= next_state;
        end
    end
    
    always @(*) begin
        case (state)
            S0: begin
                if(in) begin
                    next_state = S2;
                    out = 1;
                end
                else begin
                    next_state = S0;
                    out = 0;
                end
            end
            S1: begin
                out = 1;
                if(in) next_state = S4; 
                else next_state = S0;
            end
            S2: begin
                if(in) begin
                    next_state = S1;
                    out = 0;
                end
                else begin
                    next_state = S5;
                    out = 1;
                end
            end
            S3: begin
                if(in) begin
                    next_state = S2;
                    out = 0;
                end
                else begin
                    next_state = S3;
                    out = 1;
                end
            end
            S4: begin
                out = 1;
                if(in) next_state = S4;
                else next_state = S2;
            end
            S5: begin
                out = 0;
                if(in) next_state = S4;
                else next_state = S3;
            end
        endcase
    end
endmodule

Lab4/Basic/4-2/Mealy_t.v
`timescale 1ns/1ps
`include "Lab4_Mealy.v"

module Mealy_t;
reg clk = 1'b1;
reg rst_n = 1'b1;
reg in = 1'b0;
wire out;
wire [2:0] state;

// specify duration of a clock cycle.
parameter cyc = 10;

// generate clock.
always #(cyc/2) clk = ~clk;

Mealy m (
    .clk (clk),
    .rst_n (rst_n),
    .in (in),
    .out (out),
    .state (state)
);

// uncommment and add "+access+r" to your nverilog command to dump fsdb waveform on NTHUCAD
// initial begin
//     $fsdbDumpfile("Mealy.fsdb");
//     $fsdbDumpvars;
// end

initial begin
    $dumpfile("Mealy.vcd");
    $dumpvars(0, Mealy_t);
    @ (negedge clk) rst_n = 1'b0;
    @ (posedge clk) // reset to S0
    @ (negedge clk) rst_n = 1'b1;
    @ (posedge clk) // S0 -0-> S0
    @ (negedge clk) in = 1'b1;
    @ (posedge clk) // S0 -1-> S2
    @ (negedge clk) in = 1'b0;
    @ (posedge clk) // S2 -0-> S5
    @ (negedge clk) in = 1'b1;
    @ (posedge clk) // S5 -1-> S4
    @ (posedge clk) // S4 -1-> S4
    @ (negedge clk) in = 1'b0;
    @ (posedge clk) // S4 -1-> S2
    @ (posedge clk) // S2 -0-> S5
    @ (negedge clk) in = 1'b0;
    @ (posedge clk) // S5-0->S3
    @ (posedge clk) // S3-0->S3
    @ (negedge clk) in = 1'b1;
    @ (posedge clk) // S3-1->S2
    @ (posedge clk) // S2-1->S1
    @ (negedge clk) $finish;
end

endmodule

Lab4/Basic/4-2/Mealy.vcd
$date
	Thu Oct 26 16:03:15 2023
$end
$version
	Icarus Verilog
$end
$timescale
	1ps
$end
$scope module Mealy_t $end
$var wire 3 ! state [2:0] $end
$var wire 1 " out $end
$var reg 1 # clk $end
$var reg 1 $ in $end
$var reg 1 % rst_n $end
$scope module m $end
$var wire 1 # clk $end
$var wire 1 $ in $end
$var wire 1 % rst_n $end
$var reg 3 & next_state [2:0] $end
$var reg 1 " out $end
$var reg 3 ' state [2:0] $end
$upscope $end
$upscope $end
$enddefinitions $end
#0
$dumpvars
bx '
bx &
1%
0$
1#
x"
bx !
$end
#5000
0%
0#
#10000
0"
b0 &
b0 !
b0 '
1#
#15000
1%
0#
#20000
1#
#25000
1"
b10 &
1$
0#
#30000
0"
b1 &
b10 !
b10 '
1#
#35000
1"
b101 &
0$
0#
#40000
b11 &
0"
b101 !
b101 '
1#
#45000
b100 &
1$
0#
#50000
1"
b100 !
b100 '
1#
#55000
0#
#60000
1#
#65000
b10 &
0$
0#
#70000
b101 &
b10 !
b10 '
1#
#75000
0#
#80000
b11 &
0"
b101 !
b101 '
1#
#85000
0#
#90000
1"
b11 !
b11 '
1#
#95000
0#
#100000
1#
#105000
0"
b10 &
1$
0#
#110000
b1 &
b10 !
b10 '
1#
#115000
0#
#120000
b100 &
1"
b1 !
b1 '
1#
